Workbook

Sheet Cover Sheet
A1: NILE Platform — Production Support
A2: Monthly Issue Report · April 2026 · Auto-generated
A5: Total Issues | C5: Spooler issue | E5: Configuration Issue | G5: Needs Review
A6: =COUNTIF('Raw Tickets'!$V$3:$V$10000,"<>") | C6: 31 | E6: 29 | G6: =TEXT(IF(COUNTIF('Raw Tickets'!$V$3:$V$10000,"<>")>0,COUNTIF('Raw Tickets'!$V$3:$V$10000,"Other")/COUNTIF('Raw Tickets'!$V$3:$V$10000,"<>"),0),"0.0%")
A9: ✓ Health Status: Categorization rate is healthy. Top issue this month: Spooler issue (31). Total issues tracked: 236.
A12: Category | B12: Count | C12: % Share | D12: vs Last Month | E12: Trend Bar
A13: Configuration Issue | B13: 29 | C13: 12.3% | D13: ▲ +7 | E13: █████████
A14: File Issue | B14: 28 | C14: 11.9% | D14: ▲ +4 | E14: ████████
A15: Spooler issue | B15: 31 | C15: 13.1% | D15: ▲ +8 | E15: █████████
A16: Data Issue | B16: 16 | C16: 6.8% | D16: ▲ +4 | E16: █████
A17: File Missing | B17: 20 | C17: 8.5% | D17: ▲ +2 | E17: ██████
A18: Unmatched raw data count | B18: 4 | C18: 1.7% | D18: — same | E18: █
A19: Pipeline Schedule | B19: 19 | C19: 8.1% | D19: ▲ +4 | E19: ██████
A20: DB Issue | B20: 4 | C20: 1.7% | D20: ▲ +1 | E20: █
A21: Metric drop | B21: 5 | C21: 2.1% | D21: ▲ +2 | E21: █
A22: Schema issue | B22: 8 | C22: 3.4% | D22: ▲ +1 | E22: ██
A23: Issue Platform | B23: 4 | C23: 1.7% | D23: ▼ -1 | E23: █
A24: Other | B24: 68 | C24: 28.8% | D24: ▼ -32 | E24: ████████████████████
A25: TOTAL | B25: 236 | C25: 100%
A27: All figures are auto-generated from the Jira export. Re-run the tracker to refresh. Needs Review tickets require manual categorization.

Sheet Raw Tickets
A1: NILE Pipeline Issues — April 2026
A2: Key | B2: Issue id | C2: Parent id | D2: Summary | E2: Description | F2: Comment | G2: Close Notes | H2: Categories | I2: New Categories | J2: Assign | K2: Status | L2: Created | M2: Updated | N2: Custom field (Assignment Group) | O2: Assignee | P2: Reporter | Q2: Resolution | R2: Custom field (Comments) | S2: Inward issue link (Cloners) | T2: Outward issue link (Cloners) | U2: Inward issue link (Relates) | V2: Category | W2: Review Required
A3: IT-3023323 | B3: IT-3023323 | D3: Monthly pipeline dm-uhc-unet-actian_migration_provider_npi_detail has failed for data date: 202604 | E3: Pipeline dm-uhc-unet-actian_migration_provider_npi_detail has failed with the error message: Source file schema is not matching with the Table Schema, Please check Column names and their Data-types. Please investigate | F3: We are using the dm-uhc-unet-actian_migration_provider_npi_detail _newtemp pipeline, so we won't need to ingest with this pipeline anymore. Thank you melly | G3: Use the _newtemp pipeline to ingest. | H3: Other | I3: Other | K3: Closed | L3: 2026-04-29 | M3: 2026-04-30 | N3: Nile Production Support | O3: Unassigned | P3: Acharya, Suraj | Q3: Resolved | R3: We are using the dm-uhc-unet-actian_migration_provider_npi_detail _newtemp pipeline, so we won't need to ingest with this pipeline anymore. Thank you melly | V3: Schema issue
A4: IT-3023321 | B4: IT-3023321 | D4: HCSCG - History PROF & INST. Files Missing - 04/28/2026 | E4: Hi Nile Team, We are missing HCSCG History Professional and Institutional for 04/24, So please check and provide us an update. hcscg_history_incoming_1 hcscg_ophistory_incoming_1 | G4: Files received and processed successfully. | K4: Closed | L4: 2026-04-29 | M4: 2026-05-01 | N4: Nile Production Support | O4: Unassigned | P4: Gudala, Kumaraswamy | Q4: Closed | V4: File Missing
A5: IT-3023116 | B5: IT-3023116 | D5: dm-bcbs_ma_bcbs_ma-actian_migration_caqh_and_bmc_workflow_CHC_BCBS_MA_ADH_CAQH_Load_NILE | E5: Weekly pipeline has been failing for over a month. The client has been sending file as CAQH File.* instead of CAQH file.* (lowercase). Pipeline is manually rerun each week using Override Parameters to complete successfully old {"source_data_pattern": "CAQH file .*.xlsx", "source_entity_1_file_pattern": "CAQH file .*.xlsx"} new {"source_data_pattern": "CAQH File .*.xlsx", "source_entity_1_file_pattern": "CAQH File.*.xlsx"} Suggestion : set source_data_pattern and source_entity_1_file_pattern to CAQH. * . xslx to account for both variations the client sends, or CAQH File . .xlsx | G5: Updated {"source_data_pattern": "CAQH File .*.xlsx", "source_entity_1_file_pattern": "CAQH File.*.xlsx"} | H5: Other | I5: Other | K5: Closed | L5: 2026-04-29 | M5: 2026-04-29 | N5: Nile Production Support | O5: Unassigned | P5: Easley, Keaton | Q5: Resolved | V5: Configuration Issue
A6: IT-3022913 | B6: IT-3022913 | D6: BCBS_MA CAQH files not ingested for April '26 | E6: Hello Nile team , BCBS_MA CAQH weekly files have not been ingested for April '26. The latest file we have in SQL is :- C*AQH File 20260407.xlsx* pipeline :- dm-bcbs_ma_bcbs_ma-actian_migration_caqh_and_bmc_workflow_CHC_BCBS_MA_ADH_CAQH_Load_NILE Missing files that Nile received but ingestion was not complete : - C*AQH File 20260414.xlsx* C*AQH File 20260421.xlsx* C*AQH File 20260428.xlsx* Thanks, Teena. | G6: Ingestion completed for all outstanding files | K6: Closed | L6: 2026-04-29 | M6: 2026-04-30 | N6: Nile Production Support | O6: Unassigned | P6: Vandanath, Teena | Q6: Closed | V6: File Issue
A7: IT-3022274 | B7: IT-3022274 | D7: Request for Data Validation: Claim Raw/model vs NILE Raw Data (Claims Header Fields) | E7: Client: BCBS_ND We are validating data in the ARK platform and observed that all fields in the Claims Header are populated from the Claim model, which in turn is sourced from Claim raw data. The values in the Claim model and raw data match exactly with the Claims Header, indicating that the data is loading as per the current logic. Since the Claim model data originates from NILE, we would like to understand how the raw data from NILE is structured and whether any transformations are applied to the relevant columns before being delivered downstream. Currently, we do not have visibility into the NILE raw files/tables to verify this. For example members CH_PATIENT_CLIENT_MASTER_ID (member_id) IN (135557853, 66442765, 93553925), OPS has requested validation of the raw data to determine whether the client is sending multiple policy/UMI plans per member. The goal is to identify whether the root cause of the mapping issue is related to how the client sends the data or a Cotiviti mapping issue. The columns to validate in the Claims Header are [PatNum] , [PatFirstName] , [PatLastName] , [EmployerName] , and [GroupNum] , with corresponding Claim Model/Raw columns CH_PATIENT_CLIENT_ID, CH_PATIENT_FIRST_NAME, CH_PATIENT_LAST_NAME, CH_GROUP_NAME, and CH_GROUP_NUMBER. | H7: Other | I7: Other | K7: Open | L7: 2026-04-29 | M7: 2026-04-29 | N7: Nile Production Support | O7: Unassigned | P7: Hagelin, Lindsay | Q7: Unresolved | V7: Data Issue
A8: IT-3022254 | B8: IT-3022254 | D8: Update to "MsrLobConcurrencyRates" Table | E8: Please do a full replacement of the existing table. There was an update to the values for a Medicaid state and we need those reflected in SpotCheck for claim accuracy. This is a one off from the normal cadence schedule. | F8: MsrLobConcurrencyRates.xlsx (28 kB) Hello Nile Team. The pipeline and table for this file already exist. Pipeline: dm-mcl-mcl-actian_migration_MsrLobConcurrencyRates The source file is located here: Y:\Ftp\B2B\MCL-NILE\MsrLobConcurrencyRates\2026-04-01\MsrLobConcurrencyRates.xlsx Thanks. Mike Hello Dhakal, Sambeg . I have reviewed the MsrLobConcurrencyRates table and the data looks good. You can close the ticket. Thanks. Mike Knochel, Tanya , Deynarian, Michael the pipeline has failed. Has the table already been updated? It failed at stage trigger BMC. | H8: Other | I8: Other | K8: In Progress (HD1) | L8: 2026-04-29 | M8: 2026-05-06 | N8: Nile Production Support | O8: Unassigned | P8: Knochel, Tanya | Q8: Unresolved | R8: MsrLobConcurrencyRates.xlsx (28 kB) Hello Nile Team. The pipeline and table for this file already exist. Pipeline: dm-mcl-mcl-actian_migration_MsrLobConcurrencyRates The source file is located here: Y:\Ftp\B2B\MCL-NILE\MsrLobConcurrencyRates\2026-04-01\MsrLobConcurrencyRates.xlsx Thanks. Mike Hello Dhakal, Sambeg . I have reviewed the MsrLobConcurrencyRates table and the data looks good. You can close the ticket. Thanks. Mike Knochel, Tanya , Deynarian, Michael the pipeline has failed. Has the table already been updated? It failed at stage trigger BMC. | V8: Pipeline Schedule
A9: IT-3021950 | B9: IT-3021950 | D9: bcbsnjhorizon_facets_no_touch failed due to file path does not exist. | E9: Pipeline: bcbsnjhorizon_facets_no_touch Got failed in Preprocessor [data-preprocessor] stage due to file path does not exist, since the files is already available in spooler location. Please do check on the file path location for the file. | F9: Hi Raya, Birajan file processed Thanks Satish Devatha | G9: file processed | H9: Other | I9: Other | K9: Closed | L9: 2026-04-29 | M9: 2026-04-29 | N9: Nile Production Support | O9: Unassigned | P9: Raya, Birajan | Q9: Resolved | R9: Hi Raya, Birajan file processed Thanks Satish Devatha | V9: File Issue
A10: IT-3021831 | B10: IT-3021831 | D10: CLONE - Peer Review for Aetna-Trad-SCM BMC pipeline Optimization | E10: Review all the required conditions for the BMC/child pipelines: Prechecks pipeline version to be updated to Latest Remove unwanted parameters from the pipeline All the child pipelines need to be published BMC pipeline needs to be published and Scheduled/Subscribe option need to be enabled. Update all the prod documents with latest pipeline versions. | G10: Since it's a direct bmc pipeline it doesn't require any changes. | H10: Other | I10: Other | K10: Closed | L10: 2026-04-29 | M10: 2026-04-30 | N10: Nile Production Support | O10: Unassigned | P10: Kamsetty, Sravani | Q10: Done | V10: Other | W10: Yes
A11: IT-3021830 | B11: IT-3021830 | D11: [BCBS_MI]-Update prechecks for BMC and publish all the child pipelines. | E11: Update precheck with pipeline version as latest and remove all the unnecessary parameters from the pipeline. Publish all the child pipelines and modify subscribe BMC pipeline versions to latest. | F11: BMC Pipeline prechecks conditions for pipeline version is updated to latest. Published and scheduled the latest BMC version pipeline. FYI: trigger_bmc_workflow-bcbs_mi_bcbs_mi_monthly Version: V1.6 | G11: BMC Pipeline prechecks conditions for pipeline version is updated to latest. Published and scheduled the latest BMC version pipeline. FYI: trigger_bmc_workflow-bcbs_mi_bcbs_mi_monthly Version: V1.6 | H11: Other | I11: Other | K11: Closed | L11: 2026-04-29 | M11: 2026-05-01 | N11: Nile Production Support | O11: Unassigned | P11: Kamsetty, Sravani | Q11: Resolved | R11: BMC Pipeline prechecks conditions for pipeline version is updated to latest. Published and scheduled the latest BMC version pipeline. FYI: trigger_bmc_workflow-bcbs_mi_bcbs_mi_monthly Version: V1.6 | V11: Other | W11: Yes
A12: IT-3021086 | B12: IT-3021086 | D12: Unmatched cosmosfaclcontractcategory raw data count - 20260428_1 - prod - dm-uhc-cosmos-actian_migration_cosmosfaclcontractcategory | E12: File name(s) COSMOS_FACL_CONTRACT_CATEGORY_OUT_HIST_APR26.txt Rejected records Impala table prod_niledataingestion_unrestricted.uhc_cosmos_raw_cosmosfaclcontractcategory_rejected_records_20260428_1 File data line count 201469543 Total raw data line count 201469543 Ingested row count 0 | F12: Hi Raya, Birajan , There is an extra column added to the end of the record on the existing schema .so, entire file is being rejected. Total columns as per the schema : 66 new file columns : 67 Need to check with EDM engineer. schema updated and file processed successfully. | G12: File processed successfully. | H12: Other | I12: Other | K12: Closed | L12: 2026-04-29 | M12: 2026-05-05 | N12: Nile Production Support | O12: Unassigned | P12: Raya, Birajan | Q12: Resolved | R12: Hi Raya, Birajan , There is an extra column added to the end of the record on the existing schema .so, entire file is being rejected. Total columns as per the schema : 66 new file columns : 67 Need to check with EDM engineer. schema updated and file processed successfully. | V12: Data Issue
A13: IT-3020658 | B13: IT-3020658 | D13: NAS Spoolers failed and pipeline not completed,Hue browser not working in production environment. | E13: Today, we experienced a Hadoop issue where spoolers failed, pipelines got stuck, and the Hue browser became inaccessible. | F13: The HUE browser is not accessible, and from the Nile side all NAS spoolers have failed. The failure occurred while trying to write files to HDFS. The error indicates that the HDFS NameNode is in safe mode, which prevents any file creation or write operations. Because of this, the spooler is unable to write files to the HDFS path, causing all spooling processes to fail. The system will remain in safe mode until the required block threshold is met, after which it should automatically turn off and resume normal operations. Hadoop noticed the issue and rolling restart the cluster. Instatly issue was resolved. After sometime pipeline are not running as expected. we notify and connected with different teams. They noticed the issue and resolved with the cluster restart. Summary: (Object(s) that caused the issue (host names, etc), issues/symptoms, include a link to the alert if there was one) - There are 20 missing blocks due to which Pipelines are unable to pick any jobs Resolution: (Actions taken by support teams to resolve the issue, Team/Individual that fixed the issue, additional tickets involved) - Restarted the Nile prod cluster (usapnlhdpe01) Summary: (Object(s) that caused the issue (host names, etc), issues/symptoms, include a link to the alert if there was one) - There are 20 missing blocks due to which Pipelines are unable to pick any jobs Resolution: (Actions taken by support teams to resolve the issue, Team/Individual that fixed the issue, additional tickets involved) - Restarted the Nile prod cluster (usapnlhdpe01) | G13: Summary: (Object(s) that caused the issue (host names, etc), issues/symptoms, include a link to the alert if there was one) - There are 20 missing blocks due to which Pipelines are unable to pick any jobs Resolution: (Actions taken by support teams to resolve the issue, Team/Individual that fixed the issue, additional tickets involved) - Restarted the Nile prod cluster (usapnlhdpe01) | H13: Other | I13: Other | K13: Closed | L13: 2026-04-29 | M13: 2026-04-29 | N13: Nile Production Support | O13: Unassigned | P13: Kantimahanti, Ravisankar | Q13: Resolved | R13: The HUE browser is not accessible, and from the Nile side all NAS spoolers have failed. The failure occurred while trying to write files to HDFS. The error indicates that the HDFS NameNode is in safe mode, which prevents any file creation or write operations. Because of this, the spooler is unable to write files to the HDFS path, causing all spooling processes to fail. The system will remain in safe mode until the required block threshold is met, after which it should automatically turn off and resume normal operations. Hadoop noticed the issue and rolling restart the cluster. Instatly issue was resolved. After sometime pipeline are not running as expected. we notify and connected with different teams. They noticed the issue and resolved with the cluster restart. Summary: (Object(s) that caused the issue (host names, etc), issues/symptoms, include a link to the alert if there was one) - There are 20 missing blocks due to which Pipelines are unable to pick any jobs Resolution: (Actions taken by support teams to resolve the issue, Team/Individual that fixed the issue, additional tickets involved) - Restarted the Nile prod cluster (usapnlhdpe01) Summary: (Object(s) that caused the issue (host names, etc), issues/symptoms, include a link to the alert if there was one) - There are 20 missing blocks due to which Pipelines are unable to pick any jobs Resolution: (Actions taken by support teams to resolve the issue, Team/Individual that fixed the issue, additional tickets involved) - Restarted the Nile prod cluster (usapnlhdpe01) | V13: Spooler issue
A14: IT-3020610 | B14: IT-3020610 | D14: Update the tracker with the newly deployed History Lean Ingestion pipelines for DevotedHealth that are now live in production. | E14: Hello Jani, Shaik , We have scheduled the devotedhealth - devotedhealth history lean ingestion pipelines in production, and these will be used going forward. Please note that for TBA, we will continue using the currently running Slim_Refactoring pipeline for devotedhealth - devotedhealth, as its estimated runtime is already around 13–14 minutes. The following is the list of old pipeline Ids replaced by the lean ingestion pipelines. 2023-02-27-54910254 -> 2026-03-30-111442046 reports: 2026-03-30-90594816 2023-02-27-52996445 -> 2026-03-30-111388968 reports: 2026-03-30-90568473 Thank You | G14: Details recorded accordingly. | H14: Other | I14: Other | K14: Closed | L14: 2026-04-29 | M14: 2026-05-06 | N14: Nile Production Support | O14: Unassigned | P14: Karakavalasa, SriVarshini | Q14: Resolved | V14: Other | W14: Yes
A15: IT-3020001 | B15: IT-3020001 | D15: CIGMC Prof. History File Failure 4/25/2026 | E15: Hi Nile team, The below file has failed for being out of sequence because it is using a seq# that was previously processed on 02/11/2026. Can you please have the client correct this and resend for processing? Failure: { } CIGMC|H| 0027710 |20260208|1|R TRAILER|1|20260208|160050 cigmc_history_incoming_113147 (1) Total Lines Processed for Run : 1 File Processing Information: ---------------------------------------------------------------------------------------------------- File : cigmc_history_incoming_113147.04-25-2026_1255 QA Status : FAILED Reason : FAILED- out-of-sequence Previously processed File: { } CIGMC|H| 0027710 |20260211|142|R TRAILER|142|20260211|160050 cigmc_ophistory_incoming_125706 (142) Total Lines Processed for Run : 142 File Processing Information: ---------------------------------------------------------------------------------------------------- File : cigmc_ophistory_incoming_125706.02-11-2026_1311 QA Status : PASSED File Run Completed : 02-11-2026_1311 | F15: Requested for the replacement file to the client Email subject reference: replacement file needed with corrected sequence number for CIGNA Medicare history professional file (2026/04/25) Client confirmed the corrected file was sent as cigmc_history_professional_incoming_20260429_100103.txt. File was received by Nile and processed successfully 4/29 around 11AMEST. Production Control team confirmed today that this file was successful on their side as well. File : cigmc_history_incoming_100103.04-29-2026_1115 QA Status : PASSED File Run Completed : 04-29-2026_1115 | G15: Client confirmed the corrected file was sent as cigmc_history_professional_incoming_20260429_100103.txt. File was received by Nile and processed successfully 4/29 around 11AMEST. Production Control team confirmed today that this file was successful on their side as well. File : cigmc_history_incoming_100103.04-29-2026_1115 QA Status : PASSED File Run Completed : 04-29-2026_1115 | H15: Other | I15: Other | K15: Closed | L15: 2026-04-28 | M15: 2026-05-05 | N15: Nile Production Support | O15: Unassigned | P15: Daniels, Ben | Q15: Resolved | R15: Requested for the replacement file to the client Email subject reference: replacement file needed with corrected sequence number for CIGNA Medicare history professional file (2026/04/25) Client confirmed the corrected file was sent as cigmc_history_professional_incoming_20260429_100103.txt. File was received by Nile and processed successfully 4/29 around 11AMEST. Production Control team confirmed today that this file was successful on their side as well. File : cigmc_history_incoming_100103.04-29-2026_1115 QA Status : PASSED File Run Completed : 04-29-2026_1115 | V15: File Issue
A16: IT-3019955 | B16: IT-3019955 | D16: TXCHP Institutional/TBA Files Failing 4/28/2026 | E16: We are experiencing a situation similar to IT-3004600 - TXCHP Institutional/TBA & History Files Failing 4/21/2026 TXCHP is continuing to fail. We have confirmed the files have been previously run in 2025. See the failed file list below. Can you please confirm if the client intentionally sent these files? Ticket: txchp_daily_incoming_1.04-28-2026_1700 txchp_daily_incoming_1.04-28-2026_1740 txchp_daily_incoming_1.04-28-2026_1815 txchp_outpatient_incoming_1.04-28-2026_1830 txchp_daily_incoming_1.04-28-2026_1855 txchp_outpatient_incoming_1.04-28-2026_1910 txchp_daily_incoming_1.04-28-2026_1934 txchp_outpatient_incoming_1.04-28-2026_1950 txchp_daily_incoming_1.04-28-2026_2023 txchp_outpatient_incoming_1.04-28-2026_2035 txchp_outpatient_incoming_1.04-28-2026_2120 txchp_daily_incoming_1.04-28-2026_2130 txchp_outpatient_incoming_1.04-28-2026_2210 txchp_daily_incoming_1.04-28-2026_2210 | F16: Melly's email (question): RE: IT-3019955 TXCHP Institutional/TBA Files Failing 4/28/2026 Need to understand what the source files are.. RE: IT-3019955 TXCHP Institutional/TBA Files Failing 4/28/2026 | H16: Other | I16: Other | K16: On Hold | L16: 2026-04-28 | M16: 2026-05-05 | N16: Nile Production Support | O16: Unassigned | P16: Edwards, Andrea | Q16: Unresolved | R16: Melly's email (question): RE: IT-3019955 TXCHP Institutional/TBA Files Failing 4/28/2026 Need to understand what the source files are.. RE: IT-3019955 TXCHP Institutional/TBA Files Failing 4/28/2026 | V16: File Issue
A17: IT-3019608 | B17: IT-3019608 | D17: Pipeline: dm-amerihealth-results-actian_migration_claims_detail | Data Date: 2026/04/28 | Failure | E17: Pipeline: dm-amerihealth-results-actian_migration_claims_detail , Version: V1.3 , Data Date: 2026/04/28 Error Message: Exiting Process with failure.Key source-file: /dataingestionprod/restricted/218-amerihealth-results/rawincoming/2024-09-20-102280221/1.3/125369.115465/20260428/1/NCDS_ClaimsRecovery.03132026.zip/NCDS_ClaimsRecovery.03132026.txt is zero-byte and Size: 0 . Stopping Ingestion Process as configured as mandatory file (Source section). We got CONFIRMATION from Karyn (EDM) to proceed with the loading. Thank you | F17: Hi Enid Ike pipeline completed Thanks Satish Devatha | G17: pipeline completed | H17: Other | I17: Other | K17: Closed | L17: 2026-04-28 | M17: 2026-04-28 | N17: Nile Production Support | O17: Unassigned | P17: Enid Ike | Q17: Resolved | R17: Hi Enid Ike pipeline completed Thanks Satish Devatha | V17: Other | W17: Yes
A18: IT-3019286 | B18: IT-3019286 | D18: BCNAM GWF Flag | E18: Hello, Currently, BCNAM is fully GWF eligible and everything on our end is configured this way. However, we are still seeing claims come through as not GWF eligible. We were wondering if this field is hardcoded at the GDF/CDF level. Can you please provide how these fields are currently mapped? GDF: CH_US_ONLY_INDICATOR CDF: US_ONLY_YN | F18: Hi Giri, Kushal , Good morning. I have verified the mappings and provided the below information to here. There is no raw field mapping for the below field in the GDF. CAST(NULL AS STRING) AS CH_US_ONLY_INDICATOR No mapping for the US_ONLY_YN Details have been conveyed to the customer. awaiting response. | H18: Other | I18: Other | K18: On Hold | L18: 2026-04-28 | M18: 2026-05-05 | N18: Nile Production Support | O18: Unassigned | P18: Giri, Kushal | Q18: Unresolved | R18: Hi Giri, Kushal , Good morning. I have verified the mappings and provided the below information to here. There is no raw field mapping for the below field in the GDF. CAST(NULL AS STRING) AS CH_US_ONLY_INDICATOR No mapping for the US_ONLY_YN Details have been conveyed to the customer. awaiting response. | V18: Configuration Issue
A19: IT-3018431 | B19: IT-3018431 | D19: Update to Molina post pay claim extract file | E19: Per the attached email from Molina, an update is being made to Molina’s post pay claim extract file, go live 5/28/2026. Email body from original Molina notification: Our IT will be making a change to the post-pay CLAIMS Extract. Go Live – 5/28/2026 Change: Addition of field at the end of the file New field: Provider_Adjust_Amount – This field now contains the Medicare Sequestration amount on a claim line (net_amt field is unchanged, but now the sequestration amt is explicitly listed in this field) Trey Simpson – AVP, Payment Integrity – Molina Healthcare, Inc. | F19: RE_ Update to Claims Extract.msg (135 kB) Hi Madel, William Does the change apply to all claims? Does the field need to be immediately displayed or is it to be displayed starting on the go-live date? cc Devatha, Satish | H19: Other | I19: Other | K19: Open | L19: 2026-04-28 | M19: 2026-04-29 | N19: Nile Production Support | O19: Unassigned | P19: Madel, William | Q19: Unresolved | R19: RE_ Update to Claims Extract.msg (135 kB) Hi Madel, William Does the change apply to all claims? Does the field need to be immediately displayed or is it to be displayed starting on the go-live date? cc Devatha, Satish | V19: File Issue
A20: IT-3018019 | B20: IT-3018019 | D20: Optumcare RCCV Professional Prod Transition Documents | E20: Hello Team, Please find the prod transition checklist documents for Optumcare RCCV Professional below: Checklist: Optumcare-RCCV_DataIgestion_Production_Job_Transition_Checklist.docx Escalation Doc: OptumCare_Joint Data Escalation Plan Enterprise External 20250424.xlsx I have created a ticket for document review: https://jira2.cotiviti.com/browse/NDICR-5409 | G20: Documents reviewed, Details reviewed and recorded and transition scheduled for today. | H20: Other | I20: Other | K20: Closed | L20: 2026-04-28 | M20: 2026-05-05 | N20: Nile Production Support | O20: Unassigned | P20: Shaik, Parveena | Q20: Resolved | V20: Other | W20: Yes
A21: IT-3017779 | B21: IT-3017779 | D21: Wellmark 3ppmo file Investigation | E21: The client informed that 3PPMO response file was not received. Upon Initial investigation, we found that #PPMO file was not received. Need further investigation on this. | F21: 3PPMO file has not been received from client server to axway itself. Verified with MFT team Asha and could not find the file from client. Sent an email for confirmation: Re: WMK PPMO - welex files not received 04/27/2026 Files received and processed successfully. | G21: Files received and processed successfully. | H21: Other | I21: Other | K21: Closed | L21: 2026-04-28 | M21: 2026-05-04 | N21: Nile Production Support | O21: Unassigned | P21: Bhattarai, Krishna | Q21: Resolved | R21: 3PPMO file has not been received from client server to axway itself. Verified with MFT team Asha and could not find the file from client. Sent an email for confirmation: Re: WMK PPMO - welex files not received 04/27/2026 Files received and processed successfully. | V21: File Missing
A22: IT-3017677 | B22: IT-3017677 | D22: dm-aetna-hrp-actian_migration_caqh got failed for 04/17 | E22: dm-aetna-hrp-actian_migration_caqh got failed for 04/17. Issue show the error not all mandatory file received but we have the files. It looks like below aetna -traditional pipeline processes the same file as well and it is also getting failed with the similar reason. dm-aetna-traditional-actian_migration_caqh | F22: Seems source filename is not having any issue. It's restricted client and need to check the unzipped files. Please let US people know so they can resolve. copied, moved files. re-spooled. ran pipeline, failed. | H22: Other | I22: Other | K22: In Progress (HD1) | L22: 2026-04-28 | M22: 2026-04-30 | N22: Nile Production Support | O22: Unassigned | P22: Aryal, Neerajan | Q22: Unresolved | R22: Seems source filename is not having any issue. It's restricted client and need to check the unzipped files. Please let US people know so they can resolve. copied, moved files. re-spooled. ran pipeline, failed. | V22: Pipeline Schedule
A23: IT-3017668 | B23: IT-3017668 | D23: UHC PNICE Transition | E23: UHC PNICE Transition | G23: Details recorded after reviewing the documents. | H23: Other | I23: Other | K23: Closed | L23: 2026-04-28 | M23: 2026-05-04 | N23: Nile Production Support | O23: Unassigned | P23: Bobbiti, Jithendra | Q23: Resolved | V23: Other | W23: Yes
A24: IT-3017655 | B24: IT-3017655 | D24: Production Transition - Tufts-Diamond | E24: Production Transition - Tufts-Diamond RCCV 2 pipelines Inpatient & Iphistory | F24: Waiting for the transition. also, the feedback fixes. | H24: Other | I24: Other | K24: On Hold | L24: 2026-04-28 | M24: 2026-05-05 | N24: Nile Production Support | O24: Unassigned | P24: Vutukuri, Praveen | Q24: Unresolved | R24: Waiting for the transition. also, the feedback fixes. | V24: Other | W24: Yes
A25: IT-3017640 | B25: IT-3017640 | D25: Wellcare Pipelines got failed | E25: dm-wellcare_wellcare_actian_migration_claim_header_icd10 Pipeline got failed on Fail Stage-raw_data_ingestion_error [fail] Stage. dm-wellcare-wellcare-mem_prov_claims_ingestion — Unmatched Raw Data Count Issue. Email Sub: Unmatched claimsheader_ark raw data count - 20260427_1 - prod - dm-wellcare-wellcare-mem_prov_claims_ingestion | F25: We have rejected records for wellcare claim header file for 20260427. Checking with EDM team. Pipeline processed successfully. | G25: Pipeline processed successfully. | H25: Other | I25: Other | K25: Closed | L25: 2026-04-28 | M25: 2026-04-30 | N25: Nile Production Support | O25: Unassigned | P25: Aryal, Neerajan | Q25: Resolved | R25: We have rejected records for wellcare claim header file for 20260427. Checking with EDM team. Pipeline processed successfully. | V25: Unmatched raw data count
A26: IT-3017571 | B26: IT-3017571 | D26: NAS Spoolers failed in production environment. | E26: we have noticed Nwe have noticed NAS Spoolers failed in production environment. Error: The job failed because our system tried to call another service to get file transfer logs, but that service didn’t respond in time. File spooling failed due to a timeout while calling the external transfer logs API. Error: The job failed because our system tried to call another service to get file transfer logs, but that service didn’t respond in time. File spooling failed due to a timeout while calling the external transfer logs API. | F26: I contacted the Command Center, and they will set up a bridge call with the Unix, Platform, and Axway teams. Service desk ticket from command center https://jiraet.cotiviti.com/browse/IT-3014827 Issue : Summary: (Object(s) that caused the issue (host names, etc), issues/symptoms, include a link to the alert if there was one) Automatic Process of spooling files for PPM clients was affected. The Admin Portal for Transfer2 SFTP URL which is used for the for monitoring or tracking is hung on gad1pt2axcore02 server and caused the log monitoring API not responded. (The NAS spoolers are getting failed to fetch the file from NAS dropbox to Nile HDFS location.) Resolution: (Actions taken by support teams to resolve the issue, Team/Individual that fixed the issue, additional tickets involved) MFT team has restarted the Admin Portal Services to restore the functionality and requested Nile team to use the FQDN url instead of single server url https://transfer2admin.cotiviti.com/api/v2.0/docs/index.html We manually copied the files into ML_Nile B2B and placed them in the HDFS locations. We will monitor the pipelines to ensure the files are delivered on time. We have delivered the files on time. connected with pc team get the confirmation from the user. | G26: We have delivered the files on time. connected with pc team get the confirmation from the user. | H26: Other | I26: Other | K26: Closed | L26: 2026-04-28 | M26: 2026-04-29 | N26: Nile Production Support | O26: Unassigned | P26: Kantimahanti, Ravisankar | Q26: Resolved | R26: I contacted the Command Center, and they will set up a bridge call with the Unix, Platform, and Axway teams. Service desk ticket from command center https://jiraet.cotiviti.com/browse/IT-3014827 Issue : Summary: (Object(s) that caused the issue (host names, etc), issues/symptoms, include a link to the alert if there was one) Automatic Process of spooling files for PPM clients was affected. The Admin Portal for Transfer2 SFTP URL which is used for the for monitoring or tracking is hung on gad1pt2axcore02 server and caused the log monitoring API not responded. (The NAS spoolers are getting failed to fetch the file from NAS dropbox to Nile HDFS location.) Resolution: (Actions taken by support teams to resolve the issue, Team/Individual that fixed the issue, additional tickets involved) MFT team has restarted the Admin Portal Services to restore the functionality and requested Nile team to use the FQDN url instead of single server url https://transfer2admin.cotiviti.com/api/v2.0/docs/index.html We manually copied the files into ML_Nile B2B and placed them in the HDFS locations. We will monitor the pipelines to ensure the files are delivered on time. We have delivered the files on time. connected with pc team get the confirmation from the user. | V26: Spooler issue
A27: IT-3017569 | B27: IT-3017569 | D27: Nile NAS spooler failures | E27: Nile NAS spooler failures Effected clients: caloptima -tba geisinger -tba triples - qnxttricm Carefirst Aetna HRP | F27: Duplicate ticket created. | H27: Other | I27: Other | K27: Cancelled | L27: 2026-04-28 | M27: 2026-04-29 | N27: Nile Production Support | O27: Unassigned | P27: Kamsetty, Sravani | Q27: Cancelled | R27: Duplicate ticket created. | V27: Spooler issue
A28: IT-3017529 | B28: IT-3017529 | D28: Nile NAS spooler failures | E28: Nile NAS spooler failures Effected clients: caloptima -tba geisinger -tba triples - qnxttricm Carefirst Aetna HRP | F28: Nile NAS spoolers failed and Joined command center bridge call. Helped gathering the issue and ran the pipelines manually as a workaround until the issue is fixed. | G28: Nile NAS spoolers failed and Joined command center bridge call. Helped gathering the issue and ran the pipelines manually as a workaround until the issue is fixed. | H28: Other | I28: Other | K28: Closed | L28: 2026-04-28 | M28: 2026-04-28 | N28: Nile Production Support | O28: Unassigned | P28: Kamsetty, Sravani | Q28: Resolved | R28: Nile NAS spoolers failed and Joined command center bridge call. Helped gathering the issue and ran the pipelines manually as a workaround until the issue is fixed. | V28: Spooler issue
A29: IT-3017053 | B29: IT-3017053 | D29: Request to add EDM's distro list to NILE's email notifications | E29: Hi Nile Prod Support team. Please add EDM’s distribution list to NILE’s ingestion report email notifications (see sample attached). EDM’s distribution list for each client is also attached. | F29: Data metric percentage drop hits threshold 202603 - prod - dm-humana-hdap-actian_migration_MEDCLM_RAW_AMBULANCE.msg (84 kB) Late Client File Notification - prod - Kaiser - WA - Kaiser-WA-Actian.msg (70 kB) prod - Cannot kick off bmc workflow CHC_UHC_COSMOS_PROVIDER_INCREMENTAL_NILE for ingestion period 20260428.msg (79 kB) Unmatched caqh raw data count - 20260404_1 - prod - dm-excellus-actian_migration_caqh.msg (77 kB) AuditDistroList-1.xlsx to make sure the email implementation of UHC Cirrus and HCSC is okay for EDM | H29: Other | I29: Other | K29: On Hold | L29: 2026-04-27 | M29: 2026-04-29 | N29: Nile Production Support | O29: Unassigned | P29: Pacete, John | Q29: Unresolved | R29: Data metric percentage drop hits threshold 202603 - prod - dm-humana-hdap-actian_migration_MEDCLM_RAW_AMBULANCE.msg (84 kB) Late Client File Notification - prod - Kaiser - WA - Kaiser-WA-Actian.msg (70 kB) prod - Cannot kick off bmc workflow CHC_UHC_COSMOS_PROVIDER_INCREMENTAL_NILE for ingestion period 20260428.msg (79 kB) Unmatched caqh raw data count - 20260404_1 - prod - dm-excellus-actian_migration_caqh.msg (77 kB) AuditDistroList-1.xlsx to make sure the email implementation of UHC Cirrus and HCSC is okay for EDM | V29: Other | W29: Yes
A30: IT-3016920 | B30: IT-3016920 | D30: Copy files From Nile Prod Raw path to Nile QC Raw path - Aetna Trad | E30: Hi Team, Could you please copy the below mentioned files from the Nile PROD location to the Nile QC location? for the last week files, 04/19/2026 to latest. This request is critical as we have early communicated with prod support team. Nile PROD RAW PATH (Source): /dataingestionprod/raw/unrestricted/5-aetna-traditional Nile Dev RAW PATH (Target): /dataingestionqc/raw/unrestricted/5-aetna-traditional Once copied to QC folder, the owner should be set to "svcpnilediqcraw" and group should be set to "qcunrestricted" and permissions should be 75 | F30: Files Copied | G30: Files Copied | H30: Other | I30: Other | K30: Closed | L30: 2026-04-27 | M30: 2026-04-27 | N30: Nile Production Support | O30: Unassigned | P30: Shivalingu, Naveen | Q30: Resolved | R30: Files Copied | V30: Other | W30: Yes
A31: IT-3016913 | B31: IT-3016913 | D31: Copy files From Nile Prod Raw path to Nile QC Raw path - Aetna Trad | E31: Hi Team, Could you please copy the below mentioned files from the Nile PROD location to the Nile QC location? for the last week files, 04/19/2026 to latest. This request is critical as we have early communicated with prod support team. Nile PROD RAW PATH (Source): /dataingestionprod/raw/unrestricted/5-aetna-traditional Nile Dev RAW PATH (Target): /dataingestionqc/raw/unrestricted/5-aetna-traditional Once copied to QC folder, the owner should be set to "svcpnilediqcraw" and group should be set to "qcunrestricted" and permissions should be 75 | F31: Files are already copied | G31: Files are already copied | H31: Other | I31: Other | K31: Closed | L31: 2026-04-27 | M31: 2026-04-28 | N31: Nile Production Support | O31: Unassigned | P31: Shivalingu, Naveen | Q31: Resolved | R31: Files are already copied | V31: Other | W31: Yes
A32: IT-3016384 | B32: IT-3016384 | D32: Molina Raw Data Needed | E32: Please provide the raw data for the below 5 CCV inpatient files to assist us in researching some data discrepancies that are impacting CCV audits. If possible, please provide the raw files that ultimately feed the below CCV inpatient files. We need to look at the actual raw files from the client, and not the GDF/CDF files that CCV is using (we already have that information). If the actual files cannot be provided, can they be loaded to Hive or Impala for us to query to aid in our research? molhc_inpatient_incoming_1r.02-17-2026_1345 molia_inpatient_incoming_1r.02-17-2026_1345 molky_inpatient_incoming_1r.01-17-2026_1043 molky_inpatient_incoming_1r.02-17-2026_1350 molut_inpatient_incoming_1r.02-17-2026_1400 cc: Free, Ann Waud, Jason | F32: Hi Arevalo, Anna Shared IA,KY,MC and UT raw files Thanks Satish Devatha | G32: Shared IA,KY,MC and UT raw files | H32: Other | I32: Other | K32: Closed | L32: 2026-04-27 | M32: 2026-04-29 | N32: Nile Production Support | O32: Unassigned | P32: Arevalo, Anna | Q32: Resolved | R32: Hi Arevalo, Anna Shared IA,KY,MC and UT raw files Thanks Satish Devatha | V32: Data Issue
A33: IT-3016136 | B33: IT-3016136 | D33: Update spooler name | E33: Hi Team, Could you please update the spooler name in prod? Before : Wellcare-Wellcare_Actian_PBM_MTH_notouch New name : Wellcare-Wellcare_notouch Thank you! | F33: Hi Varghese, Shilpa Anna updated the spooler name Thanks | G33: Updated Spooler name | H33: Other | I33: Other | K33: Closed | L33: 2026-04-27 | M33: 2026-04-27 | N33: Nile Production Support | O33: Unassigned | P33: Varghese, Shilpa Anna | Q33: Resolved | R33: Hi Varghese, Shilpa Anna updated the spooler name Thanks | V33: Spooler issue
A34: IT-3016120 | B34: IT-3016120 | D34: Move two Aetna Trad files to different folders | E34: In HDFS (nile prod server), please move the following files to new locations. Ultimately we want the parent folder of these files to represent a different date (20260411 vs 20260427). Source files: /dataingestiondev/raw/unrestricted/5-aetna-traditional/20260427/M2603M1.ZIP /dataingestiondev/raw/unrestricted/5-aetna-traditional/20260427/M2603M2.ZIP Destinations: /dataingestiondev/raw/unrestricted/5-aetna-traditional/20260411/M2603M1.ZIP /dataingestiondev/raw/unrestricted/5-aetna-traditional/20260411/M2603M2.ZIP | F34: Hi Maguire, Patrick Files moved and updated permissions too please verify | G34: Files moved and updated permissions too | H34: Other | I34: Other | K34: Closed | L34: 2026-04-27 | M34: 2026-04-27 | N34: Nile Production Support | O34: Unassigned | P34: Maguire, Patrick | Q34: Resolved | R34: Hi Maguire, Patrick Files moved and updated permissions too please verify | V34: Issue Platform
A35: IT-3016008 | B35: IT-3016008 | D35: Requesting information for Cigna Gross ID amount dataset | E35: We are looking to learn information on Cigna Gross ID amount dataset as it relates to if it is provided to Nile and if so how and where it can accessed. | H35: Other | I35: Other | K35: In Progress (HD1) | L35: 2026-04-27 | M35: 2026-04-28 | N35: Nile Production Support | O35: Unassigned | P35: Hayes, Denzel | Q35: Unresolved | V35: Other | W35: Yes
A36: IT-3015943 | B36: IT-3015943 | D36: Weekly rccv-bsca-facets-ingest_history_institutional_claims_GDF2_12 got failed due to significant data drop for date 04/25. | E36: Above pipeline got failed due to significant data drop and CSM wants to know the reason for it. Please help investigate and reply to the mail subject: Data metric percentage drop hits threshold 20260425 - prod - rccv-bsca-facets-ingest_history_institutional_claims_GDF2_12 | F36: Hi Kandel, Amik shared the counts with Paul and Rhona Waiting for response on replacement file Got confirmation to add parameter. Now pipeline is running now Hi Kandel, Amik Pipeline completed | G36: Pipeline completed | H36: Other | I36: Other | K36: Closed | L36: 2026-04-27 | M36: 2026-04-29 | N36: Nile Production Support | O36: Unassigned | P36: Kandel, Amik | Q36: Resolved | R36: Hi Kandel, Amik shared the counts with Paul and Rhona Waiting for response on replacement file Got confirmation to add parameter. Now pipeline is running now Hi Kandel, Amik Pipeline completed | V36: Metric drop
A37: IT-3015919 | B37: IT-3015919 | D37: UHC Cosmos Layout update in file 'HCCC_CD_OUT_<>' | E37: Hello Nile Team, There is a layout update in file ‘HCCC_CD_OUT_<>’. Could you please update the data type length of fields HcccDesc to Varchar(24) and HcccSumTxt to Varchar(27) The pipeline name that needs to be updated is prod - dm-uhc-cosmos-actian_migration_HcccCd Thanks, Priya | F37: Dongol, Priya Pipeline dm-uhc-cosmos-actian_migration_HcccCd is now running for data date 2026/04 with updated UDC changes. Dongol, Priya pipeline has ran successfully. Closing ticket. | G37: Pipeline was updated and ran successfully. | H37: Other | I37: Other | K37: Closed | L37: 2026-04-27 | M37: 2026-04-27 | N37: Nile Production Support | O37: Unassigned | P37: Dongol, Priya | Q37: Resolved | R37: Dongol, Priya Pipeline dm-uhc-cosmos-actian_migration_HcccCd is now running for data date 2026/04 with updated UDC changes. Dongol, Priya pipeline has ran successfully. Closing ticket. | V37: Schema issue
A38: IT-3015767 | B38: IT-3015767 | D38: UHC Cosmos/Unet - Layout Update in file ‘DISCOUNT_TYPE_CD_OUT_<>’ | E38: Hello Nile Production Team, We have a layout update on field DscntTypDesc for file ‘DISCOUNT_TYPE_CD_OUT_<>’. I have updated the length of this field in both Cosmos and Unet SQL tables. Could you please update the data type length of fields DscntTypDesc to varchar(1500) in Nile pipelines? Pipeline names are; prod - dm-uhc-cosmos-actian_migration_dscnttype prod - dm-uhc-unet-actian_migration_DscntType Thanks, Priya | F38: Hi Dongol, Priya , Updated UDC for both the pipelines. prod - dm-uhc-cosmos-actian_migration_dscnttype: pipeline is running with the data date 202604 prod - dm-uhc-unet-actian_migration_DscntType: pipeline will run in the next schedule. Dongol, Priya Pipeline: dm-uhc-unet-actian_migration_DscntType. Also ran with data date: 2026/04. So, closing this ticket. Thank you. | G38: Pipeline was updated and ran successfully. | H38: Other | I38: Other | K38: Closed | L38: 2026-04-27 | M38: 2026-05-04 | N38: Nile Production Support | O38: Unassigned | P38: Dongol, Priya | Q38: Resolved | R38: Hi Dongol, Priya , Updated UDC for both the pipelines. prod - dm-uhc-cosmos-actian_migration_dscnttype: pipeline is running with the data date 202604 prod - dm-uhc-unet-actian_migration_DscntType: pipeline will run in the next schedule. Dongol, Priya Pipeline: dm-uhc-unet-actian_migration_DscntType. Also ran with data date: 2026/04. So, closing this ticket. Thank you. | V38: Schema issue
A39: IT-3015029 | B39: IT-3015029 | D39: Removing unused spoolers with a retention period of ‘-1’ from the production environment. | E39: Removed published spoolers with a retention period of -1 from the production environment, as they were no longer in use. A backup was taken by importing and saving them in a folder prior to deletion. Below is the list of spoolers that were removed from production. | F39: Deleted date: 22-04-2026 | G39: Removed the unused spoolers. | H39: Other | I39: Other | K39: Closed | L39: 2026-04-27 | M39: 2026-04-27 | N39: Nile Production Support | O39: Unassigned | P39: Karakavalasa, SriVarshini | Q39: Resolved | R39: Deleted date: 22-04-2026 | V39: Spooler issue
A40: IT-3014397 | B40: IT-3014397 | D40: Please help ingest 4/13's UHC Cirrus file | E40: Hello team we received Cirrus weekly files on 4/21, the ingestion was on hold because we have to finish some process first. Now the process from our end has completed. The 4/21’s file has been copied over for Nile ingestion would you please help ingest all the files? This is a very time sensitive request, thanks and please let me know if you need additional info. | F40: Hi Tang, Chao , Files spooled and processed from NILE under 20260420 ingestion date. Please check and confirm. Chao confirmed to close the ticket. Thanks. | G40: Files processed from NILE. | H40: Other | I40: Other | K40: Closed | L40: 2026-04-26 | M40: 2026-04-28 | N40: Nile Production Support | O40: Unassigned | P40: Tang, Chao | Q40: Resolved | R40: Hi Tang, Chao , Files spooled and processed from NILE under 20260420 ingestion date. Please check and confirm. Chao confirmed to close the ticket. Thanks. | V40: Spooler issue
A41: IT-3014330 | B41: IT-3014330 | D41: Excellus Business Segments | E41: The mapping has not been implemented as expected, Claim cdf1 is still blank in files loaded on April 20 Please update mapping as requested in previous ticket | F41: For Excellus files, please allow value from vr_inpatient_claim_detail_iface. BSNS_SGMNT be mapped to CC_CUSTOM_FIELD_04. Hi Varughese, Neena please find latest results for your refernce. The mapping looks correct, please implement for May 2026 CCV cdf Hello Varughese, Neena , The requested mapping changes have been implemented in the dev environment. With Satish’s assistance, we reviewed the data, and the updated details are attached to the ticket. Please verify the data and inform us if any changes are needed. Once confirmed, we will deploy the changes to prod. Hello Varughese, Neena , The updated pipelines have been promoted to production and scheduled. Kindly review and let me know if any changes are needed. Awaiting user review | G41: Received confirmation from the user. | H41: COM | I41: Other Support | K41: Closed | L41: 2026-04-26 | M41: 2026-05-04 | N41: Nile Production Support | O41: Unassigned | P41: Varughese, Neena | Q41: Resolved | R41: For Excellus files, please allow value from vr_inpatient_claim_detail_iface. BSNS_SGMNT be mapped to CC_CUSTOM_FIELD_04. Hi Varughese, Neena please find latest results for your refernce. The mapping looks correct, please implement for May 2026 CCV cdf Hello Varughese, Neena , The requested mapping changes have been implemented in the dev environment. With Satish’s assistance, we reviewed the data, and the updated details are attached to the ticket. Please verify the data and inform us if any changes are needed. Once confirmed, we will deploy the changes to prod. Hello Varughese, Neena , The updated pipelines have been promoted to production and scheduled. Kindly review and let me know if any changes are needed. Awaiting user review | V41: Configuration Issue
A42: IT-3013659 | B42: IT-3013659 | D42: PREBC - TBA PROF & INST files missing - 04/24/2026 & 04/25/2026 | E42: Hi Nile Team, We are missing below files for 04/24/2026 & 04/25/2026. Please check and let us know when we can expect the missing files. prebc_daily_incoming_2 prebc_outpatient_incoming_2 | F42: we successfully processed the 24th and 25th data date files. attached screenshot for reference we successfully processed the 24th and 25th data date files. attached screenshot for reference. | G42: we successfully processed the 24th and 25th data date files. attached screenshot for reference. | K42: Closed | L42: 2026-04-25 | M42: 2026-04-28 | N42: Nile Production Support | O42: Unassigned | P42: Gudala, Kumaraswamy | Q42: Closed | R42: we successfully processed the 24th and 25th data date files. attached screenshot for reference we successfully processed the 24th and 25th data date files. attached screenshot for reference. | V42: File Missing
A43: IT-3012722 | B43: IT-3012722 | D43: rccv-cignamedicare-facets-tba_institutional_claims_custom_GDF2_5_CDF2_5 for May 2025 ingestion.. | E43: Hi Satish, Just creating this ticket as a placeholder In May 2026, Monitoring team will check for the arrival files for Cignamdicare facets drg. After the files are spooled, you and I will sync up to decide: rccv-cignamedicare-facets-tba_institutional_claims_custom_GDF2_5_CDF2_5 which version to use, and what schema. The latest one from Din is v1.9. Thanks Satish, melly | F43: Hi Suryani, Melly Thanks for running latest version v1.9 pipeline Thanks Satish Devatha | H43: Other | I43: Other | K43: In Progress (HD1) | L43: 2026-04-24 | M43: 2026-05-07 | N43: Nile Production Support | O43: Unassigned | P43: Suryani, Melly | Q43: Unresolved | R43: Hi Suryani, Melly Thanks for running latest version v1.9 pipeline Thanks Satish Devatha | V43: Other | W43: Yes
A44: IT-3012689 | B44: IT-3012689 | D44: Please ingest a supplemental file for BCBS_TN Member data. | E44: Please ingest a catchup file for BCBS_TN Member data, based on an existing pipeline: Existing Pipeline: dm-bcbstn-bcbstn-actian_migration_member Source File: MEMBER_AUG2025-MAR2026_GBQ_20260422.tab Target Table: BCBS_TNDataRaw.dbo.Member_Load_Monthly_Catchup | G44: Completed ingestion to adhoc table as requested | H44: Other | I44: Other | K44: Closed | L44: 2026-04-24 | M44: 2026-04-27 | N44: Nile Production Support | O44: Unassigned | P44: Castro, Ronald | Q44: Resolved | V44: File Issue
A45: IT-3012305 | B45: IT-3012305 | D45: Schedule Wellcare pipelines for weekly data load files to run at 4PM ET every Monday. | E45: Currently the pipelines for these below files are scheduled to run at 8pm every Monday. Can we please set the schedule to run the pipelines of loading these files into sql tables starting 4pm ET every Monday? Generic_DB_YYYYMMDD.zip VENDOR_YYYYMMDD.txt.gz PROVIDER_YYYYMMDD_X.txt.gz CLAIM_HEADER_YYYYMMDD_X.txt.gz CLAIM_LINE_YYYYMMDD_X.txt.gz SUBSCRIBER_YYYYMMDD_X.txt.gz Sample File Names : (please see attached screenshot) | G45: Monitored for the latest run and the pipelines got triggered. | H45: Other | I45: Other | K45: Closed | L45: 2026-04-24 | M45: 2026-05-06 | N45: Nile Production Support | O45: Unassigned | P45: Trivedi Shukla, Zarna | Q45: Resolved | V45: Pipeline Schedule
A46: IT-3011925 | B46: IT-3011925 | D46: BCSAL and BCPAL files not seen in CAT for production of the audit selection report | E46: Payer short BCSAL and BCPAL files were received by the client (RCA file) and ready for production on 4/7, however the files are still not visible in the CAT tool for the selections team to create the audit selection report. Not sure where the files are. | F46: Hi Judy, Nile don't process ccv for BCBS AL; We only ingest the raw files from the client to the staging tables, and from there, EDM RCA carry the downstream processes, including parts of ccv processes. Let me check with Sajjan Shrestha to confirm; Thx melly moving to Nile per engineer not for CRS Support This is not with Nile - I'm not sure yet how we should proceed. | H46: Other | I46: Other | K46: On Hold | L46: 2026-04-24 | M46: 2026-05-06 | N46: Nile Production Support | O46: Unassigned | P46: Cashen, Judy | Q46: Unresolved | R46: Hi Judy, Nile don't process ccv for BCBS AL; We only ingest the raw files from the client to the staging tables, and from there, EDM RCA carry the downstream processes, including parts of ccv processes. Let me check with Sajjan Shrestha to confirm; Thx melly moving to Nile per engineer not for CRS Support This is not with Nile - I'm not sure yet how we should proceed. | V46: File Missing
A47: IT-3011918 | B47: IT-3011918 | D47: BCSAL and BCPAL files not seen in CAT for production of the audit selection report | E47: Hi, for payer shorts BCSAL and BCPA the files were received by RCA and ready for production on 4/7, however they are not showing in the CAT tool for the selections team to produce the audit selection report. Need to know where the files are. | F47: moving to Nile per engineer not for CRS Support This is not with Nile - I'm not sure yet how we should proceed. | H47: ICMS | I47: Other | K47: On Hold | L47: 2026-04-24 | M47: 2026-05-06 | N47: Nile Production Support | O47: Unassigned | P47: Cashen, Judy | Q47: Unresolved | R47: moving to Nile per engineer not for CRS Support This is not with Nile - I'm not sure yet how we should proceed. | V47: File Missing
A48: IT-3011677 | B48: IT-3011677 | D48: Please confirm if RCA Engineering is receiving and ingesting the SIU Weekly Provider Report Geisinger sends us via SFTP that is an exclusion file for our teams. | E48: Geisinger sends us a weekly SIU Provider exclusion file that should be received via SFTP. They also send it to us via e-mail. However, when CCV and I first began receiving this via e-mail, Phil Thomas, informed the CCV CSM and I we could ignore these e-mails as they get sent to us via SFTP and automatically ingested. It appears from the below that is the case for CCV. Do you know if that is still the case for RCA? Recently the client, began adding additional exclusions to this list that we do have to share with Audit Ops for updates. This concerned me that perhaps this could impact our appropriate ingestion of the SIU weekly provider exclusions the client sends us via SFTP. Would you mind having the team look into this for us and confirm if we are ingesting these files via the SFTP? If we are, are the files we’re ingesting, the same as the examples the client sends to us via e-mail as well? Please let me know who I need to send a copy of the e-mail exclusion file to once this ticket is picked up. Thank you!! | F48: Active Pipelines dm-geisinger-facets-weekly_SIU_notouch_file geisinger-facets-weekly_provider_report_passthrough File: SIU Weekly Provider Report.* Filesource: /B2B/Geisinger/inbound/production Cadence: Weekly I compared SIU Weekly Provider Report for Vendor 12-1-2025 file spooled from SFTP with SIU Weekly Provider Report for Vendor 12-1-2025 file Reporter received via email. These files have many discrepancies, namely it seems the reports were generated at different times. Namely, the email file has a report date of 12/4/2025, while the file spooled from SFTP has a report date of 12/17/2025. I compared SIU Weekly Provider Report for Vendor 04-06-2026 file spooled from SFTP with SIU Weekly Provider Report for Vendor 04-06-2026 file Reporter received via email. These files both contain 519 records. The files also contain 4,152 data points that match exactly. So these files are the same. SIU Weekly Provider Report for Vendor 02-23-2026 Records 452 ValuesMatched 3616 ValuesUnmatched 0 SIU Weekly Provider Report for Vendor 03-09-2026 Records 477 Values 3808 ValuesUnmatched 0 SIU Weekly Provider Report for Vendor 01-12-2026 Records 423 ValuesMatched 2965 ValuesUnmatched 419 Analysis: The values that are unmatched are from the "Case Create Date" column. An example of these unmatched values are 1/13/2026 5:27: 41 PM vs 1/13/2026 5:27: 00 PM SIU Weekly Provider Report for Vendor 02-23-2026 Records 452 ValuesMatched 3616 ValuesUnmatched 0 SIU Weekly Provider Report for Vendor 03-09-2026 Records 477 Values 3808 ValuesUnmatched 0 SIU Weekly Provider Report for Vendor 01-12-2026 Records 423 ValuesMatched 2965 ValuesUnmatched 419 | G48: Provided the requestor's analysis in the comments which included comparing 4 SFTP files against files received from email | H48: Other | I48: Other | K48: Closed | L48: 2026-04-24 | M48: 2026-05-01 | N48: Nile Production Support | O48: Unassigned | P48: Depolo, Kara | Q48: Resolved | R48: Active Pipelines dm-geisinger-facets-weekly_SIU_notouch_file geisinger-facets-weekly_provider_report_passthrough File: SIU Weekly Provider Report.* Filesource: /B2B/Geisinger/inbound/production Cadence: Weekly I compared SIU Weekly Provider Report for Vendor 12-1-2025 file spooled from SFTP with SIU Weekly Provider Report for Vendor 12-1-2025 file Reporter received via email. These files have many discrepancies, namely it seems the reports were generated at different times. Namely, the email file has a report date of 12/4/2025, while the file spooled from SFTP has a report date of 12/17/2025. I compared SIU Weekly Provider Report for Vendor 04-06-2026 file spooled from SFTP with SIU Weekly Provider Report for Vendor 04-06-2026 file Reporter received via email. These files both contain 519 records. The files also contain 4,152 data points that match exactly. So these files are the same. SIU Weekly Provider Report for Vendor 02-23-2026 Records 452 ValuesMatched 3616 ValuesUnmatched 0 SIU Weekly Provider Report for Vendor 03-09-2026 Records 477 Values 3808 ValuesUnmatched 0 SIU Weekly Provider Report for Vendor 01-12-2026 Records 423 ValuesMatched 2965 ValuesUnmatched 419 Analysis: The values that are unmatched are from the "Case Create Date" column. An example of these unmatched values are 1/13/2026 5:27: 41 PM vs 1/13/2026 5:27: 00 PM SIU Weekly Provider Report for Vendor 02-23-2026 Records 452 ValuesMatched 3616 ValuesUnmatched 0 SIU Weekly Provider Report for Vendor 03-09-2026 Records 477 Values 3808 ValuesUnmatched 0 SIU Weekly Provider Report for Vendor 01-12-2026 Records 423 ValuesMatched 2965 ValuesUnmatched 419 | V48: Other | W48: Yes
A49: IT-3011541 | B49: IT-3011541 | D49: Please help ingest 4/13's UHC Cirrus file | E49: Hello team we received Cirrus weekly files on 4/13, would you please help reingest all the files? a little background: the file was arrived on time, but we have to hold off on loading them, because the 4/6’s file ingestion was not completed yet, and now 4/6 process has finally completed, we need to start ingest 4/13’s file. This is a very time sensitive request, we will need your help to get the file successfully ingested today. Thanks and please let me know if you need additional info. | F49: 4/13 ingestion is complete. closing out ticket | G49: 4/13 ingestion is complete. closing out ticket | H49: Other | I49: Other | K49: Closed | L49: 2026-04-24 | M49: 2026-04-24 | N49: Nile Production Support | O49: Unassigned | P49: Tang, Chao | Q49: Resolved | R49: 4/13 ingestion is complete. closing out ticket | V49: Spooler issue
A50: IT-3011476 | B50: IT-3011476 | D50: Unmatched gdf_member_enrollment raw data count - 20260422_1 - prod - fwa-BCBSND-OSCAR_member_GDF2_3 | E50: Pipeline fwa-BCBSND-OSCAR_member_GDF2_3 has failed due to unmatched records. Email Ref: Unmatched gdf_member_enrollment raw data count - 20260422_1 - prod - fwa-BCBSND-OSCAR_member_GDF2_3 Please investigate. | F50: Due to rejected records. So added override and running the pipeline Not Sure why pipeline is in Draft mode can we publish and schedule the pipeline?? pipeline completed | G50: pipeline completed | H50: Other | I50: Other | K50: Closed | L50: 2026-04-24 | M50: 2026-04-24 | N50: Nile Production Support | O50: Unassigned | P50: Acharya, Suraj | Q50: Resolved | R50: Due to rejected records. So added override and running the pipeline Not Sure why pipeline is in Draft mode can we publish and schedule the pipeline?? pipeline completed | V50: Data Issue
A51: IT-3010303 | B51: IT-3010303 | D51: HCSC_BackFill_Set_2_files process. | F51: The second set of files is not being spooled, and we’re facing several challenges. For example, the file name pattern does not include any suffix, and the files have the same name and size as those previously processed. When attempting to spool them, the system indicates that the files have already been processed. I also tried placing all folders in the HDFS location, but the spooler got stuck, so I reached out to the platform team. As an alternative, we copied the files from FTP to HDFS with Satish’s help. The data is currently still loading. we successfully proceed the second set of files, verifying the tables data. Second set of files proceed from the Nile side. | G51: Second set of files proceed from the Nile side. | H51: Other | I51: Other | K51: Closed | L51: 2026-04-24 | M51: 2026-04-28 | N51: Nile Production Support | O51: Unassigned | P51: Kantimahanti, Ravisankar | Q51: Done | R51: The second set of files is not being spooled, and we’re facing several challenges. For example, the file name pattern does not include any suffix, and the files have the same name and size as those previously processed. When attempting to spool them, the system indicates that the files have already been processed. I also tried placing all folders in the HDFS location, but the spooler got stuck, so I reached out to the platform team. As an alternative, we copied the files from FTP to HDFS with Satish’s help. The data is currently still loading. we successfully proceed the second set of files, verifying the tables data. Second set of files proceed from the Nile side. | V51: Other | W51: Yes
A52: IT-3009815 | B52: IT-3009815 | D52: Centene PCCV MI MCD Expansion Prod Transition Documents Review | E52: Please review the prod transition checklist documents for Centene PCCV MI MCD Expansion and let us know if any changes are needed. Creating this ticket as a placeholder. Will update ticket with document links once complete. | F52: Awaiting documents. | H52: Other | I52: Other | K52: On Hold | L52: 2026-04-23 | M52: 2026-05-05 | N52: Nile Production Support | O52: Unassigned | P52: Malmgren, Natalie | Q52: Unresolved | R52: Awaiting documents. | V52: Other | W52: Yes
A53: IT-3009664 | B53: IT-3009664 | D53: Clarification on Premera History Files for Data Date 2026/04/06 | E53: I’m looking for understanding of what the issue was with the below files that were received on 4/15/26 related to the Shared Admin Invoicing Process. Previous communication indicated that there was missing header and trailer information, but Premera has responded saying that the header and footer is present on the file sent. Can we update our response or provide screenshots of the missing information? Thanks! | F53: EXTERNAL RE_ Clarification on Premera History Files for Data Date 2026_04_06.msg (328 kB) Production Control team can you please check and let us know if you need anything? Hi Nile PS Triage team, I notice for these two historical files: ppm-premera-bluecross-history_professional_claims_GDF2_2_CDF2_2_lean_ingestion ppm-premera-bluecross-history_institutional_claims_GDF2_2_CDF2_2_lean_ingestion for date ingestion 2026-04-06 failed in preprocessor step with error message: File /dataingestionprod/unrestricted/109-premera-bluecross/rawincoming/2026-03-30-102438457/1/136533/20260406/1 does not exist. Can you investigate what's going on? I can see the raw files are avaialablei in hue Raw. Thank you melly Suryani, Melly please see the correct files in question. They are dated 04/06, but they were received on 4/15 as described in the email I attached. prebc_history_institutional_incoming_20260406_1.txt.pgp prebc_history_professional_incoming_20260406_1.txt.pgp Sent a reply to Adam: It seems the files on 20260406 are super small. waiting follow up from Adam. Premera has sent over a new set of files. It appears that these files were successfully received in Axway. Can we please confirm they were loaded correctly? prebc_history_institutional_incoming_20260428_1.txt prebc_history_professional_incoming_20260428_1.txt They also resent the unlinked file as well: prebc_unlinkedadj_incoming_1_20260428.zip Hi Adam, We are still getting an error on the replacement files 4/28. We're taking a closer look... Thank you melly Melly's update 4/30: I can see both header-trailer in the source files: /dataingestionprod/unrestricted/109-premera-bluecross/rawincoming/2026-03-30-91183910/1/136533/src_file_backup/20260428/1/prebc_history_institutional_incoming_20260428_1.txt /dataingestionprod/unrestricted/109-premera-bluecross/rawincoming/2026-03-30-102438457/1/136533/src_file_backup/20260428/1/prebc_history_professional_incoming_20260428_1.txt Pipeline error message: No of columns not matching in Header record or Trailer record. Hi Adam, I got my answer: The reason of the error is because they dont conform with the regular history trailer records because they dont have the date stamp at the end: We received @@TRAILER@@|428 (for institutional) @@TRAILER@@|2002 (for professional). Expected: @@TRAILER@@|428|date time (for institutional) @@TRAILER@@|2002|date time (for professional). Would you mind asking the client for the replacement files? Thanks so much melly Client finally sent their final replacement files and they were processed successfully: prebc_history_institutional_incoming_20260503_1.txt.pgp prebc_history_professional_incoming_20260503_1.txt.pgp | G53: Replacement from client on 5/1/2026 processed successfully | H53: Other | I53: Other | K53: Closed | L53: 2026-04-23 | M53: 2026-05-04 | N53: Nile Production Support | O53: Unassigned | P53: Spinelli, Adam | Q53: Resolved | R53: EXTERNAL RE_ Clarification on Premera History Files for Data Date 2026_04_06.msg (328 kB) Production Control team can you please check and let us know if you need anything? Hi Nile PS Triage team, I notice for these two historical files: ppm-premera-bluecross-history_professional_claims_GDF2_2_CDF2_2_lean_ingestion ppm-premera-bluecross-history_institutional_claims_GDF2_2_CDF2_2_lean_ingestion for date ingestion 2026-04-06 failed in preprocessor step with error message: File /dataingestionprod/unrestricted/109-premera-bluecross/rawincoming/2026-03-30-102438457/1/136533/20260406/1 does not exist. Can you investigate what's going on? I can see the raw files are avaialablei in hue Raw. Thank you melly Suryani, Melly please see the correct files in question. They are dated 04/06, but they were received on 4/15 as described in the email I attached. prebc_history_institutional_incoming_20260406_1.txt.pgp prebc_history_professional_incoming_20260406_1.txt.pgp Sent a reply to Adam: It seems the files on 20260406 are super small. waiting follow up from Adam. Premera has sent over a new set of files. It appears that these files were successfully received in Axway. Can we please confirm they were loaded correctly? prebc_history_institutional_incoming_20260428_1.txt prebc_history_professional_incoming_20260428_1.txt They also resent the unlinked file as well: prebc_unlinkedadj_incoming_1_20260428.zip Hi Adam, We are still getting an error on the replacement files 4/28. We're taking a closer look... Thank you melly Melly's update 4/30: I can see both header-trailer in the source files: /dataingestionprod/unrestricted/109-premera-bluecross/rawincoming/2026-03-30-91183910/1/136533/src_file_backup/20260428/1/prebc_history_institutional_incoming_20260428_1.txt /dataingestionprod/unrestricted/109-premera-bluecross/rawincoming/2026-03-30-102438457/1/136533/src_file_backup/20260428/1/prebc_history_professional_incoming_20260428_1.txt Pipeline error message: No of columns not matching in Header record or Trailer record. Hi Adam, I got my answer: The reason of the error is because they dont conform with the regular history trailer records because they dont have the date stamp at the end: We received @@TRAILER@@|428 (for institutional) @@TRAILER@@|2002 (for professional). Expected: @@TRAILER@@|428|date time (for institutional) @@TRAILER@@|2002|date time (for professional). Would you mind asking the client for the replacement files? Thanks so much melly Client finally sent their final replacement files and they were processed successfully: prebc_history_institutional_incoming_20260503_1.txt.pgp prebc_history_professional_incoming_20260503_1.txt.pgp | V53: Other | W53: Yes
A54: IT-3009644 | B54: IT-3009644 | D54: Premera - Automated Ack File Appealed Line Sequence Length Clarification | E54: I received the below question from Premera, and was hoping to get some help with the questions highlighted. Thanks! We received an ack file last week (PREBC_appeals_ack_20260417085524) that contained Appealed Line Sequence of 79 characters , while prior guidance indicated a 50‑character maximum . Our system enforced the 50‑character limit, causing processing to fail. We’ve temporarily increased our limit to 255 , but could you please confirm: · Why this field exceeded 50 characters? · What is the expected maximum length going forward? | F54: Premera - Automated Ack File Appealed Line Sequence Length Clarification.msg (111 kB) Nile Production Support doesn't have the validation rules. Production Control team please check and let us know if you need anything on this. Hi Jani, We (Production control) don't process these files. Please check with concerned team. Where does the user see this file (from what application)? Need to know the answer of this question. | H54: Other | I54: Other | K54: On Hold | L54: 2026-04-23 | M54: 2026-04-29 | N54: Nile Production Support | O54: Unassigned | P54: Spinelli, Adam | Q54: Unresolved | R54: Premera - Automated Ack File Appealed Line Sequence Length Clarification.msg (111 kB) Nile Production Support doesn't have the validation rules. Production Control team please check and let us know if you need anything on this. Hi Jani, We (Production control) don't process these files. Please check with concerned team. Where does the user see this file (from what application)? Need to know the answer of this question. | V54: Schema issue
A55: IT-3009150 | B55: IT-3009150 | D55: CareFirst Missing History | E55: CareFirst is reporting that they have 800+ claims that we have invoiced for missing history. CareFirst claims to have sent the claims via History. I have run a few failed claims line reports and I do not see any reason why these would not have processed. CareFirst has confirmed these are all Outpatient claims and the CLCL_Paid_DT field represents the date they sent us the History file. I have attached the report of all claims they were invoiced for as it relates to missing history. The goal of this inquiry is to ensure we received the files, which I am attaching two raw data files. And also if we did receive why did they not process and how can we track any possible file/line failures in the future? The reason this is a concern is that CareFirst is billed for any unreturned history after 180 days. In order to avoid any unnecessary fees, CareFirst would like the opportunity to resolve any missing or failed history prior to the 180 days. Original Email: Subject: RE: Claims Hist Feed>Follow-up From: Thachapilly, Abhilash Abhilash.Thachapilly@carefirst.com To: Snyder, Amery amery.snyder@cotiviti.com CC: Saubhagya.Sarangi@carefirst.com ; McDonald, Christina Christina.McDonald@carefirst.com ; Vinay.Kommera@carefirst.com ; lauren.nunez Lauren.Nunez@carefirst.com ; jenn.livengood Jenn.Livengood@carefirst.com ; jeff.rose@carefirst.com Jeff.Rose@carefirst.com ; Jefferson, Jaclyn Jaclyn.Jefferson@carefirst.com ; Boddu, Srikanth Srikanth.Boddu@carefirst.com Mon 4/13/2026 12:21 PM Good morning Amery! Can you check with team to see why below claims were not loaded to coti history tables? There are almost 800+ claims Invoce team reported as missing paid feed. If Cotiviti runs an error report, we can identify the root cause of the fallouts Attached is the list of all claims reported as missing paid feed. But for an initial analysis below sample from Jul2025 are enough. CLCL_ID CLCL_PAID_DT G18260513300 08-JUL-25 12.00.00.000000000 AM G18816254600 08-JUL-25 12.00.00.000000000 AM G18270181100 08-JUL-25 12.00.00.000000000 AM G18270259300 08-JUL-25 12.00.00.000000000 AM G18270841900 08-JUL-25 12.00.00.000000000 AM G1831A221500 08-JUL-25 12.00.00.000000000 AM G18360231100 08-JUL-25 12.00.00.000000000 AM G18411004200 08-JUL-25 12.00.00.000000000 AM G18411297200 08-JUL-25 12.00.00.000000000 AM G18411863000 08-JUL-25 12.00.00.000000000 AM G18518104000 09-JUL-25 12.00.00.000000000 AM G18813430000 09-JUL-25 12.00.00.000000000 AM G18813811100 09-JUL-25 12.00.00.000000000 AM G18814006500 09-JUL-25 12.00.00.000000000 AM G18814355000 09-JUL-25 12.00.00.000000000 AM G18814363700 09-JUL-25 12.00.00.000000000 AM G18817245400 09-JUL-25 12.00.00.000000000 AM G1881A528200 09-JUL-25 12.00.00.000000000 AM G18910125700 09-JUL-25 12.00.00.000000000 AM G18910994200 09-JUL-25 12.00.00.000000000 AM G18911901800 09-JUL-25 12.00.00.000000000 AM Thanks and regards, Abhilash | F55: carfh_history_incoming_1.07-08-2025_0530.txt (7.95 MB) carfh_history_incoming_1.07-09-2025_0320.txt (10.29 MB) Cotiviti Detail IDR_Feb26 Invoice_CLAIM_IDs.xlsx (31 kB) EXTERNAL RE_ Claims Hist Feed_Follow-up.msg (320 kB) Failed Claim Lines ICMS - CSPRD6.xlsx (182 kB) I’ve started looking into this ticket. From the Nile side, the pipeline processes were completed on 2025-07-08 and 2025-07-09. Due to a data access issue, our onshore team will work on this ticket. /dataingestionprod/raw/restricted/280-carefirst-facets/20250701/carfh_history_professional_incoming_legacy_1_20250701.txt.pgp /dataingestionprod/raw/restricted/280-carefirst-facets/20250702/carfh_history_professional_incoming_legacy_1_20250702.txt.pgp /dataingestionprod/raw/restricted/280-carefirst-facets/20250703/carfh_history_professional_incoming_legacy_1_20250703.txt.pgp /dataingestionprod/raw/restricted/280-carefirst-facets/20250707/carfh_history_professional_incoming_legacy_1_20250707.txt.pgp /dataingestionprod/raw/restricted/280-carefirst-facets/20250708/carfh_history_professional_incoming_legacy_1_20250708.txt.pgp /dataingestionprod/raw/restricted/280-carefirst-facets/20250709/carfh_history_professional_incoming_legacy_1_20250709.txt.pgp /dataingestionprod/raw/restricted/280-carefirst-facets/20250710/carfh_history_professional_incoming_legacy_1_20250710.txt.pgp /dataingestionprod/raw/restricted/280-carefirst-facets/20250711/carfh_history_professional_incoming_legacy_1_20250711.txt.pgp /dataingestionprod/raw/restricted/280-carefirst-facets/20250714/carfh_history_professional_incoming_legacy_1_20250714.txt.pgp /dataingestionprod/raw/restricted/280-carefirst-facets/20250715/carfh_history_professional_incoming_legacy_1_20250715.txt.pgp /dataingestionprod/raw/restricted/280-carefirst-facets/20250716/carfh_history_professional_incoming_legacy_1_20250716.txt.pgp /dataingestionprod/raw/restricted/280-carefirst-facets/20250717/carfh_history_professional_incoming_legacy_1_20250717.txt.pgp /dataingestionprod/raw/restricted/280-carefirst-facets/20250718/carfh_history_professional_incoming_legacy_1_20250718.txt.pgp /dataingestionprod/raw/restricted/280-carefirst-facets/20250721/carfh_history_professional_incoming_legacy_1_20250721.txt.pgp /dataingestionprod/raw/restricted/280-carefirst-facets/20250722/carfh_history_professional_incoming_legacy_1_20250722.txt.pgp /dataingestionprod/raw/restricted/280-carefirst-facets/20250723/carfh_history_professional_incoming_legacy_1_20250723.txt.pgp /dataingestionprod/raw/restricted/280-carefirst-facets/20250724/carfh_history_professional_incoming_legacy_1_20250724.txt.pgp /dataingestionprod/raw/restricted/280-carefirst-facets/20250725/carfh_history_professional_incoming_legacy_1_20250725.txt.pgp /dataingestionprod/raw/restricted/280-carefirst-facets/20250728/carfh_history_professional_incoming_legacy_1_20250728.txt.pgp /dataingestionprod/raw/restricted/280-carefirst-facets/20250729/carfh_history_professional_incoming_legacy_1_20250729.txt.pgp /dataingestionprod/raw/restricted/280-carefirst-facets/20250730/carfh_history_professional_incoming_legacy_1_20250730.txt.pgp /dataingestionprod/restricted/280-carefirst-facets/2023-09-21-119194747/2/file-writer/91020.86504/20250708/1/* | H55: Other | I55: Other | K55: In Progress (HD1) | L55: 2026-04-23 | M55: 2026-04-29 | N55: Nile Production Support | O55: Unassigned | P55: Snyder, Amery | Q55: Unresolved | R55: carfh_history_incoming_1.07-08-2025_0530.txt (7.95 MB) carfh_history_incoming_1.07-09-2025_0320.txt (10.29 MB) Cotiviti Detail IDR_Feb26 Invoice_CLAIM_IDs.xlsx (31 kB) EXTERNAL RE_ Claims Hist Feed_Follow-up.msg (320 kB) Failed Claim Lines ICMS - CSPRD6.xlsx (182 kB) I’ve started looking into this ticket. From the Nile side, the pipeline processes were completed on 2025-07-08 and 2025-07-09. Due to a data access issue, our onshore team will work on this ticket. /dataingestionprod/raw/restricted/280-carefirst-facets/20250701/carfh_history_professional_incoming_legacy_1_20250701.txt.pgp /dataingestionprod/raw/restricted/280-carefirst-facets/20250702/carfh_history_professional_incoming_legacy_1_20250702.txt.pgp /dataingestionprod/raw/restricted/280-carefirst-facets/20250703/carfh_history_professional_incoming_legacy_1_20250703.txt.pgp /dataingestionprod/raw/restricted/280-carefirst-facets/20250707/carfh_history_professional_incoming_legacy_1_20250707.txt.pgp /dataingestionprod/raw/restricted/280-carefirst-facets/20250708/carfh_history_professional_incoming_legacy_1_20250708.txt.pgp /dataingestionprod/raw/restricted/280-carefirst-facets/20250709/carfh_history_professional_incoming_legacy_1_20250709.txt.pgp /dataingestionprod/raw/restricted/280-carefirst-facets/20250710/carfh_history_professional_incoming_legacy_1_20250710.txt.pgp /dataingestionprod/raw/restricted/280-carefirst-facets/20250711/carfh_history_professional_incoming_legacy_1_20250711.txt.pgp /dataingestionprod/raw/restricted/280-carefirst-facets/20250714/carfh_history_professional_incoming_legacy_1_20250714.txt.pgp /dataingestionprod/raw/restricted/280-carefirst-facets/20250715/carfh_history_professional_incoming_legacy_1_20250715.txt.pgp /dataingestionprod/raw/restricted/280-carefirst-facets/20250716/carfh_history_professional_incoming_legacy_1_20250716.txt.pgp /dataingestionprod/raw/restricted/280-carefirst-facets/20250717/carfh_history_professional_incoming_legacy_1_20250717.txt.pgp /dataingestionprod/raw/restricted/280-carefirst-facets/20250718/carfh_history_professional_incoming_legacy_1_20250718.txt.pgp /dataingestionprod/raw/restricted/280-carefirst-facets/20250721/carfh_history_professional_incoming_legacy_1_20250721.txt.pgp /dataingestionprod/raw/restricted/280-carefirst-facets/20250722/carfh_history_professional_incoming_legacy_1_20250722.txt.pgp /dataingestionprod/raw/restricted/280-carefirst-facets/20250723/carfh_history_professional_incoming_legacy_1_20250723.txt.pgp /dataingestionprod/raw/restricted/280-carefirst-facets/20250724/carfh_history_professional_incoming_legacy_1_20250724.txt.pgp /dataingestionprod/raw/restricted/280-carefirst-facets/20250725/carfh_history_professional_incoming_legacy_1_20250725.txt.pgp /dataingestionprod/raw/restricted/280-carefirst-facets/20250728/carfh_history_professional_incoming_legacy_1_20250728.txt.pgp /dataingestionprod/raw/restricted/280-carefirst-facets/20250729/carfh_history_professional_incoming_legacy_1_20250729.txt.pgp /dataingestionprod/raw/restricted/280-carefirst-facets/20250730/carfh_history_professional_incoming_legacy_1_20250730.txt.pgp /dataingestionprod/restricted/280-carefirst-facets/2023-09-21-119194747/2/file-writer/91020.86504/20250708/1/* | V55: File Missing
A56: IT-3008418 | B56: IT-3008418 | D56: Monthly uhc - cosmos pipeline failed for 2026/04 | E56: Pipeline name: dm-uhc-cosmos-actian_migration_dscnttype dm-uhc-cosmos-actian_migration_HcccCd | H56: Other | I56: Other | K56: Open | L56: 2026-04-23 | M56: 2026-04-23 | N56: Nile Production Support | O56: Unassigned | P56: Limbu, Sajan | Q56: Unresolved | V56: Pipeline Schedule
A57: IT-3008305 | B57: IT-3008305 | D57: Update the tracker with the newly deployed History and TBA Lean Ingestion pipelines for Oscar-Homegrown that are now live in production. | E57: Hello Jani, Shaik , The History pipelines for Oscar-Homegrown have been successfully deployed to production. Please update the tracker with the new pipelines. Details of the old and new pipelines are provided below. 2024-03-12-76144063 -> 2026-04-08-75711996 report: 2026-04-08-86206946 2024-03-12-76123265 -> 2026-04-08-74423010 report: 2026-04-08-85983173 2024-03-12-75948469 -> 2026-04-10-115454593 report: 2026-04-13-91286715 2024-03-12-75890753 -> 2026-04-10-114013583 report: 2026-04-13-91025017 Thank You | G57: Details recorded accordingly. | H57: Other | I57: Other | K57: Closed | L57: 2026-04-23 | M57: 2026-04-29 | N57: Nile Production Support | O57: Unassigned | P57: Karakavalasa, SriVarshini | Q57: Resolved | V57: Other | W57: Yes
A58: IT-3008084 | B58: IT-3008084 | D58: Peer Review for Aetna-Trad-SCM BMC pipeline Optimization | E58: Review all the required conditions for the BMC/child pipelines: Prechecks pipeline version to be updated to Latest Remove unwanted parameters from the pipeline All the child pipelines need to be published BMC pipeline needs to be published and Scheduled/Subscribe option need to be enabled. Update all the prod documents with latest pipeline versions. | F58: Hi Kamsetty, Sravani , Verified that all child pipelines have been published successfully. | G58: Verified that all child pipelines are published, ensuring the latest versions are used when running the BMC pipelines. | H58: Other | I58: Other | K58: Closed | L58: 2026-04-23 | M58: 2026-04-24 | N58: Nile Production Support | O58: Unassigned | P58: Kamsetty, Sravani | Q58: Done | R58: Hi Kamsetty, Sravani , Verified that all child pipelines have been published successfully. | V58: Other | W58: Yes
A59: IT-3007910 | B59: IT-3007910 | D59: WellCare RCA ARK Client Transition. | E59: WellCare RCA ARK Client Transition. | G59: Transition Completed successfully. | H59: Other | I59: Other | K59: Closed | L59: 2026-04-23 | M59: 2026-04-23 | N59: Nile Production Support | O59: Unassigned | P59: Jani, Shaik | Q59: Resolved | V59: Other | W59: Yes
A60: IT-3007255 | B60: IT-3007255 | D60: Copy 2 Aetna Trad files from dataingestionprod/ to dataingestiondev/ | E60: Hello, I would like to copy 2 files from dataingestionprod/ to dataingestiondev/ in HDFS. Server is nile prod. Please see attached for files and copy destinations. Ping me with any questions. Thank you. | F60: Data request - monthly Provider and Member files - Aenta Trad.xlsx (11 kB) Hi Maguire, Patrick Files copied please verify Thanks | G60: Files Copied | H60: Other | I60: Other | K60: Closed | L60: 2026-04-22 | M60: 2026-04-23 | N60: Nile Production Support | O60: Unassigned | P60: Maguire, Patrick | Q60: Resolved | R60: Data request - monthly Provider and Member files - Aenta Trad.xlsx (11 kB) Hi Maguire, Patrick Files copied please verify Thanks | V60: Issue Platform
A61: IT-3005937 | B61: IT-3005937 | D61: Please add these two pipelines in the tracking sheet.. | E61: Hi Jani, Would you mind adding these two pipelines in the tracking sheet? dm-excellus-actian_migration_caqh (weekly pipeline) I remember we use to monitor this but for some reason we couldn’t find it yesterday. The second one is this: rccv-optumcare-facets-TIN_exclusion_file It is noted as “Adhoc”, so I am not sure how we can get it tracked. Thank you in advance, Jani, melly | G61: Updated the details in tracker. | H61: Other | I61: Other | K61: Closed | L61: 2026-04-22 | M61: 2026-04-23 | N61: Nile Production Support | O61: Unassigned | P61: Suryani, Melly | Q61: Resolved | V61: Other | W61: Yes
A62: IT-3005392 | B62: IT-3005392 | D62: HCSC_BackFill_Set_1_files process. | F62: we already proceed the set1 files and completed. | G62: we got the confirmation from the user and closed this ticket. | H62: Other | I62: Other | K62: Closed | L62: 2026-04-22 | M62: 2026-04-24 | N62: Nile Production Support | O62: Unassigned | P62: Kantimahanti, Ravisankar | Q62: Done | R62: we already proceed the set1 files and completed. | V62: Other | W62: Yes
A63: IT-3005387 | B63: IT-3005387 | D63: [harvardpilgrim - ohi]-Update prechecks for BMC and publish all the child pipelines. | E63: Update precheck with pipeline version as latest and remove all the unnecessary parameters from the pipeline. Publish all the child pipelines and modify subscribe BMC pipeline versions to latest. | F63: I have implemented the BMC optimization for the clients assigned to me. | G63: I have implemented the BMC optimization for the clients assigned to me. | H63: Other | I63: Other | K63: Closed | L63: 2026-04-22 | M63: 2026-05-05 | N63: Nile Production Support | O63: Unassigned | P63: Kantimahanti, Ravisankar | Q63: Resolved | R63: I have implemented the BMC optimization for the clients assigned to me. | V63: Other | W63: Yes
A64: IT-3005308 | B64: IT-3005308 | D64: OLA Configuration Changes and Monitoring on cigna-cghb-rca-prepay | E64: I have made configuration changes in OLA, including adding buffer time. I will monitor a few executions and confirm that the changes are working as expected. | F64: Buffer time has been added, and I will monitor the OLA warnings. The warnings on OLA monitoring are not valid, made some changes on config, will monitor one more day to conclude I found some issues with the spooler configuration. I will monitor it for the next few days. Monitoring OLA | H64: Other | I64: Other | K64: On Hold | L64: 2026-04-22 | M64: 2026-05-05 | N64: Nile Production Support | O64: Unassigned | P64: Bhattarai, Krishna | Q64: Unresolved | R64: Buffer time has been added, and I will monitor the OLA warnings. The warnings on OLA monitoring are not valid, made some changes on config, will monitor one more day to conclude I found some issues with the spooler configuration. I will monitor it for the next few days. Monitoring OLA | V64: Configuration Issue
A65: IT-3005302 | B65: IT-3005302 | D65: OLA Configuration Changes and Monitoring on Securityhealth - qnxt | E65: I have made configuration changes in OLA, including adding buffer time. I will monitor a few executions and confirm that the changes are working as expected. | F65: Date 04/14–> Buffer time has been added, and I will monitor the OLA warnings. Securityheath - tba - Professional Issue on 04/16--> The warning is valid as file arrived lately Issue on 04/18--> The warning is valid as file arrived lately Securityheath - tba - Institutional Issue on 04/18--> The warning is valid as file arrived lately config updated Monitoring OLA | H65: Other | I65: Other | K65: On Hold | L65: 2026-04-22 | M65: 2026-05-05 | N65: Nile Production Support | O65: Unassigned | P65: Bhattarai, Krishna | Q65: Unresolved | R65: Date 04/14–> Buffer time has been added, and I will monitor the OLA warnings. Securityheath - tba - Professional Issue on 04/16--> The warning is valid as file arrived lately Issue on 04/18--> The warning is valid as file arrived lately Securityheath - tba - Institutional Issue on 04/18--> The warning is valid as file arrived lately config updated Monitoring OLA | V65: Configuration Issue
A66: IT-3005125 | B66: IT-3005125 | D66: Daily pipeline tricm tba professional pipeline is getting failed for 2026/04/21 | E66: Pipeline is picking two files where only one file is expected. It is picking up 0 byte pgp file in addition to regular file. Please investigate and help fix the issue. Pipeline name: ppm -triples-tricm-tba_professional_claims_GDF2_9_CDF2_9_Slim_Refactoring | F66: 0 byte files received and blocking the ingestion, deleted the file from raw location and File processed successfully. | G66: 0 byte files received and blocking the ingestion, deleted the file from raw location and File processed successfully. | H66: Other | I66: Other | K66: Closed | L66: 2026-04-21 | M66: 2026-04-22 | N66: Nile Production Support | O66: Unassigned | P66: Kandel, Amik | Q66: Resolved | R66: 0 byte files received and blocking the ingestion, deleted the file from raw location and File processed successfully. | V66: Pipeline Schedule
A67: IT-3004600 | B67: IT-3004600 | D67: TXCHP Professional Institutional/TBA & History Files Failing 4/21/2026 | E67: Hi Nile, TXCHP files are continuing to actively fail. Can you please check with the client as they are sending files that have already been processed in our database with the same sequence number. SEQ# 334 txchp_ophistory_incoming_1.04-21-2026_1726--> txchp_daily_incoming_1.11-01-2025_1739 SEQ# 352 txchp_history_incoming_1.04-21-2026_1726--> txchp_daily_incoming_1.11-08-2025_1550 SEQ# 333 txchp_history_incoming_1.04-21-2026_1640--> txchp_outpatient_incoming_1.11-01-2025_1739 SEQ# 327 txchp_ophistory_incoming_1.04-21-2026_1640--> txchp_outpatient_incoming_1.10-29-2025_1550 SEQ# 315 txchp_history_incoming_1.04-21-2026_1605--> txchp_outpatient_incoming_1.10-25-2025_1550 SEQ# 328 txchp_history_incoming_1.04-21-2026_1600--> txchp_daily_incoming_1.10-29-2025_1550 SEQ# 351 txchp_ophistory_incoming_1.04-21-2026_1600--> txchp_outpatient_incoming_1.11-08-2025_1555 SEQ# 359 txchp_history_incoming_1.04-21-2026_1800--> txchp_ophistory_incoming_1.11-11-2025_1830 SEQ# 357 txchp_ophistory_incoming_1.04-21-2026_1800--> txchp_daily_incoming_1.11-11-2025_1550 SEQ# 363 txchp_history_incoming_1.04-21-2026_1835--> txchp_outpatient_incoming_1.11-12-2025_1553 SEQ# 362 txchp_ophistory_incoming_1.04-21-2026_1840--> Not loaded in DB SEQ# 321 txchp_daily_incoming_1.04-21-2026_1600--> txchp_daily_incoming_1.10-28-2025_1621 SEQ# 317 txchp_daily_incoming_1.04-21-2026_1645--> txchp_outpatient_incoming_1.10-26-2025_1550 SEQ# 318 txchp_outpatient_incoming_1.04-21-2026_1600--> txchp_daily_incoming_1.10-26-2025_1550 SEQ#366 txchp_history_incoming_1.04-21-2026_1915--> txchp_daily_incoming_1.11-13-2025_1600 SEQ# 364 txchp_ophistory_incoming_1.04-21-2026_1925--> txchp_daily_incoming_1.11-12-2025_1553 SEQ#381 txchp_history_incoming_1.04-21-2026_2030--> txchp_daily_incoming_1.11-19-2025_1550 SEQ#380 txchp_ophistory_incoming_1.04-21-2026_2040--> Not loaded in DB | F67: Adding 2 more files txchp_ophistory_incoming_1.04-21-2026_2040 txchp_history_incoming_1.04-21-2026_2030 Communication from email thread: Re: IT-3004600 - TXCHP Institutional/TBA & History Files Failing 4/21/2026 Hi @Moorefield, Mia, Looks like these are test files but files came as regular files to Nile QC environment and processed by Nile Successfully. Due to incorrect file name (missing test in file name pattern) while processing in Production Control ,files are moved to Production DB instead of QC DB. Can you please send the files with processing naming standards TBA file name pattern History file name pattern please let us know if you need any additional information. Hi Daniels, Ben now i think we are good with qc files for txchp please let me know Thanks | H67: Other | I67: Other | K67: In Progress (HD1) | L67: 2026-04-21 | M67: 2026-05-07 | N67: Nile Production Support | O67: Unassigned | P67: Daniels, Ben | Q67: Unresolved | R67: Adding 2 more files txchp_ophistory_incoming_1.04-21-2026_2040 txchp_history_incoming_1.04-21-2026_2030 Communication from email thread: Re: IT-3004600 - TXCHP Institutional/TBA & History Files Failing 4/21/2026 Hi @Moorefield, Mia, Looks like these are test files but files came as regular files to Nile QC environment and processed by Nile Successfully. Due to incorrect file name (missing test in file name pattern) while processing in Production Control ,files are moved to Production DB instead of QC DB. Can you please send the files with processing naming standards TBA file name pattern History file name pattern please let us know if you need any additional information. Hi Daniels, Ben now i think we are good with qc files for txchp please let me know Thanks | V67: File Issue
A68: IT-3004426 | B68: IT-3004426 | D68: Humana PMDM File Ingestion Setup | E68: Creating ticket per Joy’s request. What is the request? Ingest PMDM files into SQL tables, What files do you need Nile to ingest and create spoolers and pipelines? What is the file name? The PMDM extract is now two CSV files compressed into a single zip named PMDM_YYYYMM.zip. When you extract the zip file, you will see the two individual files as shown below. prov_ntwk_YYYYMM prov_pymt_ctrct_dly_YYYYMM Please provide data dictionary in the ticket. The final updates to the ETL and Guide are being completed and will be sent to Cotiviti by EOW, It seems Humana posted two file patterns for Cotiviti to work on. prov_pymt_ctrct_dly_* prov_ntwk_Historical_* Are these two file patterns for Humana PMDM? How many kinds of files that we need to process for PMDM (because the dictionary said we should get PMDM_YYYYMM)? 1 , This 1 st FTP includes historical data thru March2026. The 4/9 email screenshot below details what is included in each file. These files include data from the past 18 months, along with all related contracts from previous years that fall within that 18-month period. 2, Going forward with April2026 data next month the PMDM extract will be sent with the below naming convention (2 CSV files inside the zip file - PMDM_YYYYMM). prov_ntwk_YYYYMM prov_pymt_ctrct_dly_YYYYMM Where do you need this data ingested to? What SQL server, database and table names? Table = CnlyProvider For the PMDM file, it has never been used by RCA. A new Table would need to be created (Need to confirm with Sajjan). Field Updates to be in Decipher Screens to be updated: Claims Header/Claims Detail, & ACE What date in the month that the PMDM file(s) will arrive? Sent monthly on the 5th When will we expect to receive the monthly files? The files you just received has all PMDM data thru March2026. You will receive April2026 data on your regular schedule which will be the 5 th of each month. How would we receive the files? The PMDM file was FTP’d to Cotiviti on 4/7 and the just resent yesterday 4/20 per the client. Will they send to use? Do we need to download from their SFTP site? Yes, files will be delivered at the same location as other Humana files are received today. Regular site https://st.humana.com/ Non-production site https://qa-st.humana.com/ | F68: R2B2 Ticket reference [RCASA-74509] Humana - Enhance PMDM Monthly File Ingestion to Support Three New Specialty Fields - R&D Jira - WDC Updated Data Dictionary from client located here: Humana Supplemental Data Extract Guide_4.0 | H68: Other | I68: Other | K68: In Progress (HD1) | L68: 2026-04-21 | M68: 2026-05-06 | N68: Nile Production Support | O68: Unassigned | P68: Franklin, Maria | Q68: Unresolved | R68: R2B2 Ticket reference [RCASA-74509] Humana - Enhance PMDM Monthly File Ingestion to Support Three New Specialty Fields - R&D Jira - WDC Updated Data Dictionary from client located here: Humana Supplemental Data Extract Guide_4.0 | V68: Configuration Issue
A69: IT-3004277 | B69: IT-3004277 | D69: Copy data from QC hdfs to Dev hdfs - Nile | E69: Hello Team : Need your help in copying GDF data for UHC cosmos for 202510 from QC to Dev and update permissioning. Please find below details Source path: /dataingestionqc/unrestricted/18-uhc-cosmos/Processed/GDF/claims/medical/postcheck/202510_1/ Target path (new): /dataingestiondev/unrestricted/18-*/Processed/GDF/claims/medical/postcheck/ Please do reach out to me in case of any questions. Thanks. | F69: Hi Prasad, Nirav Data Copied please verify hdfs dfs -cp /dataingestionqc/unrestricted/18-uhc-cosmos/Processed/GDF/claims/medical/postcheck/202510_1 /dataingestiondev/unrestricted/18-uhc-cosmos/Processed/GDF/claims/medical/postcheck hdfs dfs -chown -R svcddataunrestricted /dataingestiondev/unrestricted/18-uhc-cosmos/Processed/GDF/claims/medical/postcheck/ hdfs dfs -chgrp -R devunrestricted /dataingestiondev/unrestricted/18-uhc-cosmos/Processed/GDF/claims/medical/postcheck/ hdfs dfs -chmod -R 770 /dataingestiondev/unrestricted/18-uhc-cosmos/Processed/GDF/claims/medical/postcheck/ | G69: Data Copied | H69: Other | I69: Other | K69: Closed | L69: 2026-04-21 | M69: 2026-04-22 | N69: Nile Production Support | O69: Unassigned | P69: Prasad, Nirav | Q69: Resolved | R69: Hi Prasad, Nirav Data Copied please verify hdfs dfs -cp /dataingestionqc/unrestricted/18-uhc-cosmos/Processed/GDF/claims/medical/postcheck/202510_1 /dataingestiondev/unrestricted/18-uhc-cosmos/Processed/GDF/claims/medical/postcheck hdfs dfs -chown -R svcddataunrestricted /dataingestiondev/unrestricted/18-uhc-cosmos/Processed/GDF/claims/medical/postcheck/ hdfs dfs -chgrp -R devunrestricted /dataingestiondev/unrestricted/18-uhc-cosmos/Processed/GDF/claims/medical/postcheck/ hdfs dfs -chmod -R 770 /dataingestiondev/unrestricted/18-uhc-cosmos/Processed/GDF/claims/medical/postcheck/ | V69: Other | W69: Yes
A70: IT-3004275 | B70: IT-3004275 | D70: Please schedule the spooler accentsep-sodexo-inc96L3-CDL | E70: Please schedule the spooler accentsep-sodexo-inc96L3-CDL . This is monthly file. we will get file from the client between 10th to 20th of the month. | F70: Scheduled Run every hour between 10th and 20th of the month. 0 0/1 10-20 * * Will followup again see if it works in May. Pipeline is not schedule accent-separation-anthem-Sodexo-inc96L3-CDL Pipeline accent-separation-anthem-Sodexo-inc96L3-CDL Also scheduled: 5/1 * 10-20 * * | G70: both spooler and pipeline scheduled | H70: Other | I70: Other | K70: Closed | L70: 2026-04-21 | M70: 2026-04-30 | N70: Nile Production Support | O70: Unassigned | P70: Nekkanti, Alekya | Q70: Resolved | R70: Scheduled Run every hour between 10th and 20th of the month. 0 0/1 10-20 * * Will followup again see if it works in May. Pipeline is not schedule accent-separation-anthem-Sodexo-inc96L3-CDL Pipeline accent-separation-anthem-Sodexo-inc96L3-CDL Also scheduled: 5/1 * 10-20 * * | V70: Spooler issue
A71: IT-3004238 | B71: IT-3004238 | D71: Healthspring DM 5381 - Claim Date Spans Showing on All Lines in Detail Decipher Screens | E71: After some investigating it appears the issues needs to be fixed at the Nile level or whatever pushes the Raw tables to SQL Stg. I need NILE to load the DOS (line_service_to_date) field from the RAW tables to the detail tables. Both dates need in the attached example to be fixed by Nile. The Excel worksheet provided and the query results that I pasted clearly shows that both values are wrong for this particular claim. Note: in the second image, all lines are showing the date range, we are looking specific date of service to each claim line. Query for attached table. SELECT TOP (1000) CnlyClaimNum , LineNum , LineBeginDOS , LineEndDOS FROM [HealthSpringDataClaimDetail] . [dbo] . [CnlyClaimsDetail] WHERE 1=1 ANDCnlyClaimNum='24E162751100' SELECT TOP (1000) CnlyClaimId , ClaimLine , FromDate , ThroughDate FROM [HealthSpringDataRaw] . [dbo] . [ProfessionalClaims_Load_New] WHERE 1=1 ANDCnlyClaimId='24E162751100' Reference: RCASA-69496 | F71: we want to discuss about this ticket get more inputs from the user. | H71: HC RCA PROD Support | I71: Other | K71: On Hold | L71: 2026-04-21 | M71: 2026-05-05 | N71: Nile Production Support | O71: Unassigned | P71: Price, Ryon | Q71: Unresolved | R71: we want to discuss about this ticket get more inputs from the user. | V71: Data Issue
A72: IT-3004202 | B72: IT-3004202 | D72: bcbsnc_crosswalk spooler update | E72: update this spooler bcbsnc_crosswalk with wildcard. currently it is hardcoded CrosswalkNCProf_20260201_20260320.csv.pgp We have already received this month file CrosswalkNCProf_20260301_20260420.csv.pgp | G72: Updated the spoolr. Corrected the file name pattern and tested if it will spool both prof and inst file | H72: Other | I72: Other | K72: Closed | L72: 2026-04-21 | M72: 2026-04-21 | N72: Nile Production Support | O72: Unassigned | P72: Easley, Keaton | Q72: Resolved | V72: Spooler issue
A73: IT-3004125 | B73: IT-3004125 | D73: Excellus CAQH: [20260417 - prod - dm-excellus-actian_migration_caqh] Please Hold until we receive missing files from week of 04/10 | E73: Hello Team , Please hold pipeline [*prod - dm-excellus-actian_migration_caqh*] until we receive missing files from week of 04/10. | F73: Waiting on missing files | H73: Other | I73: Other | K73: On Hold | L73: 2026-04-21 | M73: 2026-05-05 | N73: Nile Production Support | O73: Unassigned | P73: Hirpara, Meera | Q73: Unresolved | R73: Waiting on missing files | V73: File Missing
A74: IT-3004101 | B74: IT-3004101 | D74: Error when running Humana BMC pipeline: trigger_bmc_workflow_CHC_HUMANA_MTH_DATALOADMEMBER_NILE_monthly | E74: Hi Nile PS Triage Team, When I press the execute button for the pipeline above, it immediately throws an error (snapshot). Would you mind taking a look? Thank you melly | F74: There is an issue in the precheck conditions, Modified and published the pipeline version v1.2 Also, updated the pipeline with latest precheck condition and removed unwanted parameters from pipeline. Pipeline changed to EDA and subscriber enabled. BMC triggered for 202604 Thanks. | G74: Pipeline processed successfully. | H74: Other | I74: Other | K74: Closed | L74: 2026-04-21 | M74: 2026-04-22 | N74: Nile Production Support | O74: Unassigned | P74: Suryani, Melly | Q74: Resolved | R74: There is an issue in the precheck conditions, Modified and published the pipeline version v1.2 Also, updated the pipeline with latest precheck condition and removed unwanted parameters from pipeline. Pipeline changed to EDA and subscriber enabled. BMC triggered for 202604 Thanks. | V74: Other | W74: Yes
A75: IT-3003713 | B75: IT-3003713 | D75: Update Production spooler late cron check | E75: Hi Team, Could you please update the notouch spooler in production for Wellcare with value - 0 14 * * TUE Spooler name - Wellcare-Wellcare_Actian_PBM_MTH_notouch Thanks, Shilpa Anna | F75: late cron has been updated Will close once demo is done | G75: Edited schedule and late cron for this spooler | H75: Other | I75: Other | K75: Closed | L75: 2026-04-21 | M75: 2026-04-23 | N75: Nile Production Support | O75: Unassigned | P75: Varghese, Shilpa Anna | Q75: Resolved | R75: late cron has been updated Will close once demo is done | V75: Spooler issue
A76: IT-3003394 | B76: IT-3003394 | D76: Medical Codes Library Document Submission | E76: Please add the attached table (DX Code Laterality Table) to the Medical Codes Library (MCL). Table is needed for Spotcheck content logic. | F76: DX Code Laterality Table.xlsx (1.39 MB) Hi Kamsetty, Sravani . This is a new table and will require a new pipeline. The DDL for this table is: CREATE TABLE [dbo] . [DxCodeLaterality] ( [DiagCode] [varchar] (10) NULL, [Category] [varchar] (300) NULL, [SubCategory] [varchar] (300) NULL, [Description] [varchar] (1000) NULL, [Source] [varchar] (500) NULL, [Laterality] [varchar] (20) NULL, [LastUpdateUser] [varchar] (100) NULL, [SFileDate] [smalldatetime] NULL, [SFilename] [varchar] (100) NULL, [AutoId] [int] IDENTITY(1,1) NOT NULL ) The source file has been saved to this location: Y:\Ftp\B2B\MCL-NILE\DxCodeLaterality\2026-04-01\DX Code Laterality Table.xlsx Per requestor, the data should be loaded in Append mode. Please let me know if you have any questions. Thanks. Mike Hi Deynarian, Michael , Thanks for the info. I started working on the new pipeline and all the required configurations in nile. Thanks. Hi Deynarian, Michael , Data has been loaded to table. Could you verify and confirm please. hello Kamsetty, Sravani . I have reviewed the table and it looks good. Thank you for getting this done so quickly! You can close this ticket. Mike Hi Deynarian, Michael , Migrated all the required configurations to production. Closing the ticket. | G76: All the required configurations are completed and tested in dev environment. Mike validated and confirmed to close the ticket. Migrated all the configs to production. | H76: Other | I76: Other | K76: Closed | L76: 2026-04-21 | M76: 2026-04-29 | N76: Nile Production Support | O76: Unassigned | P76: Pineo, Rob | Q76: Resolved | R76: DX Code Laterality Table.xlsx (1.39 MB) Hi Kamsetty, Sravani . This is a new table and will require a new pipeline. The DDL for this table is: CREATE TABLE [dbo] . [DxCodeLaterality] ( [DiagCode] [varchar] (10) NULL, [Category] [varchar] (300) NULL, [SubCategory] [varchar] (300) NULL, [Description] [varchar] (1000) NULL, [Source] [varchar] (500) NULL, [Laterality] [varchar] (20) NULL, [LastUpdateUser] [varchar] (100) NULL, [SFileDate] [smalldatetime] NULL, [SFilename] [varchar] (100) NULL, [AutoId] [int] IDENTITY(1,1) NOT NULL ) The source file has been saved to this location: Y:\Ftp\B2B\MCL-NILE\DxCodeLaterality\2026-04-01\DX Code Laterality Table.xlsx Per requestor, the data should be loaded in Append mode. Please let me know if you have any questions. Thanks. Mike Hi Deynarian, Michael , Thanks for the info. I started working on the new pipeline and all the required configurations in nile. Thanks. Hi Deynarian, Michael , Data has been loaded to table. Could you verify and confirm please. hello Kamsetty, Sravani . I have reviewed the table and it looks good. Thank you for getting this done so quickly! You can close this ticket. Mike Hi Deynarian, Michael , Migrated all the required configurations to production. Closing the ticket. | V76: Other | W76: Yes
A77: IT-3002800 | B77: IT-3002800 | D77: prebc_history both inst & prof failed for data date 04/06 | E77: Both the Premera history pipelines for data date 04/06 have failed. The files are available in the spooler, but the pipelines are not able to pick up the files. Could you please analyze the files and check if there are any issues causing the pipelines to not detect or process them? | F77: Hi, Since we are trying to ingest the previous period of files, hash key generated by latest ingest date should be smaller than the actual run hash key. So, need to modify spooler required to NO. Files ingestion is failing due to required missing header/trailer records. Please ask for replacement files. Thanks. | G77: Files ingestion is failing due to required missing header/trailer records. Please ask for replacement files. | H77: Other | I77: Other | K77: Closed | L77: 2026-04-21 | M77: 2026-04-23 | N77: Nile Production Support | O77: Unassigned | P77: Raya, Birajan | Q77: Resolved | R77: Hi, Since we are trying to ingest the previous period of files, hash key generated by latest ingest date should be smaller than the actual run hash key. So, need to modify spooler required to NO. Files ingestion is failing due to required missing header/trailer records. Please ask for replacement files. Thanks. | V77: Spooler issue
A78: IT-3002556 | B78: IT-3002556 | D78: Pipeline bcbsnjhorizon_facets_no_touch not picking up spooled files – File does not exist error | E78: the pipeline bcbsnjhorizon_facets_no_touch . The spooler was manually executed, and the files were successfully spooled. However, after triggering the pipeline, it is still not able to pick up the files. The following error is observed: "File /dataingestionprod/restricted/273-bcbsnjhorizon-facets/rawincoming/2023-11-07-64453041/1.1/1/20260417/1 does not exist." Kindly verify the file path, file availability, and any possible path or permission issues causing the pipeline to not detect the spooled files. | F78: we fixed the issue and successfully processed the pipeline for 20260417 data date. we fixed the issue and processed the pipeline. | G78: we fixed the issue and processed the pipeline. | H78: Other | I78: Other | K78: Closed | L78: 2026-04-21 | M78: 2026-04-24 | N78: Nile Production Support | O78: Unassigned | P78: Raya, Birajan | Q78: Resolved | R78: we fixed the issue and successfully processed the pipeline for 20260417 data date. we fixed the issue and processed the pipeline. | V78: Spooler issue
A79: IT-3002267 | B79: IT-3002267 | D79: [Aetna-Trad-SCM]-Update prechecks for BMC and publish all the child pipelines. | E79: Update precheck with pipeline version as latest and remove all the unnecessary parameters from the pipeline. Publish all the child pipelines and modify subscribe BMC pipeline versions to latest. | F79: BMC Pipeline prechecks conditions for pipeline version is updated to latest for all the 78 pipeline ID's. Published all the 78 child pipelines. Published and scheduled the latest BMC version pipeline. FYI: trigger_bmc_workflow_CHC_AETNA_WKY_SCM_NILE Version: V1.3 | G79: BMC Pipeline prechecks conditions for pipeline version is updated to latest. Published and scheduled the latest BMC version pipeline. FYI: trigger_bmc_workflow_CHC_AETNA_WKY_SCM_NILE Version: V1.3 | H79: Other | I79: Other | K79: Closed | L79: 2026-04-20 | M79: 2026-04-29 | N79: Nile Production Support | O79: Unassigned | P79: Kamsetty, Sravani | Q79: Resolved | R79: BMC Pipeline prechecks conditions for pipeline version is updated to latest for all the 78 pipeline ID's. Published all the 78 child pipelines. Published and scheduled the latest BMC version pipeline. FYI: trigger_bmc_workflow_CHC_AETNA_WKY_SCM_NILE Version: V1.3 | V79: Other | W79: Yes
A80: IT-3002260 | B80: IT-3002260 | D80: dm-bcbs_ma-actian_migration_caqh Pipeline Failed – Mandatory Files Not Recognized | E80: The pipeline dm-bcbs_ma_bcbs_ma-actian_migration_caqh_and_bmc_workflow_CHC_BCBS_MA_ADH_CAQH_Load_NILE has failed during execution. The error message observed is: "Exiting Process with failure. Not all mandatory source files are present for Period: 20260331. No sub-stage(s) should run." However, upon verification, the required source files appear to be available in the expected source location with valid file sizes. Request: Kindly investigate why the pipeline is unable to detect the mandatory source files despite their presence in the source path. Please verify file naming, file availability checks, and source configuration for Period 20260331 . Impact: The pipeline execution is currently blocked due to the mandatory file validation failure, preventing further downstream processing. | F80: Filename pattern changed from CAQH file.* to CAQH File.* Ran the pipeline using override parameters and completed successfully. | G80: Filename pattern changed from CAQH file.* to CAQH File.* Ran the pipeline using override parameters and completed successfully. | H80: Other | I80: Other | K80: Closed | L80: 2026-04-20 | M80: 2026-04-21 | N80: Nile Production Support | O80: Unassigned | P80: Raya, Birajan | Q80: Resolved | R80: Filename pattern changed from CAQH file.* to CAQH File.* Ran the pipeline using override parameters and completed successfully. | V80: Pipeline Schedule
A81: IT-3001908 | B81: IT-3001908 | D81: BCBS_AL COMM - Suspend Pharmacy pipeline | E81: Hello, Please shut down BCBS_AL COMM Pharmacy pipeline: prod - dm-bcbsalcomm-custom-actian_migration_pharmacy Because the client will no longer be sending this file. Thank you | F81: Adding this email screenshot as a proof of approval by Director of Audit Ops, Rx - Paul Saxon, stating that the Pharmacy file would not be required to complete the audit. dm-bcbsalcomm-custom-actian_migration_pharmacy pipelines has been suspended and the rest of the files have been ingested. | G81: dm-bcbsalcomm-custom-actian_migration_pharmacy pipelines have been suspended and the rest of the files have been ingested. | H81: Other | I81: Other | K81: Closed | L81: 2026-04-20 | M81: 2026-04-21 | N81: Nile Production Support | O81: Unassigned | P81: Shrestha, Sajjan | Q81: Resolved | R81: Adding this email screenshot as a proof of approval by Director of Audit Ops, Rx - Paul Saxon, stating that the Pharmacy file would not be required to complete the audit. dm-bcbsalcomm-custom-actian_migration_pharmacy pipelines has been suspended and the rest of the files have been ingested. | V81: Other | W81: Yes
A82: IT-3001338 | B82: IT-3001338 | D82: Copy files From Nile Prod Raw path to Nile QC Raw path - UHC-CSP | E82: Hi Team, Could you please copy all the data for the date given below from the Nile PROD raw path to the Nile QC raw path? 20260412 Nile PROD RAW PATH (Source): /dataingestionprod/raw/restricted/19-uhc-csp Nile QC RAW PATH (Target): /dataingestionqc/raw/restricted/19-uhc-csp Once copied to QC, the owner should be set to "svcpnilediqcraw" and group should be set to "qcunrestricted" and permissions should be 750. | F82: Hi Pati, Jagadeesh Chandra Files copied please verify | G82: Files Copied | H82: Other | I82: Other | K82: Closed | L82: 2026-04-20 | M82: 2026-04-20 | N82: Nile Production Support | O82: Unassigned | P82: Pati, Jagadeesh Chandra | Q82: Resolved | R82: Hi Pati, Jagadeesh Chandra Files copied please verify | V82: Other | W82: Yes
A83: IT-3001212 | B83: IT-3001212 | D83: Copy files From Nile Prod Raw path to Nile QC Raw path - Aetna Trad | E83: Hi Team, Could you please copy the below mentioned files from the Nile PROD location to the Nile QC location? for the last week files, 04/12/2026 to latest. This request is critical as we have early communicated with prod support team. Nile PROD RAW PATH (Source): /dataingestionprod/raw/unrestricted/5-aetna-traditional Nile Dev RAW PATH (Target): /dataingestionqc/raw/unrestricted/5-aetna-traditional Once copied to QC folder, the owner should be set to "svcpnilediqcraw" and group should be set to "qcunrestricted" and permissions should be 75 | F83: Hi Shivalingu, Naveen Files copied please verify Thanks Satish Devatha | G83: Files Copied | H83: Other | I83: Other | K83: Closed | L83: 2026-04-20 | M83: 2026-04-20 | N83: Nile Production Support | O83: Unassigned | P83: Shivalingu, Naveen | Q83: Resolved | R83: Hi Shivalingu, Naveen Files copied please verify Thanks Satish Devatha | V83: Other | W83: Yes
A84: IT-3001086 | B84: IT-3001086 | D84: Subject: OSCAR no claim volume Importance: High | E84: From: Svc_PowerEmail < svc_poweremail@cotiviti.com > Sent: Monday, April 20, 2026 10:45 AM To: Production Ops PCA < PCAProductionOperations@cotiviti.com >; Production Control < production.control@cotiviti.com >; Nile Production Support < NileProductionSupport@cotiviti.com > Cc: CV Support Team < DL-CVSupportTeam@cotiviti.com >; CSMs < CSMs@cotiviti.com >; PCI Management < PCIManagement@cotiviti.com >; Azuela, Errol < errol.azuela.1@cotiviti.com > Subject: OSCAR no claim volume Importance: High Hello, We are missing 4/20/26 OSCAR batch for nurse review. Kindly look into this. Thanks! Ticket: IT-3001039 Client(s): OSCAR Processing Platform: PPM Not newly implemented client. No viable workaround. | F84: I realized this was on the client side and shouldnt have created the ticket | H84: Other | I84: Other | K84: Cancelled | L84: 2026-04-20 | M84: 2026-04-22 | N84: Nile Production Support | O84: Unassigned | P84: Briguglio, Katrina | Q84: Cancelled | R84: I realized this was on the client side and shouldnt have created the ticket | V84: Metric drop
A85: IT-3000667 | B85: IT-3000667 | D85: Humana claims file not ingested | E85: Hello, Humana claims file is not ingested. File have arrived on their website. Please check. Thank you | F85: Nile pipeline: Lineage Report 202603 -1 - prod - dm_humana-hdap-actian_migration_claim_detail Hi Shrestha, Sajjan Now pipeline is running Earlier pipeline failed with below error The file extraction process has failed due to possible file corruption or an invalid compression format, Hence unable to unarchive the file using existing methods. : icd10_medclm_202604.txt.gz Hi Shrestha, Sajjan pipeline completed | G85: pipeline completed | H85: Other | I85: Other | K85: Closed | L85: 2026-04-20 | M85: 2026-04-20 | N85: Nile Production Support | O85: Unassigned | P85: Shrestha, Sajjan | Q85: Resolved | R85: Nile pipeline: Lineage Report 202603 -1 - prod - dm_humana-hdap-actian_migration_claim_detail Hi Shrestha, Sajjan Now pipeline is running Earlier pipeline failed with below error The file extraction process has failed due to possible file corruption or an invalid compression format, Hence unable to unarchive the file using existing methods. : icd10_medclm_202604.txt.gz Hi Shrestha, Sajjan pipeline completed | V85: File Issue
A86: IT-2999879 | B86: IT-2999879 | D86: Peer review for BMC workflow pipelines | E86: The above pipelines need to be verified. | F86: I have to check this ticket now. I have reviewed the bmc pipelines. | G86: I have reviewed the bmc pipelines. | H86: Other | I86: Other | K86: Closed | L86: 2026-04-20 | M86: 2026-04-24 | N86: Nile Production Support | O86: Unassigned | P86: Karakavalasa, SriVarshini | Q86: Done | R86: I have to check this ticket now. I have reviewed the bmc pipelines. | V86: Other | W86: Yes
A87: IT-2999839 | B87: IT-2999839 | D87: Updating the pre-checks for the BMC workflow pipelines. | E87: Updating the pre-checks to use the pipeline version as “Latest” instead of specific versions. This ensures that any pipelines with modifications and newly published versions will automatically be picked up and considered in the workflow going forward. | G87: Updated all prechecks to the **Latest** version for the pipelines, published them, verified that all respective child pipelines are published, and proceeded with scheduling. | H87: Other | I87: Other | K87: Closed | L87: 2026-04-20 | M87: 2026-04-24 | N87: Nile Production Support | O87: Unassigned | P87: Karakavalasa, SriVarshini | Q87: Resolved | V87: Other | W87: Yes
A88: IT-2999831 | B88: IT-2999831 | D88: Premera OLA Configuration Update | E88: Update Premera OLA Configuration setup in ProdOps to avoid unnecessary pipeline status in monitoring tab. | F88: Updated the OLA configuration in ProdOps, and it is now working as expected. We are no longer seeing unwanted warnings when files arrive and are processed. Will continue to monitor for a couple of days and, if everything remains stable, then going to close the ticket. | H88: Other | I88: Other | K88: On Hold | L88: 2026-04-20 | M88: 2026-05-05 | N88: Nile Production Support | O88: Unassigned | P88: Kamsetty, Sravani | Q88: Unresolved | R88: Updated the OLA configuration in ProdOps, and it is now working as expected. We are no longer seeing unwanted warnings when files arrive and are processed. Will continue to monitor for a couple of days and, if everything remains stable, then going to close the ticket. | V88: Configuration Issue
A89: IT-2999131 | B89: IT-2999131 | D89: ppm-prospectmedical-idx-tba_professional_claims_GDF2_8_CDF2_8-"Pipeline failed for 2026/04/18"" | E89: Pipeline Name: ppm-prospectmedical-idx-tba_professional_claims_GDF2_8_CDF2_8 Failure message: Please verify that the specified header or trailer pattern is accurate and that the source file is not empty, pattern : : @@TRAILER@@| | F89: There are 2 files in question the first file has correct trailer info ( please see attached) Th second file is missing the TRAILER info (Please se attached) This needs to be scalated replacement fil has not come in yet Confirmed with Lea; Email: RE: PROSM no claim volume (4/30/2026) ALl files were sent on 4/20. Checked both pipelines: ppm-prospectmedical-idx-tba_professional_claims_GDF2_8_CDF2_8 ppm-prospectmedical-idx-history_institutional_claims_GDF2_8_CDF2_8 We processed all the files successfully. Thank you melly | G89: Per Lea, client resent them as 4/20 files; All have been delivered successfully. | H89: Other | I89: Other | K89: Closed | L89: 2026-04-18 | M89: 2026-04-30 | N89: Nile Production Support | O89: Unassigned | P89: Limbu, Sajan | Q89: Resolved | R89: There are 2 files in question the first file has correct trailer info ( please see attached) Th second file is missing the TRAILER info (Please se attached) This needs to be scalated replacement fil has not come in yet Confirmed with Lea; Email: RE: PROSM no claim volume (4/30/2026) ALl files were sent on 4/20. Checked both pipelines: ppm-prospectmedical-idx-tba_professional_claims_GDF2_8_CDF2_8 ppm-prospectmedical-idx-history_institutional_claims_GDF2_8_CDF2_8 We processed all the files successfully. Thank you melly | V89: File Issue
A90: IT-2999102 | B90: IT-2999102 | D90: WELEX - History PROF & INST. files failed - 04/18/2026 | E90: Hi Nile Team, We have received below welex test files and failed at our end, because of sequence issue. The sequence number '230' are already used for mentioned files "welex_test_ophistory_incoming_1TST2.04-11-2026_0644"& "welex_test_history_incoming_1TST2.04-11-2026_0643" Please check with client and resend files with next available sequence numbers. File : welex_test_ophistory_incoming_1TST2.04-18-2026_1925 QA Status : FAILED Reason : The file has already been processed or it is out-of-sequence. WELEX|H|230|20260418|890198|R TRAILER|890198|20260418|161828 File : welex_test_history_incoming_1TST2.04-18-2026_2005 QA Status : FAILED Reason : The file has already been processed or it is out-of-sequence. WELEX|H|230|20260418|2204215|R TRAILER|2204215|20260418|154308 | F90: Hi Gudala, Kumaraswamy We have requested client to send the replacement file. Email ref: Requesting replacement file for Wellmark QC test tba file we haven't heard anything yet from the client so, we have again sent a follow up email to the client. | K90: Awaiting User Info | L90: 2026-04-18 | M90: 2026-05-06 | N90: Nile Production Support | O90: Unassigned | P90: Gudala, Kumaraswamy | Q90: Unresolved | R90: Hi Gudala, Kumaraswamy We have requested client to send the replacement file. Email ref: Requesting replacement file for Wellmark QC test tba file we haven't heard anything yet from the client so, we have again sent a follow up email to the client. | V90: Other | W90: Yes
A91: IT-2998225 | B91: IT-2998225 | D91: UHC-Cirrus: Pipeline Failure | Claim_EDI & cir_Claim_Detail | Data Date: 2026/04/06 | Source file schema is not matching | E91: ** UPDATED ISSUE ******4/20/26 dm-uhc-cirrus-actian_migration_entity_cir_Claim_Detail , Version: V1.3 , Data Date: 2026/04/06 Error Message: Source file schema is not matching with the Table Schema, Please check Column names and their Data-types dm-uhc-cirrus-actian_migration_entity_Claim_EDI , Version: V1.2 , Data Date: 2026/04/06 , Error Message: Source file schema is not matching with the Table Schema, Please check Column names and their Data-types -------------------------- ** PREVIOUS ISSUES *********** Background: We are re-running the historical files for UHC-CIRRUS for data date 2026/04/06. The following pipelines below failed with the error message below. Pipeline: dm-uhc-cirrus-actian_migration_entity_cir_cladeny , Version: V1 , Data Date: 2026/04/06 Error message : Could not execute broadcast in 300 secs. You can increase the timeout for broadcasts via spark.sql.broadcastTimeout or disable broadcast join by setting spark.sql.autoBroadcastJoinThreshold to -1 Pipeline: dm-uhc-cirrus-actian_migration_entity_cir_Claim_Detail , Version: V1.2 , Data Date: 2026/04/06 ** Error Message : Could not execute broadcast in 300 secs. You can increase the timeout for broadcasts via spark.sql.broadcastTimeout or disable broadcast join by setting spark.sql.autoBroadcastJoinThreshold to -1 Thanks, Enid | F91: Updated issue. dm-uhc-cirrus-actian_migration_entity_cir_Claim_Detail , Version: V1.3 , Data Date: 2026/04/06 Error Message: Source file schema is not matching with the Table Schema, Please check Column names and their Data-types dm-uhc-cirrus-actian_migration_entity_Claim_EDI , Version: V1.2 , Data Date: 2026/04/06 , Error Message: Source file schema is not matching with the Table Schema, Please check Column names and their Data-types assigning to DIN since he worked on this previously. thank you issue we need DBA to free up some space Caused by: com.microsoft.sqlserver.jdbc.SQLServerException: Could not allocate a new page for database 'UhcDataRawCirrus' because of insufficient disk space in filegroup 'PRIMARY'. Create the necessary space by dropping objects in the filegroup, adding additional files to the filegroup, or setting autogrowth on for existing files in the filegroup. at com.microsoft.sqlserver.jdbc.SQLServerException.makeFromDatabaseError(SQLServerException.java:265) | G91: Created a new module to handle and pass spark configuration updates. Also asked EDM to ask DATABASE Admin to free up some space as well as clear transaction logs for that DB | H91: Other | I91: Other | K91: Closed | L91: 2026-04-17 | M91: 2026-04-21 | N91: Nile Production Support | O91: Unassigned | P91: Enid Ike | Q91: Resolved | R91: Updated issue. dm-uhc-cirrus-actian_migration_entity_cir_Claim_Detail , Version: V1.3 , Data Date: 2026/04/06 Error Message: Source file schema is not matching with the Table Schema, Please check Column names and their Data-types dm-uhc-cirrus-actian_migration_entity_Claim_EDI , Version: V1.2 , Data Date: 2026/04/06 , Error Message: Source file schema is not matching with the Table Schema, Please check Column names and their Data-types assigning to DIN since he worked on this previously. thank you issue we need DBA to free up some space Caused by: com.microsoft.sqlserver.jdbc.SQLServerException: Could not allocate a new page for database 'UhcDataRawCirrus' because of insufficient disk space in filegroup 'PRIMARY'. Create the necessary space by dropping objects in the filegroup, adding additional files to the filegroup, or setting autogrowth on for existing files in the filegroup. at com.microsoft.sqlserver.jdbc.SQLServerException.makeFromDatabaseError(SQLServerException.java:265) | V91: Schema issue
A92: IT-2997312 | B92: IT-2997312 | D92: Please Move Elist spooler to Event Based set up | E92: Please Move Elist spooler to Event Based set up. spooler name: accentsep-cigna-misc-pp-qet-elist File name : PP_QET_ELIST.*.zip.pgp | F92: Ticket closed as [EDI2-16806] Please Move Elist spooler to Event Based set up - R&D Jira - WDC raised on DI board | H92: Other | I92: Other | K92: Cancelled | L92: 2026-04-17 | M92: 2026-04-30 | N92: Nile Production Support | O92: Unassigned | P92: Nekkanti, Alekya | Q92: Cancelled | R92: Ticket closed as [EDI2-16806] Please Move Elist spooler to Event Based set up - R&D Jira - WDC raised on DI board | V92: Spooler issue
A93: IT-2996668 | B93: IT-2996668 | D93: BMC Pipelines Review and Precheck Verification list for 15 clients. | E93: Review all BMC pipelines for 20 clients, verify module association, check precheck configuration (latest option), and identify non-module workflow calls, and shared missing pipelines list. Give demo on how to work on the pipeline changes to one of the client. | F93: Listed all the required BMC pipeline list and precheck conditions in a doc. Gathered all the restricted and unrestricted clients and assigned the clients with triage team to work on pipeline enhancements. | G93: Listed all the bmc optimization pipelines with precheck and publish status. closing this ticket. | H93: Other | I93: Other | K93: Closed | L93: 2026-04-17 | M93: 2026-04-20 | N93: Nile Production Support | O93: Unassigned | P93: Kantimahanti, Ravisankar | Q93: Resolved | R93: Listed all the required BMC pipeline list and precheck conditions in a doc. Gathered all the restricted and unrestricted clients and assigned the clients with triage team to work on pipeline enhancements. | V93: Configuration Issue
A94: IT-2995627 | B94: IT-2995627 | D94: adding 2 email list for HCSC and UHC Cirrus pipeline | E94: team, would you please help add EDM_RCA_UHC_CIRRUS@cotiviti.com to uhc cirrus nile ingestion failure email notification would you please help add EDM_RCA_HCSC@cotiviti.com to HCSC nile ingestion failure email notification Thanks | F94: Hi Sravani, Can we add UHC Cirrus and hcsc-hcsc client feeds with these 4 kinds of emails: Unmatched raw counts Data Drop File came late BMC trigger not running.. Unmatched caqh raw data count - 20260404_1 - prod - dm-excellus-actian_migration_caqh.msg prod - Cannot kick off bmc workflow CHC_UHC_COSMOS_PROVIDER_INCREMENTAL_NILE for ingestion period 20260428-1.msg Late Client File Notification - prod - Kaiser - WA - Kaiser-WA-Actian-2.msg Data metric percentage drop hits threshold 202603 - prod - dm-humana-hdap-actian_migration_MEDCLM_RAW_AMBULANCE.msg Sravani, I attached the example of the emails from other clients.. Hope this helps, thanks! melly Hi, As per the current configuration, Nile sends email notifications for BMC success events and threshold percentage drops for certain clients. If EDM requires failure notifications, there is a parameter (tech_email_dl) that triggers alerts for every event—such as pipeline start, pipeline end, and failures whenever a pipeline run fails as per the schedule. However, enabling this may lead to excessive notifications and potential confusion between Nile and EDM alerts. This likely needs further discussion. Jani and Krishna are currently looking into it. | H94: Other | I94: Other | K94: On Hold | L94: 2026-04-16 | M94: 2026-05-04 | N94: Nile Production Support | O94: Unassigned | P94: Tang, Chao | Q94: Unresolved | R94: Hi Sravani, Can we add UHC Cirrus and hcsc-hcsc client feeds with these 4 kinds of emails: Unmatched raw counts Data Drop File came late BMC trigger not running.. Unmatched caqh raw data count - 20260404_1 - prod - dm-excellus-actian_migration_caqh.msg prod - Cannot kick off bmc workflow CHC_UHC_COSMOS_PROVIDER_INCREMENTAL_NILE for ingestion period 20260428-1.msg Late Client File Notification - prod - Kaiser - WA - Kaiser-WA-Actian-2.msg Data metric percentage drop hits threshold 202603 - prod - dm-humana-hdap-actian_migration_MEDCLM_RAW_AMBULANCE.msg Sravani, I attached the example of the emails from other clients.. Hope this helps, thanks! melly Hi, As per the current configuration, Nile sends email notifications for BMC success events and threshold percentage drops for certain clients. If EDM requires failure notifications, there is a parameter (tech_email_dl) that triggers alerts for every event—such as pipeline start, pipeline end, and failures whenever a pipeline run fails as per the schedule. However, enabling this may lead to excessive notifications and potential confusion between Nile and EDM alerts. This likely needs further discussion. Jani and Krishna are currently looking into it. | V94: Other | W94: Yes
A95: IT-2995289 | B95: IT-2995289 | D95: Please provide location of Security Health Plan GDF claims professional history files | E95: I am no longer able to find the following GDF file for Security Health Plan in HUE/Hive/prod_niledataingestion_restricted: • securityhealth_qnxt_gdf_claims_professional_history_20251121_1 I need to be able to query against this file in HUE or another file name like it with a different date. This is needed for FWAPR Upgrade for Security Health Plan, which is No 4 on our list of Upgrades. Please let me know as soon as you can so I can proceed with the Gap analysis of claims for this project. | F95: From: Suryani, Melly <melly.suryani@cotiviti.com> Sent: Thursday, April 16, 2026 1:50 PM To: Herman, Donna <Donna.Herman@cotiviti.com> Cc: Dindo Octaviano <dindo.octaviano@cotiviti.com> Subject: RE: Location of Security Health Plan of Wisconsin GDF Files No worries Donna.. Din is going to reach out and help you with the gdf files that you’re looking for. Would you mind creating a generic service ticket and assign it to Nile Production Support? Can you please provide an update on this request? Thank you. Hi Herman, Donna Created a table securityhealth_qnxt_gdf_claims_professional_history_20251121_1 please verify now I just tried to pull up table and received No tables found message. I checked in Hive/prod_niledataingestion_restricted/securityhealth_qnxt_gdf_claims_professional_history_20251121_1. Please advise if this is in a different location. Thank you. Hi Herman, Donna can you please verify now Thanks Hi Satish, I cannot see the table in the list of tables that display in HUE under prod_niledataingestion_restricted, but I can run queries against that table name and get results. I think I am good to get what I need from this table. Thank you. Donna Hi Herman, Donna Table got deleted due to limitations, so i created table Thanks | G95: Created a table | H95: Other | I95: Other | K95: Closed | L95: 2026-04-16 | M95: 2026-04-22 | N95: Nile Production Support | O95: Unassigned | P95: Herman, Donna | Q95: Resolved | R95: From: Suryani, Melly <melly.suryani@cotiviti.com> Sent: Thursday, April 16, 2026 1:50 PM To: Herman, Donna <Donna.Herman@cotiviti.com> Cc: Dindo Octaviano <dindo.octaviano@cotiviti.com> Subject: RE: Location of Security Health Plan of Wisconsin GDF Files No worries Donna.. Din is going to reach out and help you with the gdf files that you’re looking for. Would you mind creating a generic service ticket and assign it to Nile Production Support? Can you please provide an update on this request? Thank you. Hi Herman, Donna Created a table securityhealth_qnxt_gdf_claims_professional_history_20251121_1 please verify now I just tried to pull up table and received No tables found message. I checked in Hive/prod_niledataingestion_restricted/securityhealth_qnxt_gdf_claims_professional_history_20251121_1. Please advise if this is in a different location. Thank you. Hi Herman, Donna can you please verify now Thanks Hi Satish, I cannot see the table in the list of tables that display in HUE under prod_niledataingestion_restricted, but I can run queries against that table name and get results. I think I am good to get what I need from this table. Thank you. Donna Hi Herman, Donna Table got deleted due to limitations, so i created table Thanks | V95: File Missing
A96: IT-2994837 | B96: IT-2994837 | D96: Centene Amisys OLA Configurations. | E96: Centene Amisys OLA Configurations. | F96: Couple of OLA logs showing incorrect, Checked with engineering team. awaiting for an update. | G96: Configured as per the latest feature available. | H96: Other | I96: Other | K96: Closed | L96: 2026-04-16 | M96: 2026-05-04 | N96: Nile Production Support | O96: Unassigned | P96: Jani, Shaik | Q96: Resolved | R96: Couple of OLA logs showing incorrect, Checked with engineering team. awaiting for an update. | V96: Configuration Issue
A97: IT-2994825 | B97: IT-2994825 | D97: Caresource RCA OLA Configurations | E97: Caresource RCA OLA Configurations | F97: To check the results if working fine. | G97: Configured the OLA as per the new feature available. | H97: Other | I97: Other | K97: Closed | L97: 2026-04-16 | M97: 2026-05-04 | N97: Nile Production Support | O97: Unassigned | P97: Jani, Shaik | Q97: Resolved | R97: To check the results if working fine. | V97: Configuration Issue
A98: IT-2994804 | B98: IT-2994804 | D98: Banner file ingestion failed | E98: Banner file ingestion failed can you please help resolve this issue This pipeline seems failing every month, can we fix this issue for all future loads? Thanks | F98: Pipeline is: dm-fwa-bannerhealth-idxbhp-history_pharmacy_claims_GDF2_6_CDF2_6 team, can we please keep this ticket open until we have an update on"This pipeline seems failing every month, can we fix this issue for all future loads?" thank you for your support Chao I started work on this ticket. will update the status accordingly | K98: Active | L98: 2026-04-16 | M98: 2026-04-20 | N98: Nile Production Support | O98: Unassigned | P98: Tang, Chao | Q98: Unresolved | R98: Pipeline is: dm-fwa-bannerhealth-idxbhp-history_pharmacy_claims_GDF2_6_CDF2_6 team, can we please keep this ticket open until we have an update on"This pipeline seems failing every month, can we fix this issue for all future loads?" thank you for your support Chao I started work on this ticket. will update the status accordingly | V98: File Issue
A99: IT-2994792 | B99: IT-2994792 | D99: Decomission HAMP EPICTAPESTRY PPM | E99: Decomission HAMP EPICTAPESTRY PPM | F99: RE_ DAILY_ Missing File_ HAMP TBA professional File not received (20260405).msg | G99: Removed the pipeline and spoolers from the Nile application and tracker. | H99: Other | I99: Other | K99: Closed | L99: 2026-04-16 | M99: 2026-04-16 | N99: Nile Production Support | O99: Unassigned | P99: Courville, Lea | Q99: Resolved | R99: RE_ DAILY_ Missing File_ HAMP TBA professional File not received (20260405).msg | V99: Other | W99: Yes
A100: IT-2994782 | B100: IT-2994782 | D100: CalOptima Facets OLA Configuration | E100: CalOptima Facets OLA Configuration | G100: Configured and updated accordingly. | H100: Other | I100: Other | K100: Closed | L100: 2026-04-16 | M100: 2026-04-16 | N100: Nile Production Support | O100: Unassigned | P100: Jani, Shaik | Q100: Resolved | V100: Configuration Issue
...

Sheet _categories
A1: Configuration Issue
A2: File Issue
A3: Spooler issue
A4: Data Issue
A5: File Missing
A6: Unmatched raw data count
A7: Pipeline Schedule
A8: DB Issue
A9: Metric drop
A10: Schema issue
A11: Issue Platform
A12: Other

Sheet Monthly Summary
A1: NILE Pipeline Issue Summary — April 2026
A2: ="Total Tickets: "&TEXT(COUNTIF('Raw Tickets'!$V$3:$V$10000,"<>"),"0")
A4: Category | B4: Count | C4: % Share | D4: vs Last Month | E4: Color Tag
A5: Configuration Issue | B5: =COUNTIF('Raw Tickets'!$V$3:$V$10000,"Configuration Issue") | C5: =IF(COUNTIF('Raw Tickets'!$V$3:$V$10000,"<>")>0,COUNTIF('Raw Tickets'!$V$3:$V$10000,"Configuration Issue")/COUNTIF('Raw Tickets'!$V$3:$V$10000,"<>"),0) | D5: ▲ +7
A6: File Issue | B6: =COUNTIF('Raw Tickets'!$V$3:$V$10000,"File Issue") | C6: =IF(COUNTIF('Raw Tickets'!$V$3:$V$10000,"<>")>0,COUNTIF('Raw Tickets'!$V$3:$V$10000,"File Issue")/COUNTIF('Raw Tickets'!$V$3:$V$10000,"<>"),0) | D6: ▲ +4
A7: Spooler issue | B7: =COUNTIF('Raw Tickets'!$V$3:$V$10000,"Spooler issue") | C7: =IF(COUNTIF('Raw Tickets'!$V$3:$V$10000,"<>")>0,COUNTIF('Raw Tickets'!$V$3:$V$10000,"Spooler issue")/COUNTIF('Raw Tickets'!$V$3:$V$10000,"<>"),0) | D7: ▲ +8
A8: Data Issue | B8: =COUNTIF('Raw Tickets'!$V$3:$V$10000,"Data Issue") | C8: =IF(COUNTIF('Raw Tickets'!$V$3:$V$10000,"<>")>0,COUNTIF('Raw Tickets'!$V$3:$V$10000,"Data Issue")/COUNTIF('Raw Tickets'!$V$3:$V$10000,"<>"),0) | D8: ▲ +4
A9: File Missing | B9: =COUNTIF('Raw Tickets'!$V$3:$V$10000,"File Missing") | C9: =IF(COUNTIF('Raw Tickets'!$V$3:$V$10000,"<>")>0,COUNTIF('Raw Tickets'!$V$3:$V$10000,"File Missing")/COUNTIF('Raw Tickets'!$V$3:$V$10000,"<>"),0) | D9: ▲ +2
A10: Unmatched raw data count | B10: =COUNTIF('Raw Tickets'!$V$3:$V$10000,"Unmatched raw data count") | C10: =IF(COUNTIF('Raw Tickets'!$V$3:$V$10000,"<>")>0,COUNTIF('Raw Tickets'!$V$3:$V$10000,"Unmatched raw data count")/COUNTIF('Raw Tickets'!$V$3:$V$10000,"<>"),0) | D10: — same
A11: Pipeline Schedule | B11: =COUNTIF('Raw Tickets'!$V$3:$V$10000,"Pipeline Schedule") | C11: =IF(COUNTIF('Raw Tickets'!$V$3:$V$10000,"<>")>0,COUNTIF('Raw Tickets'!$V$3:$V$10000,"Pipeline Schedule")/COUNTIF('Raw Tickets'!$V$3:$V$10000,"<>"),0) | D11: ▲ +4
A12: DB Issue | B12: =COUNTIF('Raw Tickets'!$V$3:$V$10000,"DB Issue") | C12: =IF(COUNTIF('Raw Tickets'!$V$3:$V$10000,"<>")>0,COUNTIF('Raw Tickets'!$V$3:$V$10000,"DB Issue")/COUNTIF('Raw Tickets'!$V$3:$V$10000,"<>"),0) | D12: ▲ +1
A13: Metric drop | B13: =COUNTIF('Raw Tickets'!$V$3:$V$10000,"Metric drop") | C13: =IF(COUNTIF('Raw Tickets'!$V$3:$V$10000,"<>")>0,COUNTIF('Raw Tickets'!$V$3:$V$10000,"Metric drop")/COUNTIF('Raw Tickets'!$V$3:$V$10000,"<>"),0) | D13: ▲ +2
A14: Schema issue | B14: =COUNTIF('Raw Tickets'!$V$3:$V$10000,"Schema issue") | C14: =IF(COUNTIF('Raw Tickets'!$V$3:$V$10000,"<>")>0,COUNTIF('Raw Tickets'!$V$3:$V$10000,"Schema issue")/COUNTIF('Raw Tickets'!$V$3:$V$10000,"<>"),0) | D14: ▲ +1
A15: Issue Platform | B15: =COUNTIF('Raw Tickets'!$V$3:$V$10000,"Issue Platform") | C15: =IF(COUNTIF('Raw Tickets'!$V$3:$V$10000,"<>")>0,COUNTIF('Raw Tickets'!$V$3:$V$10000,"Issue Platform")/COUNTIF('Raw Tickets'!$V$3:$V$10000,"<>"),0) | D15: ▼ -1
A16: Other | B16: =COUNTIF('Raw Tickets'!$V$3:$V$10000,"Other") | C16: =IF(COUNTIF('Raw Tickets'!$V$3:$V$10000,"<>")>0,COUNTIF('Raw Tickets'!$V$3:$V$10000,"Other")/COUNTIF('Raw Tickets'!$V$3:$V$10000,"<>"),0) | D16: ▼ -32
A17: Monthly Total | B17: =SUM(B5:B16) | C17: 100%

Sheet Needs Review
A1: Needs Review — 68 uncategorized tickets
A2: ="Needs Review count: "&COUNTIF('Raw Tickets'!$V$3:$V$10000,"Other")&" — Change category in Raw Tickets tab, then re-run to refresh this list"
A3: Key | B3: Summary | C3: Description | D3: Comment | E3: Close Notes | F3: Status | G3: Created
A4: IT-3021831 | B4: CLONE - Peer Review for Aetna-Trad-SCM BMC pipeline Optimization | C4: Review all the required conditions for the BMC/child pipelines: Prechecks pipeline version to be updated to Latest Remove unwanted parameters from the pipeline All the child pipelines need to be published BMC pipeline needs to be published and Scheduled/Subscribe option need to be enabled. Update all the prod documents with latest pipeline versions. | E4: Since it's a direct bmc pipeline it doesn't require any changes. | F4: Closed | G4: 2026-04-29
A5: IT-3021830 | B5: [BCBS_MI]-Update prechecks for BMC and publish all the child pipelines. | C5: Update precheck with pipeline version as latest and remove all the unnecessary parameters from the pipeline. Publish all the child pipelines and modify subscribe BMC pipeline versions to latest. | D5: BMC Pipeline prechecks conditions for pipeline version is updated to latest. Published and scheduled the latest BMC version pipeline. FYI: trigger_bmc_workflow-bcbs_mi_bcbs_mi_monthly Version: V1.6 | E5: BMC Pipeline prechecks conditions for pipeline version is updated to latest. Published and scheduled the latest BMC version pipeline. FYI: trigger_bmc_workflow-bcbs_mi_bcbs_mi_monthly Version: V1.6 | F5: Closed | G5: 2026-04-29
A6: IT-3020610 | B6: Update the tracker with the newly deployed History Lean Ingestion pipelines for DevotedHealth that are now live in production. | C6: Hello Jani, Shaik , We have scheduled the devotedhealth - devotedhealth history lean ingestion pipelines in production, and these will be used going forward. Please note that for TBA, we will continue using the currently running Slim_Refactoring pipeline for devotedhealth - devotedhealth, as its estimated runtime is already around 13–14 minutes. The following is the list of old pipeline Ids replaced by the lean ingestion pipelines. 2023-02-27-54910254 -> 2026-03-30-111442046 reports: 2026-03-30-90594816 2023-02-27-52996445 -> 2026-03-30-111388968 reports: 2026-03-30-90568473 Thank You | E6: Details recorded accordingly. | F6: Closed | G6: 2026-04-29
A7: IT-3019608 | B7: Pipeline: dm-amerihealth-results-actian_migration_claims_detail | Data Date: 2026/04/28 | Failure | C7: Pipeline: dm-amerihealth-results-actian_migration_claims_detail , Version: V1.3 , Data Date: 2026/04/28 Error Message: Exiting Process with failure.Key source-file: /dataingestionprod/restricted/218-amerihealth-results/rawincoming/2024-09-20-102280221/1.3/125369.115465/20260428/1/NCDS_ClaimsRecovery.03132026.zip/NCDS_ClaimsRecovery.03132026.txt is zero-byte and Size: 0 . Stopping Ingestion Process as configured as mandatory file (Source section). We got CONFIRMATION from Karyn (EDM) to proceed with the loading. Thank you | D7: Hi Enid Ike pipeline completed Thanks Satish Devatha | E7: pipeline completed | F7: Closed | G7: 2026-04-28
A8: IT-3018019 | B8: Optumcare RCCV Professional Prod Transition Documents | C8: Hello Team, Please find the prod transition checklist documents for Optumcare RCCV Professional below: Checklist: Optumcare-RCCV_DataIgestion_Production_Job_Transition_Checklist.docx Escalation Doc: OptumCare_Joint Data Escalation Plan Enterprise External 20250424.xlsx I have created a ticket for document review: https://jira2.cotiviti.com/browse/NDICR-5409 | E8: Documents reviewed, Details reviewed and recorded and transition scheduled for today. | F8: Closed | G8: 2026-04-28
A9: IT-3017668 | B9: UHC PNICE Transition | C9: UHC PNICE Transition | E9: Details recorded after reviewing the documents. | F9: Closed | G9: 2026-04-28
A10: IT-3017655 | B10: Production Transition - Tufts-Diamond | C10: Production Transition - Tufts-Diamond RCCV 2 pipelines Inpatient & Iphistory | D10: Waiting for the transition. also, the feedback fixes. | F10: On Hold | G10: 2026-04-28
A11: IT-3017053 | B11: Request to add EDM's distro list to NILE's email notifications | C11: Hi Nile Prod Support team. Please add EDM’s distribution list to NILE’s ingestion report email notifications (see sample attached). EDM’s distribution list for each client is also attached. | D11: Data metric percentage drop hits threshold 202603 - prod - dm-humana-hdap-actian_migration_MEDCLM_RAW_AMBULANCE.msg (84 kB) Late Client File Notification - prod - Kaiser - WA - Kaiser-WA-Actian.msg (70 kB) prod - Cannot kick off bmc workflow CHC_UHC_COSMOS_PROVIDER_INCREMENTAL_NILE for ingestion period 20260428.msg (79 kB) Unmatched caqh raw data count - 20260404_1 - prod - dm-excellus-actian_migration_caqh.msg (77 kB) AuditDistroList-1.xlsx to make sure the email implementation of UHC Cirrus and HCSC is okay for EDM | F11: On Hold | G11: 2026-04-27
A12: IT-3016920 | B12: Copy files From Nile Prod Raw path to Nile QC Raw path - Aetna Trad | C12: Hi Team, Could you please copy the below mentioned files from the Nile PROD location to the Nile QC location? for the last week files, 04/19/2026 to latest. This request is critical as we have early communicated with prod support team. Nile PROD RAW PATH (Source): /dataingestionprod/raw/unrestricted/5-aetna-traditional Nile Dev RAW PATH (Target): /dataingestionqc/raw/unrestricted/5-aetna-traditional Once copied to QC folder, the owner should be set to "svcpnilediqcraw" and group should be set to "qcunrestricted" and permissions should be 75 | D12: Files Copied | E12: Files Copied | F12: Closed | G12: 2026-04-27
A13: IT-3016913 | B13: Copy files From Nile Prod Raw path to Nile QC Raw path - Aetna Trad | C13: Hi Team, Could you please copy the below mentioned files from the Nile PROD location to the Nile QC location? for the last week files, 04/19/2026 to latest. This request is critical as we have early communicated with prod support team. Nile PROD RAW PATH (Source): /dataingestionprod/raw/unrestricted/5-aetna-traditional Nile Dev RAW PATH (Target): /dataingestionqc/raw/unrestricted/5-aetna-traditional Once copied to QC folder, the owner should be set to "svcpnilediqcraw" and group should be set to "qcunrestricted" and permissions should be 75 | D13: Files are already copied | E13: Files are already copied | F13: Closed | G13: 2026-04-27
A14: IT-3016008 | B14: Requesting information for Cigna Gross ID amount dataset | C14: We are looking to learn information on Cigna Gross ID amount dataset as it relates to if it is provided to Nile and if so how and where it can accessed. | F14: In Progress (HD1) | G14: 2026-04-27
A15: IT-3012722 | B15: rccv-cignamedicare-facets-tba_institutional_claims_custom_GDF2_5_CDF2_5 for May 2025 ingestion.. | C15: Hi Satish, Just creating this ticket as a placeholder In May 2026, Monitoring team will check for the arrival files for Cignamdicare facets drg. After the files are spooled, you and I will sync up to decide: rccv-cignamedicare-facets-tba_institutional_claims_custom_GDF2_5_CDF2_5 which version to use, and what schema. The latest one from Din is v1.9. Thanks Satish, melly | D15: Hi Suryani, Melly Thanks for running latest version v1.9 pipeline Thanks Satish Devatha | F15: In Progress (HD1) | G15: 2026-04-24
A16: IT-3011677 | B16: Please confirm if RCA Engineering is receiving and ingesting the SIU Weekly Provider Report Geisinger sends us via SFTP that is an exclusion file for our teams. | C16: Geisinger sends us a weekly SIU Provider exclusion file that should be received via SFTP. They also send it to us via e-mail. However, when CCV and I first began receiving this via e-mail, Phil Thomas, informed the CCV CSM and I we could ignore these e-mails as they get sent to us via SFTP and automatically ingested. It appears from the below that is the case for CCV. Do you know if that is still the case for RCA? Recently the client, began adding additional exclusions to this list that we do have to share with Audit Ops for updates. This concerned me that perhaps this could impact our appropriate ingestion of the SIU weekly provider exclusions the client sends us via SFTP. Would you mind having the team look into this for us and confirm if we are ingesting these files via the SFTP? If we are, are the files we’re ingesting, the same as the examples the client sends to us via e-mail as well? Please let me know who I need to send a copy of the e-mail exclusion file to once this ticket is picked up. Thank you!! | D16: Active Pipelines dm-geisinger-facets-weekly_SIU_notouch_file geisinger-facets-weekly_provider_report_passthrough File: SIU Weekly Provider Report.* Filesource: /B2B/Geisinger/inbound/production Cadence: Weekly I compared SIU Weekly Provider Report for Vendor 12-1-2025 file spooled from SFTP with SIU Weekly Provider Report for Vendor 12-1-2025 file Reporter received via email. These files have many discrepancies, namely it seems the reports were generated at different times. Namely, the email file has a report date of 12/4/2025, while the file spooled from SFTP has a report date of 12/17/2025. I compared SIU Weekly Provider Report for Vendor 04-06-2026 file spooled from SFTP with SIU Weekly Provider Report for Vendor 04-06-2026 file Reporter received via email. These files both contain 519 records. The files also contain 4,152 data points that match exactly. So these files are the same. SIU Weekly Provider Report for Vendor 02-23-2026 Records 452 ValuesMatched 3616 ValuesUnmatched 0 SIU Weekly Provider Report for Vendor 03-09-2026 Records 477 Values 3808 ValuesUnmatched 0 SIU Weekly Provider Report for Vendor 01-12-2026 Records 423 ValuesMatched 2965 ValuesUnmatched 419 Analysis: The values that are unmatched are from the "Case Create Date" column. An example of these unmatched values are 1/13/2026 5:27: 41 PM vs 1/13/2026 5:27: 00 PM SIU Weekly Provider Report for Vendor 02-23-2026 Records 452 ValuesMatched 3616 ValuesUnmatched 0 SIU Weekly Provider Report for Vendor 03-09-2026 Records 477 Values 3808 ValuesUnmatched 0 SIU Weekly Provider Report for Vendor 01-12-2026 Records 423 ValuesMatched 2965 ValuesUnmatched 419 | E16: Provided the requestor's analysis in the comments which included comparing 4 SFTP files against files received from email | F16: Closed | G16: 2026-04-24
A17: IT-3010303 | B17: HCSC_BackFill_Set_2_files process. | D17: The second set of files is not being spooled, and we’re facing several challenges. For example, the file name pattern does not include any suffix, and the files have the same name and size as those previously processed. When attempting to spool them, the system indicates that the files have already been processed. I also tried placing all folders in the HDFS location, but the spooler got stuck, so I reached out to the platform team. As an alternative, we copied the files from FTP to HDFS with Satish’s help. The data is currently still loading. we successfully proceed the second set of files, verifying the tables data. Second set of files proceed from the Nile side. | E17: Second set of files proceed from the Nile side. | F17: Closed | G17: 2026-04-24
A18: IT-3009815 | B18: Centene PCCV MI MCD Expansion Prod Transition Documents Review | C18: Please review the prod transition checklist documents for Centene PCCV MI MCD Expansion and let us know if any changes are needed. Creating this ticket as a placeholder. Will update ticket with document links once complete. | D18: Awaiting documents. | F18: On Hold | G18: 2026-04-23
A19: IT-3009664 | B19: Clarification on Premera History Files for Data Date 2026/04/06 | C19: I’m looking for understanding of what the issue was with the below files that were received on 4/15/26 related to the Shared Admin Invoicing Process. Previous communication indicated that there was missing header and trailer information, but Premera has responded saying that the header and footer is present on the file sent. Can we update our response or provide screenshots of the missing information? Thanks! | D19: EXTERNAL RE_ Clarification on Premera History Files for Data Date 2026_04_06.msg (328 kB) Production Control team can you please check and let us know if you need anything? Hi Nile PS Triage team, I notice for these two historical files: ppm-premera-bluecross-history_professional_claims_GDF2_2_CDF2_2_lean_ingestion ppm-premera-bluecross-history_institutional_claims_GDF2_2_CDF2_2_lean_ingestion for date ingestion 2026-04-06 failed in preprocessor step with error message: File /dataingestionprod/unrestricted/109-premera-bluecross/rawincoming/2026-03-30-102438457/1/136533/20260406/1 does not exist. Can you investigate what's going on? I can see the raw files are avaialablei in hue Raw. Thank you melly Suryani, Melly please see the correct files in question. They are dated 04/06, but they were received on 4/15 as described in the email I attached. prebc_history_institutional_incoming_20260406_1.txt.pgp prebc_history_professional_incoming_20260406_1.txt.pgp Sent a reply to Adam: It seems the files on 20260406 are super small. waiting follow up from Adam. Premera has sent over a new set of files. It appears that these files were successfully received in Axway. Can we please confirm they were loaded correctly? prebc_history_institutional_incoming_20260428_1.txt prebc_history_professional_incoming_20260428_1.txt They also resent the unlinked file as well: prebc_unlinkedadj_incoming_1_20260428.zip Hi Adam, We are still getting an error on the replacement files 4/28. We're taking a closer look... Thank you melly Melly's update 4/30: I can see both header-trailer in the source files: /dataingestionprod/unrestricted/109-premera-bluecross/rawincoming/2026-03-30-91183910/1/136533/src_file_backup/20260428/1/prebc_history_institutional_incoming_20260428_1.txt /dataingestionprod/unrestricted/109-premera-bluecross/rawincoming/2026-03-30-102438457/1/136533/src_file_backup/20260428/1/prebc_history_professional_incoming_20260428_1.txt Pipeline error message: No of columns not matching in Header record or Trailer record. Hi Adam, I got my answer: The reason of the error is because they dont conform with the regular history trailer records because they dont have the date stamp at the end: We received @@TRAILER@@|428 (for institutional) @@TRAILER@@|2002 (for professional). Expected: @@TRAILER@@|428|date time (for institutional) @@TRAILER@@|2002|date time (for professional). Would you mind asking the client for the replacement files? Thanks so much melly Client finally sent their final replacement files and they were processed successfully: prebc_history_institutional_incoming_20260503_1.txt.pgp prebc_history_professional_incoming_20260503_1.txt.pgp | E19: Replacement from client on 5/1/2026 processed successfully | F19: Closed | G19: 2026-04-23
A20: IT-3008305 | B20: Update the tracker with the newly deployed History and TBA Lean Ingestion pipelines for Oscar-Homegrown that are now live in production. | C20: Hello Jani, Shaik , The History pipelines for Oscar-Homegrown have been successfully deployed to production. Please update the tracker with the new pipelines. Details of the old and new pipelines are provided below. 2024-03-12-76144063 -> 2026-04-08-75711996 report: 2026-04-08-86206946 2024-03-12-76123265 -> 2026-04-08-74423010 report: 2026-04-08-85983173 2024-03-12-75948469 -> 2026-04-10-115454593 report: 2026-04-13-91286715 2024-03-12-75890753 -> 2026-04-10-114013583 report: 2026-04-13-91025017 Thank You | E20: Details recorded accordingly. | F20: Closed | G20: 2026-04-23
A21: IT-3008084 | B21: Peer Review for Aetna-Trad-SCM BMC pipeline Optimization | C21: Review all the required conditions for the BMC/child pipelines: Prechecks pipeline version to be updated to Latest Remove unwanted parameters from the pipeline All the child pipelines need to be published BMC pipeline needs to be published and Scheduled/Subscribe option need to be enabled. Update all the prod documents with latest pipeline versions. | D21: Hi Kamsetty, Sravani , Verified that all child pipelines have been published successfully. | E21: Verified that all child pipelines are published, ensuring the latest versions are used when running the BMC pipelines. | F21: Closed | G21: 2026-04-23
A22: IT-3007910 | B22: WellCare RCA ARK Client Transition. | C22: WellCare RCA ARK Client Transition. | E22: Transition Completed successfully. | F22: Closed | G22: 2026-04-23
A23: IT-3005937 | B23: Please add these two pipelines in the tracking sheet.. | C23: Hi Jani, Would you mind adding these two pipelines in the tracking sheet? dm-excellus-actian_migration_caqh (weekly pipeline) I remember we use to monitor this but for some reason we couldn’t find it yesterday. The second one is this: rccv-optumcare-facets-TIN_exclusion_file It is noted as “Adhoc”, so I am not sure how we can get it tracked. Thank you in advance, Jani, melly | E23: Updated the details in tracker. | F23: Closed | G23: 2026-04-22
A24: IT-3005392 | B24: HCSC_BackFill_Set_1_files process. | D24: we already proceed the set1 files and completed. | E24: we got the confirmation from the user and closed this ticket. | F24: Closed | G24: 2026-04-22
A25: IT-3005387 | B25: [harvardpilgrim - ohi]-Update prechecks for BMC and publish all the child pipelines. | C25: Update precheck with pipeline version as latest and remove all the unnecessary parameters from the pipeline. Publish all the child pipelines and modify subscribe BMC pipeline versions to latest. | D25: I have implemented the BMC optimization for the clients assigned to me. | E25: I have implemented the BMC optimization for the clients assigned to me. | F25: Closed | G25: 2026-04-22
A26: IT-3004277 | B26: Copy data from QC hdfs to Dev hdfs - Nile | C26: Hello Team : Need your help in copying GDF data for UHC cosmos for 202510 from QC to Dev and update permissioning. Please find below details Source path: /dataingestionqc/unrestricted/18-uhc-cosmos/Processed/GDF/claims/medical/postcheck/202510_1/ Target path (new): /dataingestiondev/unrestricted/18-*/Processed/GDF/claims/medical/postcheck/ Please do reach out to me in case of any questions. Thanks. | D26: Hi Prasad, Nirav Data Copied please verify hdfs dfs -cp /dataingestionqc/unrestricted/18-uhc-cosmos/Processed/GDF/claims/medical/postcheck/202510_1 /dataingestiondev/unrestricted/18-uhc-cosmos/Processed/GDF/claims/medical/postcheck hdfs dfs -chown -R svcddataunrestricted /dataingestiondev/unrestricted/18-uhc-cosmos/Processed/GDF/claims/medical/postcheck/ hdfs dfs -chgrp -R devunrestricted /dataingestiondev/unrestricted/18-uhc-cosmos/Processed/GDF/claims/medical/postcheck/ hdfs dfs -chmod -R 770 /dataingestiondev/unrestricted/18-uhc-cosmos/Processed/GDF/claims/medical/postcheck/ | E26: Data Copied | F26: Closed | G26: 2026-04-21
A27: IT-3004101 | B27: Error when running Humana BMC pipeline: trigger_bmc_workflow_CHC_HUMANA_MTH_DATALOADMEMBER_NILE_monthly | C27: Hi Nile PS Triage Team, When I press the execute button for the pipeline above, it immediately throws an error (snapshot). Would you mind taking a look? Thank you melly | D27: There is an issue in the precheck conditions, Modified and published the pipeline version v1.2 Also, updated the pipeline with latest precheck condition and removed unwanted parameters from pipeline. Pipeline changed to EDA and subscriber enabled. BMC triggered for 202604 Thanks. | E27: Pipeline processed successfully. | F27: Closed | G27: 2026-04-21
A28: IT-3003394 | B28: Medical Codes Library Document Submission | C28: Please add the attached table (DX Code Laterality Table) to the Medical Codes Library (MCL). Table is needed for Spotcheck content logic. | D28: DX Code Laterality Table.xlsx (1.39 MB) Hi Kamsetty, Sravani . This is a new table and will require a new pipeline. The DDL for this table is: CREATE TABLE [dbo] . [DxCodeLaterality] ( [DiagCode] [varchar] (10) NULL, [Category] [varchar] (300) NULL, [SubCategory] [varchar] (300) NULL, [Description] [varchar] (1000) NULL, [Source] [varchar] (500) NULL, [Laterality] [varchar] (20) NULL, [LastUpdateUser] [varchar] (100) NULL, [SFileDate] [smalldatetime] NULL, [SFilename] [varchar] (100) NULL, [AutoId] [int] IDENTITY(1,1) NOT NULL ) The source file has been saved to this location: Y:\Ftp\B2B\MCL-NILE\DxCodeLaterality\2026-04-01\DX Code Laterality Table.xlsx Per requestor, the data should be loaded in Append mode. Please let me know if you have any questions. Thanks. Mike Hi Deynarian, Michael , Thanks for the info. I started working on the new pipeline and all the required configurations in nile. Thanks. Hi Deynarian, Michael , Data has been loaded to table. Could you verify and confirm please. hello Kamsetty, Sravani . I have reviewed the table and it looks good. Thank you for getting this done so quickly! You can close this ticket. Mike Hi Deynarian, Michael , Migrated all the required configurations to production. Closing the ticket. | E28: All the required configurations are completed and tested in dev environment. Mike validated and confirmed to close the ticket. Migrated all the configs to production. | F28: Closed | G28: 2026-04-21
A29: IT-3002267 | B29: [Aetna-Trad-SCM]-Update prechecks for BMC and publish all the child pipelines. | C29: Update precheck with pipeline version as latest and remove all the unnecessary parameters from the pipeline. Publish all the child pipelines and modify subscribe BMC pipeline versions to latest. | D29: BMC Pipeline prechecks conditions for pipeline version is updated to latest for all the 78 pipeline ID's. Published all the 78 child pipelines. Published and scheduled the latest BMC version pipeline. FYI: trigger_bmc_workflow_CHC_AETNA_WKY_SCM_NILE Version: V1.3 | E29: BMC Pipeline prechecks conditions for pipeline version is updated to latest. Published and scheduled the latest BMC version pipeline. FYI: trigger_bmc_workflow_CHC_AETNA_WKY_SCM_NILE Version: V1.3 | F29: Closed | G29: 2026-04-20
A30: IT-3001908 | B30: BCBS_AL COMM - Suspend Pharmacy pipeline | C30: Hello, Please shut down BCBS_AL COMM Pharmacy pipeline: prod - dm-bcbsalcomm-custom-actian_migration_pharmacy Because the client will no longer be sending this file. Thank you | D30: Adding this email screenshot as a proof of approval by Director of Audit Ops, Rx - Paul Saxon, stating that the Pharmacy file would not be required to complete the audit. dm-bcbsalcomm-custom-actian_migration_pharmacy pipelines has been suspended and the rest of the files have been ingested. | E30: dm-bcbsalcomm-custom-actian_migration_pharmacy pipelines have been suspended and the rest of the files have been ingested. | F30: Closed | G30: 2026-04-20
A31: IT-3001338 | B31: Copy files From Nile Prod Raw path to Nile QC Raw path - UHC-CSP | C31: Hi Team, Could you please copy all the data for the date given below from the Nile PROD raw path to the Nile QC raw path? 20260412 Nile PROD RAW PATH (Source): /dataingestionprod/raw/restricted/19-uhc-csp Nile QC RAW PATH (Target): /dataingestionqc/raw/restricted/19-uhc-csp Once copied to QC, the owner should be set to "svcpnilediqcraw" and group should be set to "qcunrestricted" and permissions should be 750. | D31: Hi Pati, Jagadeesh Chandra Files copied please verify | E31: Files Copied | F31: Closed | G31: 2026-04-20
A32: IT-3001212 | B32: Copy files From Nile Prod Raw path to Nile QC Raw path - Aetna Trad | C32: Hi Team, Could you please copy the below mentioned files from the Nile PROD location to the Nile QC location? for the last week files, 04/12/2026 to latest. This request is critical as we have early communicated with prod support team. Nile PROD RAW PATH (Source): /dataingestionprod/raw/unrestricted/5-aetna-traditional Nile Dev RAW PATH (Target): /dataingestionqc/raw/unrestricted/5-aetna-traditional Once copied to QC folder, the owner should be set to "svcpnilediqcraw" and group should be set to "qcunrestricted" and permissions should be 75 | D32: Hi Shivalingu, Naveen Files copied please verify Thanks Satish Devatha | E32: Files Copied | F32: Closed | G32: 2026-04-20
A33: IT-2999879 | B33: Peer review for BMC workflow pipelines | C33: The above pipelines need to be verified. | D33: I have to check this ticket now. I have reviewed the bmc pipelines. | E33: I have reviewed the bmc pipelines. | F33: Closed | G33: 2026-04-20
A34: IT-2999839 | B34: Updating the pre-checks for the BMC workflow pipelines. | C34: Updating the pre-checks to use the pipeline version as “Latest” instead of specific versions. This ensures that any pipelines with modifications and newly published versions will automatically be picked up and considered in the workflow going forward. | E34: Updated all prechecks to the **Latest** version for the pipelines, published them, verified that all respective child pipelines are published, and proceeded with scheduling. | F34: Closed | G34: 2026-04-20
A35: IT-2999102 | B35: WELEX - History PROF & INST. files failed - 04/18/2026 | C35: Hi Nile Team, We have received below welex test files and failed at our end, because of sequence issue. The sequence number '230' are already used for mentioned files "welex_test_ophistory_incoming_1TST2.04-11-2026_0644"& "welex_test_history_incoming_1TST2.04-11-2026_0643" Please check with client and resend files with next available sequence numbers. File : welex_test_ophistory_incoming_1TST2.04-18-2026_1925 QA Status : FAILED Reason : The file has already been processed or it is out-of-sequence. WELEX|H|230|20260418|890198|R TRAILER|890198|20260418|161828 File : welex_test_history_incoming_1TST2.04-18-2026_2005 QA Status : FAILED Reason : The file has already been processed or it is out-of-sequence. WELEX|H|230|20260418|2204215|R TRAILER|2204215|20260418|154308 | D35: Hi Gudala, Kumaraswamy We have requested client to send the replacement file. Email ref: Requesting replacement file for Wellmark QC test tba file we haven't heard anything yet from the client so, we have again sent a follow up email to the client. | F35: Awaiting User Info | G35: 2026-04-18
A36: IT-2995627 | B36: adding 2 email list for HCSC and UHC Cirrus pipeline | C36: team, would you please help add EDM_RCA_UHC_CIRRUS@cotiviti.com to uhc cirrus nile ingestion failure email notification would you please help add EDM_RCA_HCSC@cotiviti.com to HCSC nile ingestion failure email notification Thanks | D36: Hi Sravani, Can we add UHC Cirrus and hcsc-hcsc client feeds with these 4 kinds of emails: Unmatched raw counts Data Drop File came late BMC trigger not running.. Unmatched caqh raw data count - 20260404_1 - prod - dm-excellus-actian_migration_caqh.msg prod - Cannot kick off bmc workflow CHC_UHC_COSMOS_PROVIDER_INCREMENTAL_NILE for ingestion period 20260428-1.msg Late Client File Notification - prod - Kaiser - WA - Kaiser-WA-Actian-2.msg Data metric percentage drop hits threshold 202603 - prod - dm-humana-hdap-actian_migration_MEDCLM_RAW_AMBULANCE.msg Sravani, I attached the example of the emails from other clients.. Hope this helps, thanks! melly Hi, As per the current configuration, Nile sends email notifications for BMC success events and threshold percentage drops for certain clients. If EDM requires failure notifications, there is a parameter (tech_email_dl) that triggers alerts for every event—such as pipeline start, pipeline end, and failures whenever a pipeline run fails as per the schedule. However, enabling this may lead to excessive notifications and potential confusion between Nile and EDM alerts. This likely needs further discussion. Jani and Krishna are currently looking into it. | F36: On Hold | G36: 2026-04-16
A37: IT-2994792 | B37: Decomission HAMP EPICTAPESTRY PPM | C37: Decomission HAMP EPICTAPESTRY PPM | D37: RE_ DAILY_ Missing File_ HAMP TBA professional File not received (20260405).msg | E37: Removed the pipeline and spoolers from the Nile application and tracker. | F37: Closed | G37: 2026-04-16
A38: IT-2993542 | B38: Update " SpecialtyPharmacyProviders" Table in MCL | C38: · Please create MCL table " SpecialtyPharmacyProviders " using the attached Excel table. Updates to be provided by ERT (full replace monthly). Who will be the user of this data? This table supports our next gen solution SpotCheck – We will need this table to refine data output for NPI Pharmacy Providers. Can you give a quick description of the table (what this table is about)? The values within the table depict NPI of pharmacy providers, along with their Provider Organization Name (Legal Business Name), Provider Business Practice Location Address City Name and Provider Business Practice Location Address State Name. Would you share with us what the background is for this request (e.g. How are these tables going to be used the users, reports, processes, etc)? This table will be used to support next gen content for SpotCheck. It will be a central location to house all Specialty Pharmacy Providers. How would this data be provided to the Nile Production Support team going forward? We will set up an monthly cadence with ERT to have them review the policy for any changes and deliver updates. (Replace) Will the files be provided to us or should we access/retrieve the data ourselves? Provided by ERT If the files will be given for us, will the format be consistent from delivery to delivery? Yes What will be the frequency/cadence of these files? Monthly | D38: SpecialtyPharmacyProviders.xlsx (4.73 MB) Hello Nile Team. This table and it's pipeline already exist. Table Name: GlobalHCCnlyMedicalCodesLibrary.dbo.SpecialtyPharmacyProviders Pipeline: dm-mcl-mcl-actian_migration_specialty_pharmacy_provider Source file has been saved here: Y:\Ftp\B2B\MCL-NILE\SpecialtyPharmacyProviders\2026-04-01\SpecialtyPharmacyProviders.xlsx Thanks. Mike Hello Kamsetty, Sravani I have reviewed the SQL table and the data looks good. You can close the ticket. Thanks for getting this done so quickly. Mike Thanks for the confirmation Mike. | E38: File processed successfully | F38: Closed | G38: 2026-04-16
A39: IT-2992309 | B39: Urgent Request: The Kaiser team is missing the latest Dataload which should have a max claim_paid_date of 03/27/2026 | C39: The Kaiser team is missing the latest Dataload which should have a max claim_paid_date of 03-27-2026. Please check the kaiser_ark_denorm in Impala which drives the data in Datameer. The max claim_paid_date at the moment is 03-10-2026. The team requests the issue to be resolved urgently as the missing spend is needed to meet the monthly budget. Screenshot attached. | D39: Closing. Per Melly S., should be in Nile Onboarding team. Not sure if IT-XXXXX tickets is the right forum for these tickets. Sajjan is working with operations to get this resolved. per comment: 15/Apr/26 5:14 PM EDT | F39: Cancelled | G39: 2026-04-15
A40: IT-2989822 | B40: Please add Aetna ASH into Master Tracking Sheet | C40: Hi Jani, Would you mind adding Aetna ASH entries? I think we had a transition meeting on March 26th. Thx so much Jani melly | D40: Nile_Production_Onboarding_pipelines.xlsx https://cotiviti.sharepoint.com/:x:/r/sites/ingestionandarchitecture/_layouts/15/Doc.aspx?sourcedoc=%7B50F60441-19D4-422B-818B-848FCBF1E79C%7D&file=Nile_Production_Onboarding_pipelines.xlsx&action=default&mobileredirect=true&CID=2D2CD604-3CDA-4CB4-A86B-18694490E41C&wdLOR=c3699C2E8-30C6-4651-AE59-49A331CD80CD | E40: Details recorded in a sheet | F40: Closed | G40: 2026-04-14
A41: IT-2988716 | B41: ARD-Prod Apr - 2026 Humana Retro Process | C41: ARD-Prod Apr - 2026 Humana Retro Process | D41: Received Cotiviti Global Exclusion report for 202604. prepared below 3 files using the Exclusion Report. Provider_Exclusions_202604.txt Taxgroup_Exclusions_202604.txt Clinical_Path_Provider_Exclusions_202604.txt Updated the Properties file and ran the job Currently job is running job: 4774573-260417210742368-oozie-oozi-W https://usapardhdpm03.cotiviti.com:8888/hue/jobbrowser#!id=4774573-260417210742368-oozie-oozi-W Humana job completed for 202604. Created Retro TBA files and uploaded to T1 server for processing Raised Ticket to PC Team. https://jiraet.cotiviti.com/plugins/servlet/desk/portal/7/IT-3002276 updated param file. Generated files to Finance and send email to respective members Process complete. | E41: Generated files to Finance and send email to respective members Process complete. | F41: Closed | G41: 2026-04-14
A42: IT-2988711 | B42: ARD-Prod: Run the UhCsp dups pipeline for Apr - 2026 (pulling Mar - 2026 data) RCA Job | C42: ARD-Prod: Run the UhCsp dups pipeline for Apr - 2026 (pulling Mar - 2026 data) RCA Job | D42: Step 1 Updated the below parameters LoadDate=20260420 Min_Paid_Date=2026-03-01 Max_Paid_Date=2026-03-31 Script path in Bitbucket : RCA_Workflows/UHC-CT/Refine & Denorm Workflow/ updated the Properties file. Refine_And_Denorm_UHC_Data.properties Step 2 And ran the below script path : /home/svcdatameersqoop/workflow/refine_and_denorm/UHC-CT Script : oozie job -oozie https://usapardhdpm04.cotiviti.com:11101/oozie/ -config /home/svcdatameersqoop/workflow/refine_and_denorm/UHC-CT/Refine_And_Denorm_UHC_Data.properties -run Step 3 Received email Currently job is running job: 4774294-260417210649579-oozie-oozi-W Step 4 Job Completed QA checks are done. Send email to respective members | E42: Step 4 Job Completed QA checks are done. Send email to respective members | F42: Closed | G42: 2026-04-14
A43: IT-2988581 | B43: Data Copy Request | C43: Hello Devatha, Satish , Kindly copy the Presbyterian HRP history files for the past two months (February and March). Thank you. | D43: Files are copied | E43: Files are copied | F43: Closed | G43: 2026-04-14
A44: IT-2988483 | B44: Request to ingest Aetna CAQH file -COB Smart Cotoviti 040426.zip | C44: Hello Nile team , Aetna has sent the weekly CAQH file; however, there appears to be a spelling error in the filename: COB Smart Cotoviti 040426.zip . Please proceed with ingesting the file, and we will contact the client to inform them of the misspelled filename. Thanks, Teena. | D44: Edited 3 spoolers and pipelines to process the new filename pattern. Vandanath, Teena confirmed that the files have been ingested successfully | E44: spoolers were changed to allow the misspelled file name pattern same with the pipeline | F44: Closed | G44: 2026-04-14
A45: IT-2988285 | B45: Peer review for oscar - homegrown | C45: Reviewed the Oscar homegrown data against the old dataset and the runs using the new PPM template, validation was completed with Puchakayala, Ranadeep and everything looks good. We are ready to proceed to production. | E45: Reviewed and scheduled | F45: Closed | G45: 2026-04-14
A46: IT-2986640 | B46: BCBSNJ Nasco - Delete the file from raw folder for 20260217 date | C46: Hello Team, For BCBSNJ NASCO — while we were testing the script, the file was spooled by mistake. Could you please help us delete the file from the raw folder for the 20260217 ingestion date with the below file name pattern? File name pattern to delete: hznhp_ophistory_incoming_001_20260217020717.asc | D46: Hi Shaik, Parveena Removed the file from raw path Thanks Satish Devatha | E46: Removed the file from raw path | F46: Closed | G46: 2026-04-13
A47: IT-2986624 | B47: Copy files From Nile Prod Raw path to Nile QC Raw path - Aetna Trad | C47: Hi Team, Could you please copy the below mentioned files from the Nile PROD location to the Nile QC location? for the last week files, 04/05/2026 to latest. This request is critical as we have early communicated with prod support team. Nile PROD RAW PATH (Source): /dataingestionprod/raw/unrestricted/5-aetna-traditional Nile Dev RAW PATH (Target): /dataingestionqc/raw/unrestricted/5-aetna-traditional Once copied to QC folder, the owner should be set to "svcpnilediqcraw" and group should be set to "qcunrestricted" and permissions should be 75 | D47: Hi Shivalingu, Naveen Files copied. Please verify Thanks Satish Devatha | E47: Files Copied | F47: Closed | G47: 2026-04-13
A48: IT-2986524 | B48: Copy files From Nile Prod Raw path to Nile QC Raw path - UHC-CSP | C48: Hi Team, Could you please copy all the data for the date given below from the Nile PROD raw path to the Nile QC raw path? 20260405 Nile PROD RAW PATH (Source): /dataingestionprod/raw/restricted/19-uhc-csp Nile QC RAW PATH (Target): /dataingestionqc/raw/restricted/19-uhc-csp Once copied to QC, the owner should be set to "svcpnilediqcraw" and group should be set to "qcunrestricted" and permissions should be 750. | D48: Hi Pati, Jagadeesh Chandra Files copied. please verify. Thanks | E48: Files Copied | F48: Closed | G48: 2026-04-13
A49: IT-2985806 | B49: Testing and promoting oscar - homegrown pipelines to prod using the new PPM template. | C49: Validating and deploying pipelines with the new PPM template to ensure proper functionality and compatibility. client - oscar - homegrown | D49: Subtask needed to be validated. The lean ingestion pipelines are now live in production. | E49: Lean_ingestion pipelines sent live. | F49: Closed | G49: 2026-04-13
A50: IT-2985721 | B50: Update the tracker with the newly deployed History pipelines for Premera and Geisinger that are now live in production. | C50: Hello Jani, Shaik , The History pipelines for Premera and Geisinger have been successfully deployed to production. Please update the tracker with the new pipelines. Details of the old and new pipelines are provided below. Premera (Slim_Refactoring) ppm-premera-bluecross-history_professional_claims_GDF2_2_CDF2_2_Slim_Refactoring - 2023-02-26-18587740 ppm-premera-bluecross-history_institutional_claims_GDF2_2CDF2_2_Slim_Refactoring - 2023-02-28-119555472 Premera (lean_ingestion & reports) ppm-premera-bluecross-history_professional_claims_GDF2_2_CDF2_2_lean_ingestion - 2026-03-30-102438457 ppm-premera-bluecross-history_professional_claims_GDF2_2_CDF2_2_reports - 2026-04-03-32578452 ppm-premera-bluecross-history_institutional_claims_GDF2_2_CDF2_2_lean_ingestion - 2026-03-30-91183910 ppm-premera-bluecross-history_institutional_claims_GDF2_2_CDF2_2_reports - 2026-04-03-31797856 Geisinger (Slim_Refactoring) ppm-geisinger-facets-history_professional_claims_GDF2_3_CDF2_3_Slim_Refactoring - 2023-02-26-19439618 ppm-geisinger-facets-history_institutional_claims_GDF2_3_CDF2_3_Slim_Refactoring - 2023-03-02-14385441 Geisinger (lean_ingestion reports) ppm-geisinger-facets-history_professional_claims_GDF2_3_CDF2_3_lean_ingestion - 2026-03-02-115254679 ppm-geisinger-facets-history_professional_claims_GDF2_3_CDF2_3_reports - 2026-03-04-128113272 ppm-geisinger-facets-history_institutional_claims_GDF2_3_CDF2_3_lean_ingestion - 2026-03-02-115056816 ppm-geisinger-facets-history_institutional_claims_GDF2_3_CDF2_3_reports - 2026-03-04-128204568 Thank You | E50: Details recorded accordingly. | F50: Closed | G50: 2026-04-13
A51: IT-2982952 | B51: Request for presbyterian - hrp Monthly improvement | C51: Last month, we encountered an issue with the Presbyterian HRP monthly process. The pipeline ran on March 7th with only one file ( rccv file prsby_inpatient_incoming_2r ), which turned out to be incomplete and contained only the first week of data. As a result, we had to reach out to PC and CRS to remove the file, and CRS needed to communicate with the client after submitting a corrected file. This created additional rework and client impact. To prevent this issue from happening again, I recommend implementing a weekly validation check to ensure all expected files are received before the pipeline runs. This approach has already been successfully implemented in other pipelines that depend on weekly file deliveries. I will attach a screenshot as an example to demonstrate how those pipelines are configured to wait for all required weekly files before processing. | D51: I have started working on it and am currently testing in the lower environment. I will keep you posted on the updates. Hello Kabeya, Joel , Upon your request, I have improved the Presbyterian–HRP monthly history institutional claims pipeline, which now provides weekly data validations. Please monitor the pipeline in the next run and let me know if any further changes are required. Providing the pipeline details below: pipeline name: rccv-presbyterian-hrp-history_institutional_claims_processed_GDF2_8_CDF2_8 pipeline ID: 2024-01-05-11460210 Version: V1.2 A draft version of the improved pipelines has been deployed to production and requires monitoring for the next run. Hello Kabeya, Joel , Published and scheduled the pipeline in production. Kindly monitor for the next run and let me know if any changes required. | E51: Introduced a weekly data validation module to enhance visibility into processed files and those pending processing. | F51: Closed | G51: 2026-04-10
A52: IT-2982706 | B52: trigger_bmc_workflow-uhc-unet_monthly_DataLoads_V2 | C52: trigger_bmc is not recognizing these pipelines as completed, although they are completed. there is a new version of both of these pipeliens with DATASPOOLER REQUIRED = NO? error_list= dm-uhc-unet-actian_migration_claimsfifac: Missing data dm-uhc-unet-actian_migration_claimsfinon: Missing data | D52: changed and published pipelines to get picked up by the trigger pipeline changed spooler required to Y for all pipelines also changed config to show pre-checks using LATEST version created and scheduled trigger BMC reassigning to Easley, Keaton | F52: In Progress (HD1) | G52: 2026-04-10
A53: IT-2982622 | B53: trigger_bmc_workflow-uhc-unet_monthly_Incremental_Dataload | C53: trigger_bmc_workflow-uhc-unet_monthly_Incremental_Dataload has not ran since December. not sure the issue here | D53: schedule a call with Dongol, Priya and Easley, Keaton to discuss this pipeline and we may need to recode it needed to meet with Dongol, Priya and Easley, Keaton to revisit BMC for this client created 2 pipelines trigger_bmc_workflow-uhc-unet_monthly_Incremental_Dataload_1st trigger_bmc_workflow-uhc-unet_monthly_Incremental_Dataload_2nd3rd files have been reviewed, published, and scheduled | E53: need to create 2 new BMC pipelines. One for the first run and the second one is for the 2nd and 3rd run of each month. | F53: Closed | G53: 2026-04-10
A54: IT-2982545 | B54: trigger_bmc_workflow-uhc-unet_monthly_UnetAso | C54: all pipelines are completed successfully error_list=dm-uhc-unet-actian_migration_claimsasophy: Missing data, can_proceed=0 | D54: Created a new version to set spooler YN to Y need to publish the pipelines setup config pre checks to show latest and make sure subscribr is set on the BMC trigger assigning to Easley, Keaton | F54: In Progress (HD1) | G54: 2026-04-10
A55: IT-2981879 | B55: Production Transition - Aetna - MR | C55: Production Transition - Aetna - MR | D55: Waiting for documents | F55: On Hold | G55: 2026-04-10
A56: IT-2981131 | B56: Need a copy of data from Nile PROD to Nile Dev Location | C56: Hi Team, Could you please copy the data from the Nile PROD location to the Nile Dev location? And can you set the owner to "svcddataunrestricted" and the group to "dataunrestricted". /dataingestionprod/unrestricted/198-bcbswy-oscar/Processed/GDF/member/member/ → /dataingestiondev/unrestricted/189-bcbswy-oscar/Processed/GDF/member/member/ 20260324 20260331 /dataingestionprod/unrestricted/198-bcbswy-oscar/Processed/GDF/member/address/ → /dataingestiondev/unrestricted/189-bcbswy-oscar/Processed/GDF/member/address/ 20260324 20260331 /dataingestionprod/unrestricted/198-bcbswy-oscar/Processed/GDF/member/enrollment/ → /dataingestiondev/unrestricted/189-bcbswy-oscar/Processed/GDF/member/enrollment/ 20260324 20260331 /dataingestionprod/unrestricted/198-bcbswy-oscar/Processed/GDF/member/cob/ → /dataingestiondev/unrestricted/189-bcbswy-oscar/Processed/GDF/member/cob/ 20260324 20260331 /dataingestionprod/unrestricted/198-bcbswy-oscar/Processed/GDF/provider/provider/ → /dataingestiondev/unrestricted/189-bcbswy-oscar/Processed/GDF/provider/provider/ 20260324 20260331 /dataingestionprod/unrestricted/198-bcbswy-oscar/Processed/GDF/provider/address/ → /dataingestiondev/unrestricted/189-bcbswy-oscar/Processed/GDF/provider/address/ 20260324 20260331 /dataingestionprod/unrestricted/198-bcbswy-oscar/Processed/GDF/provider/network/ → /dataingestiondev/unrestricted/189-bcbswy-oscar/Processed/GDF/provider/network/ 20260324 20260331 /dataingestionprod/unrestricted/198-bcbswy-oscar/Processed/GDF/medicalclaims/medical/postcheck/ → /dataingestiondev/unrestricted/189-bcbswy-oscar/Processed/GDF/medicalclaims/medical/postcheck/ 20260324 20260331 /dataingestionprod/unrestricted/198-bcbswy-oscar/Processed/GDF/pharmacyclaims/pharmacy/postcheck/ → /dataingestiondev/unrestricted/189-bcbswy-oscar/Processed/GDF/pharmacyclaims/pharmacy/postcheck/ 20260324 20260331 | D56: I ran the following commands and verified the data matches. Closing this ticket. hdfs dfs -ls /dataingestionprod/unrestricted/198-bcbswy-oscar/Processed/GDF/member/member/{20260324,20260331} hdfs dfs -ls /dataingestiondev/unrestricted/189-bcbswy-oscar/Processed/GDF/member/member/{20260324,20260331} hdfs dfs -ls /dataingestionprod/unrestricted/198-bcbswy-oscar/Processed/GDF/member/address/{20260324,20260331} hdfs dfs -ls /dataingestiondev/unrestricted/189-bcbswy-oscar/Processed/GDF/member/address/{20260324,20260331} hdfs dfs -ls /dataingestionprod/unrestricted/198-bcbswy-oscar/Processed/GDF/member/enrollment/{20260324,20260331} hdfs dfs -ls /dataingestiondev/unrestricted/189-bcbswy-oscar/Processed/GDF/member/enrollment/{20260324,20260331} hdfs dfs -ls /dataingestionprod/unrestricted/198-bcbswy-oscar/Processed/GDF/member/cob/{20260324,20260331} hdfs dfs -ls /dataingestiondev/unrestricted/189-bcbswy-oscar/Processed/GDF/member/cob/{20260324,20260331} hdfs dfs -ls /dataingestionprod/unrestricted/198-bcbswy-oscar/Processed/GDF/provider/provider/{20260324,20260331} hdfs dfs -ls /dataingestiondev/unrestricted/189-bcbswy-oscar/Processed/GDF/provider/provider/{20260324,20260331} hdfs dfs -ls /dataingestionprod/unrestricted/198-bcbswy-oscar/Processed/GDF/provider/address/{20260324,20260331} hdfs dfs -ls /dataingestiondev/unrestricted/189-bcbswy-oscar/Processed/GDF/provider/address/{20260324,20260331} hdfs dfs -ls /dataingestionprod/unrestricted/198-bcbswy-oscar/Processed/GDF/provider/network/{20260324,20260331} hdfs dfs -ls /dataingestiondev/unrestricted/189-bcbswy-oscar/Processed/GDF/provider/network/{20260324,20260331} hdfs dfs -ls /dataingestionprod/unrestricted/198-bcbswy-oscar/Processed/GDF/medicalclaims/medical/postcheck/{20260324,20260331} hdfs dfs -ls /dataingestiondev/unrestricted/189-bcbswy-oscar/Processed/GDF/medicalclaims/medical/postcheck/{20260324,20260331} hdfs dfs -ls /dataingestionprod/unrestricted/198-bcbswy-oscar/Processed/GDF/pharmacyclaims/pharmacy/postcheck/{20260324,20260331} hdfs dfs -ls /dataingestiondev/unrestricted/189-bcbswy-oscar/Processed/GDF/pharmacyclaims/pharmacy/postcheck/{20260324,20260331} hadoop distcp /dataingestionprod/unrestricted/198-bcbswy-oscar/Processed/GDF/member/member/{20260324,20260331} /dataingestiondev/unrestricted/189-bcbswy-oscar/Processed/GDF/member/member/ hadoop distcp /dataingestionprod/unrestricted/198-bcbswy-oscar/Processed/GDF/member/address/{20260324,20260331} /dataingestiondev/unrestricted/189-bcbswy-oscar/Processed/GDF/member/address/ hadoop distcp /dataingestionprod/unrestricted/198-bcbswy-oscar/Processed/GDF/member/enrollment/{20260324,20260331} /dataingestiondev/unrestricted/189-bcbswy-oscar/Processed/GDF/member/enrollment/ hadoop distcp /dataingestionprod/unrestricted/198-bcbswy-oscar/Processed/GDF/member/cob/{20260324,20260331} /dataingestiondev/unrestricted/189-bcbswy-oscar/Processed/GDF/member/cob/ hadoop distcp /dataingestionprod/unrestricted/198-bcbswy-oscar/Processed/GDF/provider/provider/{20260324,20260331} /dataingestiondev/unrestricted/189-bcbswy-oscar/Processed/GDF/provider/provider/ hadoop distcp /dataingestionprod/unrestricted/198-bcbswy-oscar/Processed/GDF/provider/address/{20260324,20260331} /dataingestiondev/unrestricted/189-bcbswy-oscar/Processed/GDF/provider/address/ hadoop distcp /dataingestionprod/unrestricted/198-bcbswy-oscar/Processed/GDF/provider/network/{20260324,20260331} /dataingestiondev/unrestricted/189-bcbswy-oscar/Processed/GDF/provider/network/ hadoop distcp /dataingestionprod/unrestricted/198-bcbswy-oscar/Processed/GDF/medicalclaims/medical/postcheck/{20260324,20260331} /dataingestiondev/unrestricted/189-bcbswy-oscar/Processed/GDF/medicalclaims/medical/postcheck/ hadoop distcp /dataingestionprod/unrestricted/198-bcbswy-oscar/Processed/GDF/pharmacyclaims/pharmacy/postcheck/{20260324,20260331} /dataingestiondev/unrestricted/189-bcbswy-oscar/Processed/GDF/pharmacyclaims/pharmacy/postcheck/ hdfs dfs -chown -R svcddataunrestricted /dataingestiondev/unrestricted/189-bcbswy-oscar hdfs dfs -chgrp -R devunrestricted /dataingestiondev/unrestricted/189-bcbswy-oscar hdfs dfs -chmod -R 770 /dataingestiondev/unrestricted/189-bcbswy-oscar hdfs dfs -du /dataingestionprod/unrestricted/198-bcbswy-oscar/Processed/GDF/member/member/{20260324,20260331} hdfs dfs -du /dataingestiondev/unrestricted/189-bcbswy-oscar/Processed/GDF/member/member/{20260324,20260331} hdfs dfs -du /dataingestionprod/unrestricted/198-bcbswy-oscar/Processed/GDF/member/address/{20260324,20260331} hdfs dfs -du /dataingestiondev/unrestricted/189-bcbswy-oscar/Processed/GDF/member/address/{20260324,20260331} hdfs dfs -du /dataingestionprod/unrestricted/198-bcbswy-oscar/Processed/GDF/member/enrollment/{20260324,20260331} hdfs dfs -du /dataingestiondev/unrestricted/189-bcbswy-oscar/Processed/GDF/member/enrollment/{20260324,20260331} hdfs dfs -du /dataingestionprod/unrestricted/198-bcbswy-oscar/Processed/GDF/member/cob/{20260324,20260331} hdfs dfs -du /dataingestiondev/unrestricted/189-bcbswy-oscar/Processed/GDF/member/cob/{20260324,20260331} hdfs dfs -du /dataingestionprod/unrestricted/198-bcbswy-oscar/Processed/GDF/provider/provider/{20260324,20260331} hdfs dfs -du /dataingestiondev/unrestricted/189-bcbswy-oscar/Processed/GDF/provider/provider/{20260324,20260331} hdfs dfs -du /dataingestionprod/unrestricted/198-bcbswy-oscar/Processed/GDF/provider/address/{20260324,20260331} hdfs dfs -du /dataingestiondev/unrestricted/189-bcbswy-oscar/Processed/GDF/provider/address/{20260324,20260331} hdfs dfs -du /dataingestionprod/unrestricted/198-bcbswy-oscar/Processed/GDF/provider/network/{20260324,20260331} hdfs dfs -du /dataingestiondev/unrestricted/189-bcbswy-oscar/Processed/GDF/provider/network/{20260324,20260331} hdfs dfs -du /dataingestionprod/unrestricted/198-bcbswy-oscar/Processed/GDF/medicalclaims/medical/postcheck/{20260324,20260331} hdfs dfs -du /dataingestiondev/unrestricted/189-bcbswy-oscar/Processed/GDF/medicalclaims/medical/postcheck/{20260324,20260331} hdfs dfs -du /dataingestionprod/unrestricted/198-bcbswy-oscar/Processed/GDF/pharmacyclaims/pharmacy/postcheck/{20260324,20260331} hdfs dfs -du /dataingestiondev/unrestricted/189-bcbswy-oscar/Processed/GDF/pharmacyclaims/pharmacy/postcheck/{20260324,20260331} | E56: data copied as requested and verified. | F56: Closed | G56: 2026-04-09
A57: IT-2980439 | B57: Created a runbook for Lean ingestion pipelines for Premera and Geisinger. | C57: Geisinger Facets_PPM_Lean_Ingestion_Run_Book.docx Premera BlueCross_PPM_Lean_Ingestion_Run_Book.docx | D57: Geisinger Facets_PPM_Lean_Ingestion_Run_Book.docx Premera BlueCross_PPM_Lean_Ingestion_Run_Book.docx | E57: Attached the run books in the comments. | F57: Closed | G57: 2026-04-09
A58: IT-2974191 | B58: BCBSND-OSCAR: fwa-BCBSND-OSCAR_member_GDF2_3 (ingestion date 3/11) | C58: Issue with pipeline name: fwa-BCBSND-OSCAR_member_GDF2_3 (ingestion date 3/11) Member file name: bcsnd_memberenrollment_incoming_20260311_1.txt.pgp File originally arrived 3/11/26. We tried to spool the replacement file on 3/30 but had issues with it. We need to know the following. 1.) If the replacement was good or not. 2.) If the replacement is not good, we need to know why so Melly can work with Jae- the CSM. Thank you On behalf of Melly. | D58: Created a new version fwa-BCBSND-OSCAR_member_GDF2_3 1.1 | E58: fixed and ingested files for 2026/03/11 need to schedule pipeline | F58: Closed | G58: 2026-04-06
A59: IT-2973653 | B59: DM and RCOB Layouts for Independence Blue Cross | C59: Hello, we need to conduct an OA analysis for Independence Blue Cross. We would like to use the DM and RCOB layout to get started. Will you please send these files to us? | D59: Hi Smith, Emily Shared the schema layouts Thanks Satish Devatha | E59: Shared the schema layouts | F59: Closed | G59: 2026-04-06
A60: IT-2973088 | B60: Copy files From Nile Prod Raw path to Nile QC Raw path - Aetna Trad | C60: Hi Team, Could you please copy the below mentioned files from the Nile PROD location to the Nile QC location? for the last week files, 03/29/2026 to latest. This request is critical as we have early communicated with prod support team. Nile PROD RAW PATH (Source): /dataingestionprod/raw/unrestricted/5-aetna-traditional Nile Dev RAW PATH (Target): /dataingestionqc/raw/unrestricted/5-aetna-traditional Once copied to QC folder, the owner should be set to "svcpnilediqcraw" and group should be set to "qcunrestricted" and permissions should be 75 | D60: Hi Shivalingu, Naveen Files are copied please verify | E60: Files Copied | F60: Closed | G60: 2026-04-06
A61: IT-2970242 | B61: BCBSLA PBM RCA Prod Transition Documents Review | C61: Please review the prod transition checklist documents for BCBSLA PBM RCA and let us know if any changes are needed. Creating this ticket as a placeholder. Will update ticket with document links once complete. | D61: Checklist: https://cotiviti.sharepoint.com/:w:/r/sites/EDMEngineeringTeam/_layouts/15/Doc.aspx?sourcedoc=%7B68F73DD7-1098-4012-B056-103531B4B33F%7D&file=BCBSLA_PBM_RCA_DataIngestion_Production_Job_Transition_Checklist.docx&action=default&mobileredirect=true Escalation Document: https://cotiviti.sharepoint.com/:x:/r/sites/EDMEngineeringTeam/_layouts/15/Doc.aspx?sourcedoc=%7B967D083E-45E9-470A-AEFE-B86F1E0781C4%7D&file=BCBSLA%20-%20Joint%20Data%20Escalation%20Plan%20Enterprise%20External%20APPROVED%20(3).xlsx&action=default&mobileredirect=true | E61: Transition completed. | F61: Closed | G61: 2026-04-03
A62: IT-2970071 | B62: please fix BCBS_MI-MedAdv BMC Pipeline | C62: please fix trigger_bmc_workflow-bcbs_mi_medadv_monthly bmc pipelines as it is not reflecting the latest child pipeline | D62: new pipeline created, scheduled pipeline, edited prechecks and made sure "pare" pipelines are all published | E62: Pipeline -- created a new version, changed to make pre checks work and made sure all calling pipelines are configured accordingly | F62: Closed | G62: 2026-04-03
A63: IT-2969877 | B63: Copy files From Nile Prod Raw path to Nile QC Raw path - UHC-CSP | C63: Hi Team, Could you please copy all the data for the date given below from the Nile PROD raw path to the Nile QC raw path? 20260322 Nile PROD RAW PATH (Source): /dataingestionprod/raw/restricted/19-uhc-csp Nile QC RAW PATH (Target): /dataingestionqc/raw/restricted/19-uhc-csp Once copied to QC, the owner should be set to "svcpnilediqcraw" and group should be set to "qcunrestricted" and permissions should be 750. | D63: ran the following commands and verified the data matches. closing ticket. hdfs dfs -ls /dataingestionprod/raw/restricted/19-uhc-csp/20260322 hdfs dfs -ls /dataingestionqc/raw/restricted/19-uhc-csp/20260322 hadoop distcp /dataingestionprod/raw/restricted/19-uhc-csp/20260322/* /dataingestionqc/raw/restricted/19-uhc-csp/20260322/ hdfs dfs -chown -R svcpnilediqcraw /dataingestionqc/raw/restricted/19-uhc-csp hdfs dfs -chgrp -R qcrestricted /dataingestionqc/raw/restricted/19-uhc-csp hdfs dfs -chmod -R 750 /dataingestionqc/raw/restricted/19-uhc-csp hdfs dfs -du /dataingestionprod/raw/restricted/19-uhc-csp/ | grep 20260322 hdfs dfs -du /dataingestionqc/raw/restricted/19-uhc-csp/ | grep 20260322 25474875641 76424626923 /dataingestionprod/raw/restricted/19-uhc-csp/20260322 [kevin.birney@usapnlhdpe01 ~] <PROD>$ hdfs dfs -du /dataingestionqc/raw/restricted/19-uhc-csp/ | grep 20260322 25481438669 76444316007 /dataingestionqc/raw/restricted/19-uhc-csp/20260322 | E63: all data copied as requested and verified. | F63: Closed | G63: 2026-04-03
A64: IT-2969243 | B64: Data copy Request | C64: Hello Devatha, Satish , I kindly request you to copy the latest ingestion-date data files for Premera history to the dev environment to test the pipelines built using the new PPM template. Thank You. | D64: Hi Karakavalasa, SriVarshini Data Copied hdfs dfs -cp /dataingestionprod/raw/unrestricted/109-premera-bluecross/20260401 /dataingestiondev/raw/unrestricted/109-premera-bluecross/ hdfs dfs -chown -R svcpniledidevraw /dataingestiondev/raw/unrestricted/109-premera-bluecross hdfs dfs -chgrp -R devunrestricted /dataingestiondev/raw/unrestricted/109-premera-bluecross hdfs dfs -chmod -R 750 /dataingestiondev/raw/unrestricted/109-premera-bluecross | E64: Data Copied | F64: Closed | G64: 2026-04-03
A65: IT-2969231 | B65: Skip Aetna Hrp Payment pipeline for 03/23 Data Date. | C65: Skip Aetna Hrp Payment pipeline for 03/23 Data Date. | E65: Ingestion Date Skipped 03/23. | F65: Closed | G65: 2026-04-03
A66: IT-2967657 | B66: Aetna MCD CAQH-Request to include new Region | C66: Hello Nile team , REF Ticket # [IT-2837485] Request to Ingest Aetna TRAD CAQH/HRP files to separate SQL tables - Service Desk Please include the below file naming convention to Aetna MCD dataset going forward. YYYYMMDD_1000_1775_COBReport. To the below: - Aetna MCD: - *1000_1007_COBReport *1000_1008_COBReport *1000_1009_COBReport *1000_1011_COBReport *1000_1015_COBReport *1000_1019_COBReport *1000_1021_COBReport *1000_1022_COBReport *1000_1023_COBReport *1000_1025_COBReport *1000_1006_COBReport *1000_1026_COBReport *1000_1027_COBReport *1000_1048_COBReport Thanks, Teena | D66: The new file has 95 columns – what is expected is 101 Hi Din , Can we tell if it's a particular field missing? If you can load the data to here, I can take a look: - [AetnaDataRawMCD] . [dbo] . [CAQH_OTHER] Thanks, Teena. CSM confirmed the below with the client: - "I received the following regarding the missing fields. Still waiting on a response regarding the changed fields. "Reason for the difference is because Aetna Ohio Rise did not implement with data validation as it was “Mental Health” membership only. Thus the data validation fields will not be present.” " We will probably need to ingest the fields as 'null' going forward, since client will not send them. Below are the fields affected: - scheduled a call as i need to present to Teena what we need to do Please see attached layout for the 1775 file . 1775.xlsx edited pipeline dm-aetna-mcd-actian_migration_caqh to include multiple schema Crated an entry in client- feeds and pipeline needs a new transformer to UNION the 2 files with different schemas output checked and reviwed by Vandanath, Teena | E66: new file pattern is now being saved after added to mcd files | F66: Closed | G66: 2026-04-02
A67: IT-2967594 | B67: Aetna MCD- Request to separate out the HEW files | C67: Hello Nile team, We received 2 files for Aetna MCD HEW and both files were ingested at the same time to the SQL table. The filenames seem to be merged and will need to separate them: - 'Louisiana HEW 1Q26.xlsx,Louisiana HEW 4Q25.xlsx' SQL table name:- AetnaDataRawMCD.dbo.HEW Thanks, Teena. | D67: 4Q25 file only reprocessing with 20260331 datadate. pipeline is running for 20260331 datadte for 4Q25 file. Nile processed both 4Q25 and 1Q26 files Thanks Satish Devatha | E67: Nile processed both 4Q25 and 1Q26 files | F67: Closed | G67: 2026-04-02
